Workbook
Name rq: Transport!$C:$C
Name tg: Transport!$F$192:$H$197

Sheet CADRAN
B1: VARIATIONS MENSUELLES | C1: PRODUCTIONS | J1: TRANSPORTS
C2: PRIMAIRE | D2: =Primaire!B4 -> Abattages contrôlés de viande | E2: =Primaire!B164 -> 2190.384 | F2: SECONDAIRE | G2: OR | H2: ='Secteur Secondaire'!J164 -> 1167.3686 | J2: AERIEN | K2: Mouvements d'aéronefs | L2: =Transport!$B$164 -> 2549 | M2: MARITIME | N2: EMBARQUEMENTS | O2: =+Transport!J163 -> 419.953
D3: flèche hausse | E3: =IF(Primaire!$B$2<0,0.5,0.49) -> 0.5 | G3: flèche hausse | H3: =IF('Secteur Secondaire'!$J$3<0,0.5,0.49) -> 0.5 | K3: flèche hausse | L3: =IF(Transport!$B$2<0,0.5,0.49) -> 0.5 | N3: flèche hausse | O3: =IF(Transport!$J$2<0,0.5,0.49) -> 0.49
D4: flèche baisse | E4: =IF(Primaire!$B$2>0,0.5,0.49) -> 0.49 | G4: flèche baisse | H4: =IF('Secteur Secondaire'!$J$3>0,0.5,0.49) -> 0.49 | K4: flèche baisse | L4: =IF(Transport!$B$2>0,0.5,0.49) -> 0.49 | N4: flèche baisse | O4: =IF(Transport!$J$2>0,0.5,0.49) -> 0.5
A5: ENVIRONNEMENT INTERNATIONAL | D5: Variation | E5: =Primaire!$B$2 -> -0.14275371 | G5: Variation | H5: ='Secteur Secondaire'!$J$3 -> -0.24958542 | K5: Variation | L5: =Transport!$B$2 -> -0.040300277 | N5: Variation | O5: =Transport!$J$2 -> 0.01865368
A6: Cours du baril | B6: ='Environnement International'!G163 -> 59.27 | G6: PHOSPHATE | H6: ='Secteur Secondaire'!C164 -> 132.524
A7: flèche hausse | B7: =IF('Environnement International'!$G$3<0,0.5,0.49) -> 0.49 | D7: =Primaire!C4 -> Pêche | E7: =Primaire!C164 -> 47975.904 | G7: flèche hausse | H7: =IF('Secteur Secondaire'!$C$3<0,0.5,0.49) -> 0.5 | K7: PASSAGERS | L7: =Transport!$C$164 -> 195624
A8: flèche baisse | B8: =IF('Environnement International'!$G$3>0,0.5,0.49) -> 0.5 | D8: flèche hausse | E8: =IF(Primaire!$C$2<0,0.5,0.49) -> 0.49 | G8: flèche baisse | H8: =IF('Secteur Secondaire'!$C$3>0,0.5,0.49) -> 0.49 | K8: flèche hausse | L8: =IF(Transport!$C$2<0,0.5,0.49) -> 0.49
A9: Variation | B9: ='Environnement International'!$G$3 -> 0.064508929 | D9: flèche baisse | E9: =IF(Primaire!$C$2>0,0.5,0.49) -> 0.5 | G9: Variation | H9: ='Secteur Secondaire'!$C$3 -> -0.061808271 | K9: flèche baisse | L9: =IF(Transport!$C$2>0,0.5,0.49) -> 0.5
D10: Variation | E10: =Primaire!$C$2 -> 0.10355542 | K10: Variation | L10: =Transport!$C$2 -> 0.024612402
N11: DEBARQUEMENTS | O11: =Transport!N163 -> 934.739
A12: ='[1]Environnement International'!B25 -> COURS EURO / DOLLAR USA | B12: ='Environnement International'!K163 -> 1.1416 | G12: CIMENT | H12: ='Secteur Secondaire'!R164 -> 559.47708 | K12: FRET | L12: =Transport!$G$164 -> 3040.38 | N12: flèche hausse | O12: =IF(Transport!$N$2<0,0.5,0.49) -> 0.5
A13: flèche hausse | B13: =IF('Environnement International'!$K$3<0,0.5,0.49) -> 0.49 | G13: flèche hausse | H13: =IF('Secteur Secondaire'!$R$3<0,0.5,0.49) -> 0.5 | K13: flèche hausse | L13: =IF(Transport!$G$2<0,0.5,0.49) -> 0.49 | N13: flèche baisse | O13: =IF(Transport!$N$2>0,0.5,0.49) -> 0.49
A14: flèche baisse | B14: =IF('Environnement International'!$K$3>0,0.5,0.49) -> 0.5 | G14: flèche baisse | H14: =IF('Secteur Secondaire'!$R$3>0,0.5,0.49) -> 0.49 | K14: flèche baisse | L14: =IF(Transport!$G$2>0,0.5,0.49) -> 0.5 | N14: Variation | O14: =Transport!$N$2 -> -0.20512644
A15: Variation | B15: ='Environnement International'!$K$3 -> 0.0024767273 | G15: Variation | H15: ='Secteur Secondaire'!$R$3 -> -0.048948199 | K15: Variation | L15: =Transport!$G$2 -> 0.14355908
A16: FINANCES PUBLIQUES | C16: INDICES DU CHIFFRE D'AFFAIRES BRUTS ET CORRIGES DES VARIATIONS SAISONNIERES | J16: COMMERCE EXTERIEUR
A17: (en milliards de FCFA) | B17: Janv | C17: PRIMAIRE | F17: SECONDAIRE | J17: IMPORTATIONS | K17: RIZ | L17: ='Commerce Extérieur'!B164 -> 112.59619 | M17: EXPORTATIONS | N17: PRODUITS ARACHIDIERS | O17: ='Commerce Extérieur'!F164 -> 30.70379
A18: Réalisations 2026 | B18: =graphes!O5 -> 339.34355 | K18: flèche hausse | L18: =IF('Commerce Extérieur'!$B$3<0,0.5,0.49) -> 0.5 | N18: flèche hausse | O18: =IF('Commerce Extérieur'!$F$3<0,0.5,0.49) -> 0.5
A19: Situation 2025 | B19: =graphes!O6 -> 304.16192 | K19: flèche baisse | L19: =IF('Commerce Extérieur'!$B$3>0,0.5,0.49) -> 0.49 | N19: flèche baisse | O19: =IF('Commerce Extérieur'!$F$3>0,0.5,0.49) -> 0.49
A20: Plus ou moins value | B20: =B18-B19 -> 35.181632 | K20: Variation | L20: ='Commerce Extérieur'!$B$3 -> -0.036034591 | N20: Variation | O20: ='Commerce Extérieur'!$F$3 -> -1
A21: flèche hausse | B21: =IF(B18-B19>0,0.5,0.49) -> 0.5
A22: flèche baisse | B22: =IF(B18-B19<0,0.5,0.49) -> 0.49 | K22: PETROLE BRUT | L22: ='Commerce Extérieur'!D164 -> 128.13635
K23: flèche hausse | L23: =IF('Commerce Extérieur'!$D$3<0,0.5,0.49) -> 0.5
C24: COMMERCE | F24: SERVICES | K24: flèche baisse | L24: =IF('Commerce Extérieur'!$D$3>0,0.5,0.49) -> 0.49
K25: Variation | L25: ='Commerce Extérieur'!$D$3 -> -1 | N25: PECHE | O25: ='Commerce Extérieur'!H164 -> 23.638
N26: flèche hausse | O26: =IF('Commerce Extérieur'!$H$3<0,0.5,0.49) -> 0.49
K27: PETROLE RAFFINE | L27: ='Commerce Extérieur'!E164 -> 124.97819 | N27: flèche baisse | O27: =IF('Commerce Extérieur'!$H$3>0,0.5,0.49) -> 0.5
K28: flèche hausse | L28: =IF('Commerce Extérieur'!$E$3<0,0.5,0.49) -> 0.49 | N28: Variation | O28: ='Commerce Extérieur'!$H$3 -> 0.35366649
K29: flèche baisse | L29: =IF('Commerce Extérieur'!$E$3>0,0.5,0.49) -> 0.5
K30: Variation | L30: ='Commerce Extérieur'!$E$3 -> 0.52063668
S33: c

Sheet graphes
A1: Dates | B1: Primaire brute | C1: Prim_CVS | E1: Secondaire brute | F1: Sec_CVS | H1: Services brute | I1: Sces_CVS | K1: Commerce brute | L1: Cce_CVS | N1: Finances Publiques
A2: =Primaire!A127 -> 42370 | B2: =Primaire!H127 -> 314.8191 | C2: =#REF! -> #REF! | E2: ='Indice Secondaire'!B7 -> 50.653394 | F2: =#REF! -> #REF! | H2: ='ICAS et ICAC'!C115 -> 82.427167 | I2: =#REF! -> #REF! | K2: ='ICAS et ICAC'!AO115 -> 46.548084 | L2: =#REF! -> #REF!
A3: =Primaire!A128 -> 42401 | B3: =Primaire!H128 -> 306.07246 | C3: =#REF! -> #REF! | E3: ='Indice Secondaire'!B8 -> 49.54939 | F3: =#REF! -> #REF! | H3: ='ICAS et ICAC'!C116 -> 88.269933 | I3: =#REF! -> #REF! | K3: ='ICAS et ICAC'!AO116 -> 46.677612 | L3: =#REF! -> #REF! | N3: MOIS
A4: =Primaire!A129 -> 42430 | B4: =Primaire!H129 -> 311.62873 | C4: =#REF! -> #REF! | E4: ='Indice Secondaire'!B9 -> 56.567739 | F4: =#REF! -> #REF! | H4: ='ICAS et ICAC'!C117 -> 85.365894 | I4: =#REF! -> #REF! | K4: ='ICAS et ICAC'!AO117 -> 52.553564 | L4: =#REF! -> #REF!
A5: =Primaire!A130 -> 42461 | B5: =Primaire!H130 -> 308.24261 | C5: =#REF! -> #REF! | E5: ='Indice Secondaire'!B10 -> 52.171553 | F5: =#REF! -> #REF! | H5: ='ICAS et ICAC'!C118 -> 94.825274 | I5: =#REF! -> #REF! | K5: ='ICAS et ICAC'!AO118 -> 49.695327 | L5: =#REF! -> #REF! | N5: Réalisations | O5: 339.34355 | P5: =O5/O6 -> 1.1156674
A6: =Primaire!A131 -> 42491 | B6: =Primaire!H131 -> 322.15279 | C6: =#REF! -> #REF! | E6: ='Indice Secondaire'!B11 -> 57.916839 | F6: =#REF! -> #REF! | H6: ='ICAS et ICAC'!C119 -> 89.621283 | I6: =#REF! -> #REF! | K6: ='ICAS et ICAC'!AO119 -> 51.283739 | L6: =#REF! -> #REF! | N6: Objectif | O6: 304.16192 | P6: =P7-P5 -> -0.11566744
A7: =Primaire!A132 -> 42522 | B7: =Primaire!H132 -> 281.72882 | C7: =#REF! -> #REF! | E7: ='Indice Secondaire'!B12 -> 57.374722 | F7: =#REF! -> #REF! | H7: ='ICAS et ICAC'!C120 -> 89.2359 | I7: =#REF! -> #REF! | K7: ='ICAS et ICAC'!AO120 -> 51.228262 | L7: =#REF! -> #REF! | N7: Invisible | O7: =SUM(O5:O6) -> 643.50548 | P7: 1
A8: =Primaire!A133 -> 42552 | B8: =Primaire!H133 -> 317.56455 | C8: =#REF! -> #REF! | E8: ='Indice Secondaire'!B13 -> 61.154547 | F8: =#REF! -> #REF! | H8: ='ICAS et ICAC'!C121 -> 94.623197 | I8: =#REF! -> #REF! | K8: ='ICAS et ICAC'!AO121 -> 47.626473 | L8: =#REF! -> #REF!
A9: =Primaire!A134 -> 42583 | B9: =Primaire!H134 -> 312.35879 | C9: =#REF! -> #REF! | E9: ='Indice Secondaire'!B14 -> 58.312721 | F9: =#REF! -> #REF! | H9: ='ICAS et ICAC'!C122 -> 90.753064 | I9: =#REF! -> #REF! | K9: ='ICAS et ICAC'!AO122 -> 47.897653 | L9: =#REF! -> #REF! | N9: aiguille | O9: =O5 -> 339.34355 | P9: =P5 -> 1.1156674
A10: =Primaire!A135 -> 42614 | B10: =Primaire!H135 -> 202.71898 | C10: =#REF! -> #REF! | E10: ='Indice Secondaire'!B15 -> 50.847476 | F10: =#REF! -> #REF! | H10: ='ICAS et ICAC'!C123 -> 91.592298 | I10: =#REF! -> #REF! | K10: ='ICAS et ICAC'!AO123 -> 45.538777 | L10: =#REF! -> #REF! | N10: largeur | O10: 3 | P10: 0.01
A11: =Primaire!A136 -> 42644 | B11: =Primaire!H136 -> 275.11504 | C11: =#REF! -> #REF! | E11: ='Indice Secondaire'!B16 -> 51.058351 | F11: =#REF! -> #REF! | H11: ='ICAS et ICAC'!C124 -> 88.510846 | I11: =#REF! -> #REF! | K11: ='ICAS et ICAC'!AO124 -> 47.09186 | L11: =#REF! -> #REF! | N11: Invisible | O11: =SUM(O5:O7)-SUM(O9:O10) -> 944.6674 | P11: =SUM(P5:P7)-SUM(P9:P10) -> 0.87433256
A12: =Primaire!A137 -> 42675 | B12: =Primaire!H137 -> 281.81392 | C12: =#REF! -> #REF! | E12: ='Indice Secondaire'!B17 -> 54.808174 | F12: =#REF! -> #REF! | H12: ='ICAS et ICAC'!C125 -> 110.68189 | I12: =#REF! -> #REF! | K12: ='ICAS et ICAC'!AO125 -> 54.02791 | L12: =#REF! -> #REF!
A13: =Primaire!A138 -> 42705 | B13: =Primaire!H138 -> 344.51126 | C13: =#REF! -> #REF! | E13: ='Indice Secondaire'!B18 -> 60.10097 | F13: =#REF! -> #REF! | H13: ='ICAS et ICAC'!C126 -> 110.68189 | I13: =#REF! -> #REF! | K13: ='ICAS et ICAC'!AO126 -> 58.819748 | L13: =#REF! -> #REF!
A14: =Primaire!A139 -> 42736 | B14: =Primaire!H139 -> 311.58575 | C14: =#REF! -> #REF! | E14: ='Indice Secondaire'!B19 -> 48.367178 | F14: =#REF! -> #REF! | H14: ='ICAS et ICAC'!C127 -> 89.646317 | I14: =#REF! -> #REF! | K14: ='ICAS et ICAC'!AO127 -> 55.809808 | L14: =#REF! -> #REF!
A15: =Primaire!A140 -> 42767 | B15: =Primaire!H140 -> 291.5687 | C15: =#REF! -> #REF! | E15: ='Indice Secondaire'!B20 -> 50.698895 | F15: =#REF! -> #REF! | H15: ='ICAS et ICAC'!C128 -> 85.229786 | I15: =#REF! -> #REF! | K15: ='ICAS et ICAC'!AO128 -> 54.830954 | L15: =#REF! -> #REF!
A16: =Primaire!A141 -> 42795 | B16: =Primaire!H141 -> 325.34686 | C16: =#REF! -> #REF! | E16: ='Indice Secondaire'!B21 -> 53.823284 | F16: =#REF! -> #REF! | H16: ='ICAS et ICAC'!C129 -> 90.618834 | I16: =#REF! -> #REF! | K16: ='ICAS et ICAC'!AO129 -> 59.332935 | L16: =#REF! -> #REF!
A17: =Primaire!A142 -> 42826 | B17: =Primaire!H142 -> 330.60769 | C17: =#REF! -> #REF! | E17: ='Indice Secondaire'!B22 -> 49.566802 | F17: =#REF! -> #REF! | H17: ='ICAS et ICAC'!C130 -> 90.146117 | I17: =#REF! -> #REF! | K17: ='ICAS et ICAC'!AO130 -> 56.699295 | L17: =#REF! -> #REF!
A18: =Primaire!A143 -> 42856 | B18: =Primaire!H143 -> 338.70057 | C18: =#REF! -> #REF! | E18: ='Indice Secondaire'!B23 -> 58.431244 | F18: =#REF! -> #REF! | H18: ='ICAS et ICAC'!C131 -> 88.671367 | I18: =#REF! -> #REF! | K18: ='ICAS et ICAC'!AO131 -> 57.894833 | L18: =#REF! -> #REF! | N18: ANNEE
A19: =Primaire!A144 -> 42887 | B19: =Primaire!H144 -> 294.97839 | C19: =#REF! -> #REF! | E19: ='Indice Secondaire'!B24 -> 57.791939 | F19: =#REF! -> #REF! | H19: ='ICAS et ICAC'!C132 -> 92.117849 | I19: =#REF! -> #REF! | K19: ='ICAS et ICAC'!AO132 -> 59.426002 | L19: =#REF! -> #REF!
A20: =Primaire!A145 -> 42917 | B20: =Primaire!H145 -> 315.16493 | C20: =#REF! -> #REF! | E20: ='Indice Secondaire'!B25 -> 48.924652 | F20: =#REF! -> #REF! | H20: ='ICAS et ICAC'!C133 -> 91.878546 | I20: =#REF! -> #REF! | K20: ='ICAS et ICAC'!AO133 -> 59.839201 | L20: =#REF! -> #REF! | N20: Réalisations | O20: ='Finances Publiques '!B171 -> 1810.43
A21: =Primaire!A146 -> 42948 | B21: =Primaire!H146 -> 300.36126 | C21: =#REF! -> #REF! | E21: ='Indice Secondaire'!B26 -> 51.465988 | F21: =#REF! -> #REF! | H21: ='ICAS et ICAC'!C134 -> 97.625146 | I21: =#REF! -> #REF! | K21: ='ICAS et ICAC'!AO134 -> 56.714575 | L21: =#REF! -> #REF! | N21: LFI 2019 | O21: 2657.4
A22: =Primaire!A147 -> 42979 | B22: =Primaire!H147 -> 214.39966 | C22: =#REF! -> #REF! | E22: ='Indice Secondaire'!B27 -> 49.380612 | F22: =#REF! -> #REF! | H22: ='ICAS et ICAC'!C135 -> 90.888213 | I22: =#REF! -> #REF! | K22: ='ICAS et ICAC'!AO135 -> 58.229834 | L22: =#REF! -> #REF! | N22: Invisible | O22: =SUM(O20:O21) -> 4467.83
A23: =Primaire!A148 -> 43009 | B23: =Primaire!H148 -> 297.17798 | C23: =#REF! -> #REF! | E23: ='Indice Secondaire'!B28 -> 49.743875 | F23: =#REF! -> #REF! | H23: ='ICAS et ICAC'!C136 -> 87.866075 | I23: =#REF! -> #REF! | K23: ='ICAS et ICAC'!AO136 -> 62.947106 | L23: =#REF! -> #REF!
A24: =Primaire!A149 -> 43040 | B24: =Primaire!H149 -> 333.64589 | C24: =#REF! -> #REF! | E24: ='Indice Secondaire'!B29 -> 51.427978 | F24: =#REF! -> #REF! | H24: ='ICAS et ICAC'!C137 -> 95.741008 | I24: =#REF! -> #REF! | K24: ='ICAS et ICAC'!AO137 -> 66.062313 | L24: =#REF! -> #REF!
A25: =Primaire!A150 -> 43070 | B25: =Primaire!H150 -> 361.70796 | C25: =#REF! -> #REF! | E25: ='Indice Secondaire'!B30 -> 55.640721 | F25: =#REF! -> #REF! | H25: ='ICAS et ICAC'!C138 -> 94.866296 | I25: =#REF! -> #REF! | K25: ='ICAS et ICAC'!AO138 -> 66.336591 | L25: =#REF! -> #REF!
A26: =Primaire!A151 -> 43101 | B26: =Primaire!H151 -> 346.83061 | C26: =#REF! -> #REF! | E26: ='Indice Secondaire'!B31 -> 49.027265 | F26: =#REF! -> #REF! | H26: ='ICAS et ICAC'!C139 -> 96.229927 | I26: =#REF! -> #REF! | K26: ='ICAS et ICAC'!AO139 -> 61.217494 | L26: =#REF! -> #REF!
A27: =Primaire!A152 -> 43132 | B27: =Primaire!H152 -> 322.77404 | C27: =#REF! -> #REF! | E27: ='Indice Secondaire'!B32 -> 49.49962 | F27: =#REF! -> #REF! | H27: ='ICAS et ICAC'!C140 -> 92.53842 | I27: =#REF! -> #REF! | K27: ='ICAS et ICAC'!AO140 -> 63.652574 | L27: =#REF! -> #REF!
A28: =Primaire!A153 -> 43160 | B28: =Primaire!H153 -> 375.21534 | C28: =#REF! -> #REF! | E28: ='Indice Secondaire'!B33 -> 55.996609 | F28: =#REF! -> #REF! | H28: ='ICAS et ICAC'!C141 -> 92.693022 | I28: =#REF! -> #REF! | K28: ='ICAS et ICAC'!AO141 -> 62.147878 | L28: =#REF! -> #REF!
A29: =Primaire!A154 -> 43191 | B29: =Primaire!H154 -> 358.33769 | C29: =#REF! -> #REF! | E29: ='Indice Secondaire'!B34 -> 53.190612 | F29: =#REF! -> #REF! | H29: ='ICAS et ICAC'!C142 -> 92.079512 | I29: =#REF! -> #REF! | K29: ='ICAS et ICAC'!AO142 -> 61.634925 | L29: =#REF! -> #REF!
A30: =Primaire!A155 -> 43221 | B30: =Primaire!H155 -> 343.90641 | C30: =#REF! -> #REF! | E30: ='Indice Secondaire'!B35 -> 60.560516 | F30: =#REF! -> #REF! | H30: ='ICAS et ICAC'!C143 -> 96.138391 | I30: =#REF! -> #REF! | K30: ='ICAS et ICAC'!AO143 -> 65.861987 | L30: =#REF! -> #REF!
A31: =Primaire!A156 -> 43252 | B31: =Primaire!H156 -> 334.5421 | C31: =#REF! -> #REF! | E31: ='Indice Secondaire'!B36 -> 55.389781 | F31: =#REF! -> #REF! | H31: ='ICAS et ICAC'!C144 -> 97.981845 | I31: =#REF! -> #REF! | K31: ='ICAS et ICAC'!AO144 -> 61.847001 | L31: =#REF! -> #REF!
A32: =Primaire!A157 -> 43282 | B32: =Primaire!H157 -> 321.84621 | C32: =#REF! -> #REF! | E32: ='Indice Secondaire'!B37 -> 57.849911 | F32: =#REF! -> #REF! | H32: ='ICAS et ICAC'!C145 -> 99.590283 | I32: =#REF! -> #REF! | K32: ='ICAS et ICAC'!AO145 -> 65.338899 | L32: =#REF! -> #REF!
A33: =Primaire!A158 -> 43313 | B33: =Primaire!H158 -> 261.85722 | C33: =#REF! -> #REF! | E33: ='Indice Secondaire'!B38 -> 55.851854 | F33: =#REF! -> #REF! | H33: ='ICAS et ICAC'!C146 -> 94.106023 | I33: =#REF! -> #REF! | K33: ='ICAS et ICAC'!AO146 -> 64.518521 | L33: =#REF! -> #REF!
A34: =Primaire!A159 -> 43344 | B34: =Primaire!H159 -> 256.9084 | C34: =#REF! -> #REF! | E34: ='Indice Secondaire'!B39 -> 54.484074 | F34: =#REF! -> #REF! | H34: ='ICAS et ICAC'!C147 -> 95.573004 | I34: =#REF! -> #REF! | K34: ='ICAS et ICAC'!AO147 -> 61.992498 | L34: =#REF! -> #REF!
... A121: =Primaire!A246 -> 45992 | B121: =Primaire!H246 -> 123.47314 | C121: =#REF! -> #REF! | E121: ='Indice Secondaire'!B126 -> 120.19417 | F121: =#REF! -> #REF! | H121: ='ICAS et ICAC'!C234 -> 148.17683 | I121: =#REF! -> #REF! | K121: ='ICAS et ICAC'!AO234 -> 103.79187 | L121: =#REF! -> #REF!
A122: =Primaire!A247 -> 46023 | B122: =Primaire!H247 -> 110.09631 | C122: =#REF! -> #REF! | E122: ='Indice Secondaire'!B128 -> 0 | H122: ='ICAS et ICAC'!C235 -> 123.00144 | K122: ='ICAS et ICAC'!AO235 -> 89.835383

Sheet Environnement International
A1: DIRECTION DE LA PREVISION ET DES ETUDES ECONOMIQUES
B3: =B247/B246-1 -> 0.06267736 | C3: =C247/C246-1 -> 0.024630039 | D3: =D247/D246-1 -> -0.016896056 | E3: =E247/E246-1 -> -0.005872301 | F3: =F247/F246-1 -> 0 | G3: =G247/G246-1 -> 0.064508929 | H3: =H247/H246-1 -> #VALUE! | I3: =I247/I246-1 -> 0 | ... K3: =K247/K246-1 -> 0.0024767273
B4: Cours des matières premières | H4: CHANGES (par rapport au CFA UEMOA) | K4: EURO / DOLLAR USA | L4: Taux d'intérêt nominal (long terme) | P4: Prix à la consommation (glissement sur 12 mois)
B5: Huile d'arachide | C5: Huile de palme | D5: Riz | E5: Maïs | F5: Phosphate | G5: Pétrole, BRENT | H5: 1 DTS = | I5: 1 Euro = | J5: 1 Dollar USA = | L5: France | M5: USA | N5: Allemagne | O5: Japon | P5: USA | Q5: Japon | R5: Allemagne | S5: France | T5: Zone Euro
B6: ($/t) | C6: ($/t) | D6: ($/t) | E6: ($/t) | F6: ($/t) | G6: ($/baril)
A7: 38718 | B7: 930 | C7: 424 | D7: 211 | E7: 102.7 | F7: 42 | G7: 63.6 | H7: 784.44989 | I7: 655.957 | J7: 542.01727 | K7: 1.21 | L7: 3.4 | M7: 4.42 | N7: 3.26 | O7: 1.56 | P7: 4.1 | Q7: 0.5 | R7: 2.1 | S7: 2 | T7: 2.0333333
A8: 38749 | B8: 921 | C8: 445 | D8: 215.3 | E8: 107.1 | F8: 42 | G8: 59.9 | H8: 788.88394 | I8: 655.957 | J8: 549.46894 | K8: 1.19 | L8: 3.56 | M8: 4.57 | N8: 3.4 | O8: 1.58 | P8: 3.6 | Q8: 0.4 | R8: 2.1 | S8: 1.9 | T8: 2.2
A9: 38777 | B9: 902 | C9: 440 | D9: 215 | E9: 105.3 | F9: 43 | G9: 62.3 | H9: 785.38913 | I9: 655.957 | J9: 545.7213 | K9: 1.202 | L9: 3.72 | M9: 4.72 | N9: 3.59 | O9: 1.77 | P9: 3.3 | Q9: 0.3 | R9: 1.8 | S9: 1.5 | T9: 2.3333333
A10: 38808 | B10: 899 | C10: 439 | D10: 216.8 | E10: 107.7 | F10: 43 | G10: 70.4 | H10: 776.09678 | I10: 655.957 | J10: 534.55872 | K10: 1.227 | L10: 4.01 | M10: 4.99 | N10: 3.84 | O10: 1.92 | P10: 3.5 | Q10: 0.4 | R10: 2 | S10: 1.7 | T10: 2.4
A11: 38838 | B11: 892 | C11: 440 | D11: 217.6 | E11: 110.6 | F11: 43 | G11: 70.2 | H11: 765.14289 | I11: 655.957 | J11: 513.71055 | K11: 1.2769 | L11: 4.07 | M11: 5.11 | N11: 3.89 | O11: 1.81 | P11: 4.2 | Q11: 0.6 | R11: 1.9 | S11: 2.1 | T11: 2.2444444
A12: 38869 | B12: 898 | C12: 437 | D12: 215.5 | E12: 109.4 | F12: 44.5 | G12: 68.9 | H12: 766.48399 | I12: 655.957 | J12: 518.58408 | K12: 1.2649 | L12: 4.06 | M12: 5.11 | N12: 3.9 | O12: 1.92 | P12: 4.3 | Q12: 0.5 | R12: 2 | S12: 1.9 | T12: 2.5
A13: 38899 | B13: 928 | C13: 471 | D13: 217.3 | E13: 113.99108 | F13: 45.5 | G13: 74 | H13: 764.3 | I13: 655.957 | J13: 517.2 | K13: 1.269 | L13: 4.09 | M13: 5.09 | N13: 3.96 | O13: 1.92 | P13: 4.1 | Q13: 0.3 | R13: 1.9 | S13: 1.9 | T13: 2.5
A14: 38930 | B14: 944 | C14: 510 | D14: 217.7 | E14: 116.58833 | F14: 45.5 | G14: 73.6 | H14: 761.4 | I14: 655.957 | J14: 512 | K14: 1.28 | L14: 3.96 | M14: 4.88 | N14: 3.85 | O14: 1.61 | P14: 3.8 | Q14: 1 | R14: 1.7 | S14: 1.9 | T14: 2.5
A15: 38961 | B15: 959 | C15: 498 | D15: 222.6 | E15: 121.74554 | F15: 45.5 | G15: 63.575667 | H15: 757 | I15: 655.957 | J15: 515 | K15: 1.27 | L15: 3.84 | M15: 4.72 | N15: 3.75 | O15: 1.66 | P15: 2.1 | Q15: 0.6 | R15: 1 | S15: 1.2 | T15: 2.5
A16: 38991 | B16: 1068 | C16: 506.92042 | D16: 222.3 | E16: 142.2 | F16: 45.5 | G16: 59.63 | H16: 766.48399 | I16: 655.957 | J16: 520.1467 | K16: 1.26 | L16: 3.88 | M16: 4.73 | N16: 3.79 | O16: 1.71 | P16: 1.3 | Q16: 0.3 | R16: 1.1 | S16: 1.1 | T16: 1.6
A17: 39022 | B17: 1120 | C17: 547.02533 | D17: 219 | E17: 164.53856 | F17: 45.5 | G17: 58.634 | H17: 767.56026 | I17: 655.957 | J17: 509.24385 | K17: 1.29 | L17: 3.81 | M17: 4.6 | N17: 3.73 | O17: 1.65 | P17: 1.9 | Q17: 0.1 | R17: 1.5 | S17: 1.4 | T17: 1.6
A18: 39052 | B18: 1173 | C18: 582.94099 | D18: 226.3 | E18: 160.37539 | F18: 45.5 | G18: 62.236667 | H18: 748.6 | I18: 655.957 | J18: 496.48577 | K18: 1.32 | L18: 3.87 | M18: 4.56 | N18: 3.8 | O18: 1.68 | P18: 2.5 | Q18: 0 | R18: 1.4 | S18: 1.5 | T18: 2
... A108: 41791 | B108: 1310 | C108: 857 | D108: 402.6 | E108: 202.4 | F108: 110 | G108: 111.88021 | H108: 740.3 | I108: 655.957 | J108: 482.26329 | K108: 1.3601637 | L108: 1.71 | M108: 2.6 | N108: 1.26 | O108: 0.56 | P108: 2.072 | Q108: 3.607 | R108: 1.042 | S108: 0.486 | T108: 0.494
A109: 41821 | B109: 1325 | C109: 841 | D109: 435.6 | E109: 182.7 | F109: 110 | G109: 108.29016 | H109: 741.6 | I109: 655.957 | J109: 484.58656 | K109: 1.3536426 | L109: 1.56 | M109: 2.54 | N109: 1.11 | O109: _ | P109: 1.992 | Q109: 3.4 | R109: 0.848 | S109: 0.464 | T109: 0.376
A110: 41852 | B110: 1350 | C110: 766 | D110: 460.6 | E110: 176.4 | F110: 110 | G110: 103.59885 | H110: 746.9 | I110: 655.957 | J110: 492.71031 | K110: 1.3313239 | L110: 1.41 | M110: 2.42 | N110: 0.95 | O110: _ | P110: 1.7 | Q110: 3.29 | R110: 0.848 | S110: 0.438 | T110: 0.367
A111: 41883 | B111: 1360 | C111: 709 | D111: 449.9 | E111: 163.1 | F111: 115 | G111: 98.476751 | H111: 757.1 | I111: 655.957 | J111: 509.28602 | K111: 1.2879933 | L111: 1.35 | M111: 2.53 | N111: 0.92 | O111: _ | P111: 1.7 | Q111: 3.2 | R111: 0.848 | S111: 0.29 | T111: 0.314
A112: 41913 | B112: 1365 | C112: 722 | D112: 437.57 | E112: 163.12 | F112: 115 | G112: 88.105484 | H112: 763 | I112: 655.957 | J112: 517.79877 | K112: 1.2668184 | L112: 1.26 | M112: 2.3 | N112: 0.79 | O112: _ | P112: 1.664 | Q112: 2.88 | R112: 0.755 | S112: 0.456 | T112: 0.382
A113: 41944 | B113: 1368 | C113: 731 | D113: 423.8 | E113: 178.74 | F113: 115 | G113: 80.171333 | H113: 767.9 | I113: 655.957 | J113: 526.04157 | K113: 1.246968 | L113: 1.14 | M113: 2.33 | N113: 0.72 | O113: 0.42 | P113: 1.322 | Q113: 2.381 | R113: 0.566 | S113: 0.322 | T113: 0.3
A114: 41974 | B114: 1370 | C114: 693 | D114: 421.18 | E114: 178.73 | F114: 115 | G114: 63.047149 | H114: 771.8 | I114: 655.957 | J114: 533.35894 | K114: 1.2298603 | L114: 0.92 | M114: 2.21 | N114: 0.59 | O114: 0.32 | P114: 0.756 | Q114: 2.379 | R114: 0.188 | S114: 0.071 | T114: -0.169
A115: 42005 | B115: 1391 | C115: 688 | D115: 418.55 | E115: 174.70731 | F115: 115 | G115: 50.18129 | H115: 789.7 | I115: 655.957 | J115: 564.56754 | K115: 1.1618752 | L115: 0.67 | M115: 1.88 | N115: 0.39 | O115: 0.28 | P115: -0.089 | Q115: 2.383 | R115: -0.283 | S115: -0.378 | T115: -0.6
A116: 42036 | B116: 1366 | C116: 689 | D116: 417 | E116: 173.69555 | F116: 115 | G116: 58.747963 | H116: 797.6 | I116: 655.957 | J116: 578.30909 | K116: 1.1342671 | L116: 0.6 | M116: 1.98 | N116: 0.3 | O116: 0.34 | P116: -0.025 | Q116: 2.185 | R116: 0.094 | S116: -0.274 | T116: -0.273
A117: 42064 | B117: 1356 | C117: 672 | D117: 411 | E117: 174.22702 | F117: 115 | G117: 57.173453 | H117: 812.1 | I117: 655.957 | J117: 606.24564 | K117: 1.0819987 | L117: 0.51 | M117: 2.04 | N117: 0.23 | O117: 0.4 | P117: -0.074 | Q117: 2.277 | R117: 0.281 | S117: -0.062 | T117: -0.085
A118: 42095 | B118: 1348 | C118: 662 | D118: 400.26 | E118: 172.05391 | F118: 115 | G118: 60.761 | H118: 813.6 | I118: 655.957 | J118: 606.4822 | K118: 1.0815767 | L118: 0.44 | M118: 1.94 | N118: 0.12 | O118: 0.33 | P118: -0.2 | Q118: 0.582 | R118: 0.469 | S118: 0.094 | T118: 0.008
A119: 42125 | B119: 1345 | C119: 659 | D119: 386.53 | E119: 166.29437 | F119: 115 | G119: 65.541613 | H119: 803.2 | I119: 655.957 | J119: 587.68845 | K119: 1.1161645 | L119: 0.89 | M119: 2.2 | N119: 0.56 | O119: 0.39 | P119: -0.04 | Q119: 0.5 | R119: 0.658 | S119: 0.296 | T119: 0.34
A120: 42156 | B120: 1345 | C120: 671 | D120: 375.95 | E120: 166.71954 | F120: 115 | G120: 63.481638 | H120: 801.4 | I120: 655.957 | J120: 583.99344 | K120: 1.1232267 | L120: 1.2 | M120: 2.36 | N120: 0.79 | O120: 0.45 | P120: 0.12 | Q120: 0.4 | R120: 0.281 | S120: 0.258 | T120: 0.22
A121: 42186 | B121: 1345 | C121: 636 | D121: 389.86 | E121: 179.59682 | F121: 115 | G121: 55.87 | H121: 807 | I121: 655.957 | J121: 596.48958 | K121: 1.0996957 | L121: 1.26 | M121: 2.32 | N121: 0.71 | O121: 0.41 | P121: 0.17 | Q121: 0.2 | R121: 0.19 | S121: 0.16 | T121: 0.23
A122: 42217 | B122: 1331 | C122: 549 | D122: 377.5 | E122: 162.59378 | F122: 115 | G122: 46.99 | H122: 803.6 | I122: 655.957 | J122: 588.88 | K122: 1.1144095 | L122: 1.15 | M122: 2.17 | N122: 0.61 | O122: 0.375 | P122: 0.195 | Q122: 0.2 | R122: 0.187 | S122: 0.047 | T122: 0.127
A123: 42248 | B123: 1321 | C123: 538 | D123: 360 | E123: 165.62118 | F123: 121 | G123: 47.24 | H123: 801.2 | I123: 655.957 | J123: 583.76161 | K123: 1.1236727 | L123: 1.217 | M123: 2.17 | N123: 0.65 | O123: 0.345 | P123: -0.036 | Q123: 0 | R123: 0 | S123: 0.031 | T123: -0.1
A124: 42278 | B124: 1314 | C124: 583 | D124: 369.27 | E124: 171.38859 | F124: 123 | G124: 48.12 | H124: 800.9 | I124: 655.957 | J124: 584.71718 | K124: 1.1218364 | L124: 0.903 | M124: 2.07 | N124: 0.52 | O124: 0.295 | P124: 0.171 | Q124: 0.3 | R124: 0.281 | S124: 0.055 | T124: 0.1
... A128: 42401 | B128: 1271 | C128: 640 | D128: 377.38 | E128: 159.67661 | F128: 115 | G128: 33.2 | H128: 727.65 | I128: 655.957 | J128: 590.74951 | K128: 1.110381 | L128: 0.592 | M128: 1.78 | N128: 0.17 | O128: -0.065 | P128: 1.02 | Q128: 0.3 | R128: 0 | S128: -0.19 | T128: -0.2
A129: 42430 | B129: 1286 | C129: 686 | D129: 374.9 | E129: 159.13727 | F129: 115 | G129: 39.07 | H129: 824.47 | I129: 655.957 | J129: 588.81885 | K129: 1.1140217 | L129: 0.509 | M129: 1.890 | N129: 0.17 | O129: -0.05 | P129: 0.85 | Q129: -0.1 | R129: 0.28 | S129: -0.15 | T129: 0
A130: 42461 | B130: 1350 | C130: 723 | D130: 383.53 | E130: 164.41258 | F130: 115 | G130: 42.25 | H130: 814.98 | I130: 655.957 | J130: 578.50606 | K130: 1.133881 | L130: 0.514 | M130: 1.81 | N130: 0.13 | O130: -0.085 | P130: 1.125 | Q130: -0.3 | R130: -0.09 | S130: -0.19 | T130: -0.2
A131: 42491 | B131: 1600 | C131: 706.25 | D131: 414.38 | E131: 168.96 | F131: 115 | G131: 47.13 | H131: 818.25 | I131: 655.957 | J131: 579.93 | K131: 1.1297455 | L131: 0.509 | M131: 1.81 | N131: 0.13 | O131: -0.12 | P131: 1.022 | Q131: -0.4 | R131: 0.093 | S131: -0.02 | T131: -0.1
A132: 42522 | B132: 1700 | C132: 683 | D132: 426.83 | E132: 179.87239 | F132: 115 | G132: 48.48 | H132: 822.38 | I132: 655.957 | J132: 583.98605 | K132: 1.1232409 | L132: 0.39 | M132: 1.64 | N132: -0.02 | O132: -0.235 | P132: 1.006 | Q132: -0.4 | R132: 0.28 | S132: 0.189 | T132: 0.1
A133: 42552 | B133: 1673 | C133: 651 | D133: 417.89 | E133: 161.75918 | F133: 115 | G133: 45.07 | H133: 824.15 | I133: 655.957 | J133: 592.61 | K133: 1.1063476 | L133: 0.175 | M133: 1.5 | N133: -0.15 | O133: -0.18 | P133: 0.84 | Q133: -0.4 | R133: 0.37 | S133: 0.22 | T133: 0.2
A134: 42583 | B134: 1650 | C134: 736.25 | D134: 397.84 | E134: 150.55504 | F134: 111 | G134: 46.14 | H134: 818.68 | I134: 655.957 | J134: 585.43726 | K134: 1.1204565 | L134: 0.152 | M134: 1.56 | N134: -0.13 | O134: -0.07 | P134: 1.06 | Q134: -0.5 | R134: 0.37 | S134: 0.23 | T134: 0.2
A135: 42614 | B135: 1620 | C135: 756 | D135: 365.57 | E135: 148.42523 | F135: 110 | G135: 46.19 | H135: 818.31 | I135: 655.957 | J135: 584.98028 | K135: 1.1213318 | L135: 0.184 | M135: 1.63 | N135: -0.09 | O135: -0.085 | P135: 1.46 | Q135: -0.5 | R135: 0.65 | S135: 0.39 | T135: 0.4
A136: 42644 | B136: 1575 | C136: 716 | D136: 350.3 | E136: 152.25968 | F136: 110 | G136: 49.73 | H136: 821.59 | I136: 655.957 | J136: 595.05458 | K136: 1.1023476 | L136: 0.331 | M136: 1.76 | N136: 0 | O136: -0.055 | P136: 1.636 | Q136: 0.1 | R136: 0.841 | S136: 0.36 | T136: 0.5
A137: 42675 | B137: 1525 | C137: 755 | D137: 339.59 | E137: 151.80301 | F137: 104 | G137: 46.44 | H137: 828.9 | I137: 655.957 | J137: 608.51196 | K137: 1.077969 | L137: 0.667 | M137: 2.14 | N137: 0.19 | O137: 0.015 | P137: 1.693 | Q137: 0.5 | R137: 0.84 | S137: 0.531 | T137: 0.6
A138: 42705 | B138: 1507.5 | C138: 751 | D138: 354.42 | E138: 152.44864 | F138: 103 | G138: 54.07 | H138: 837.82395 | I138: 655.957 | J138: 622.50319 | K138: 1.0537408 | L138: 0.759 | M138: 2.49 | N138: 0.25 | O138: 0.04 | P138: 2.0746 | Q138: 0.3 | R138: 1.6822 | S138: 0.6098 | T138: 1.1
A139: 42736 | B139: 1520 | C139: 805.75 | D139: 355.9 | E139: 159.98762 | F139: 99 | G139: 54.89 | H139: 834.64 | I139: 655.957 | J139: 617.08978 | K139: 1.0629847 | L139: 0.8631 | M139: 2.43 | N139: 0.25 | O139: 0.08 | P139: 2.5 | Q139: 0.4 | R139: 1.885 | S139: 1.3424 | T139: 1.8
A140: 42767 | B140: 1545 | C140: 778.75 | D140: 348.75 | E140: 162.85754 | F140: 98 | G140: 55.49 | H140: 835.26 | I140: 655.957 | J140: 616.18239 | K140: 1.0645501 | L140: 1.038 | M140: 2.42 | N140: 0.26 | O140: 0.05 | P140: 2.738 | Q140: 0.3 | R140: 2.16 | S140: 1.208 | T140: 2
A141: 42795 | B141: 1578 | C141: 736 | D141: 358.43 | E141: 158.96405 | F141: 98 | G141: 51.97 | H141: 831.79 | I141: 655.957 | J141: 613.80463 | K141: 1.0686739 | L141: 1.024 | M141: 2.48 | N141: 0.35 | O141: 0.065 | P141: 2.381 | Q141: 0.2 | R141: 1.584 | S141: 1.15 | T141: 1.5
... A241: 45839 | B241: 1727.31 | C241: 974.97 | D241: 376.05 | E241: 191.99434 | F241: 152.5 | G241: 70.951 | H241: 769.12 | I241: 655.957 | J241: 561.75131 | K241: 1.1677 | L241: 3.36 | M241: 4.39 | N241: 2.63 | O241: 1.55 | P241: 2.704902 | Q241: 3.1 | R241: 2.003339 | S241: 0.9965122 | T241: 2
A242: 45870 | B242: 1664.67 | C242: 1025.986 | D242: 357.85 | E242: 185.48678 | F242: 152.5 | G242: 68.203 | H242: .. | I242: 655.957 | J242: 563.973 | K242: 1.1631 | L242: 3.42 | M242: 4.26 | N242: 2.67 | O242: 1.6 | P242: 2.916174 | Q242: 2.73 | R242: 2.172097 | S242: 0.8838592 | T242: 2
A243: 45901 | B243: 1612.6698 | C243: 1038.3563 | D243: 355.19 | E243: 197.37534 | F243: 152.5 | G243: 67.951 | H243: .. | I243: 655.957 | J243: 762.94359 | K243: 1.1732 | L243: 3.51 | M243: 4.12 | N243: 2.69 | O243: 1.65 | P243: 3.012677 | Q243: 2.93 | R243: 2.422724 | S243: 1.162596 | T243: 2.2
A244: 45931 | B244: 1628.3213 | C244: 1038.0939 | D244: 335.91 | E244: 198.1304 | F244: 152.5 | G244: 64.651 | H244: 769.33 | I244: 655.957 | J244: 564.0215 | K244: 1.163 | L244: 3.44 | M244: 4.06 | N244: 2.62 | O244: 1.66 | P244: .. | Q244: 2.984054 | R244: 2.329451 | S244: 0.9425306 | T244: 2.1
A245: 45962 | B245: 1693.3154 | C245: 970.36208 | D245: 338.5 | E245: 202.01642 | F245: 152.5 | G245: 63.609 | H245: 770.32 | I245: 655.957 | J245: 567.43685 | K245: 1.156 | L245: 3.44 | M245: 4.09 | N245: 2.66 | O245: 1.81 | P245: 2.735085 | Q245: 2.9 | R245: 2.335279 | S245: 0.9021049 | T245: 2.1
A246: 45992 | B246: 1621 | C246: 980.51 | D246: 389.44 | E246: 205.69624 | F246: 152.5 | G246: 62.72 | H246: .. | I246: 655.957 | J246: 560.21607 | K246: 1.1709 | L246: 3.55 | M246: 4.14 | N246: 2.81 | O246: 2.06 | P246: 2.68 | Q246: 2.1 | R246: 2.171788 | S246: 0.9437702 | T246: 2.1
A247: 46023 | B247: 1722.6 | C247: 1004.66 | D247: 382.86 | E247: 204.48833 | F247: 152.5 | G247: 66.766 | H247: 765.4 | I247: 655.957 | J247: 558.832 | K247: 1.1738 | L247: 3.53 | M247: 4.21 | N247: 2.81 | O247: 2.24 | P247: 2.39 | R247: 2.08 | S247: .. | T247: ..

Sheet Primaire
A1: DIRECTION DE LA PREVISION ET DES ETUDES ECONOMIQUES
B2: =B247/B246-1 -> -0.14275371 | C2: =C247/C246-1 -> 0.10355542 | D2: =D247/D246-1 -> 0.34326579 | E2: =E247/E246-1 -> 0.075940306
B3: DONNEES DE PRODUCTION | H3: INDICE PRIMAIRE (base 100=2022)
B4: Abattages contrôlés de viande | C4: Pêche | I4: Elevage | J4: Pêche
D5: Industrielle | E5: Artisanale | K5: Artisanale | L5: Industrielle
B6: (tonnes) | C6: (tonnes) | D6: (tonnes) | E6: (tonnes)
A7: 38718 | B7: 940.988 | C7: =SUM(D7:E7) -> 33253 | D7: 4588 | E7: 28665 | AT7: 4.236331 | AU7: 1.737522 | AV7: =AU7+AT7 -> 5.9738529
A8: 38749 | B8: 1341.832 | C8: =SUM(D8:E8) -> 35111 | D8: 3984 | E8: 31127
A9: 38777 | B9: 1567.5 | C9: =SUM(D9:E9) -> 33232 | D9: 5082 | E9: 28150
A10: 38808 | B10: 1539.888 | C10: =SUM(D10:E10) -> 36126 | D10: 6457 | E10: 29669
A11: 38838 | B11: 1495.521 | C11: =SUM(D11:E11) -> 42645 | D11: 5456 | E11: 37189
A12: 38869 | B12: 1534.648 | C12: =SUM(D12:E12) -> 42039 | D12: 4763 | E12: 37276
A13: 38899 | B13: 1582.879 | C13: =SUM(D13:E13) -> 32359 | D13: 5183 | E13: 27176
A14: 38930 | B14: 1588.552 | C14: =SUM(D14:E14) -> 29389 | D14: 5890 | E14: 23499
A15: 38961 | B15: 1626.623 | C15: =SUM(D15:E15) -> 24505 | D15: 5152 | E15: 19353
A16: 38991 | B16: 1616.261 | C16: =SUM(D16:E16) -> 20708 | D16: 2839 | E16: 17869
A17: 39022 | B17: 1650.716 | C17: =SUM(D17:E17) -> 29200 | D17: 5107 | E17: 24093
A18: 39052 | B18: 1658.469 | C18: =SUM(D18:E18) -> 35333 | D18: 5137 | E18: 30196
A19: 39083 | B19: 1223.853 | C19: =SUM(D19:E19) -> 33198.06 | D19: 5348 | E19: 27850.06
... A126: 42339 | B126: 2167.2815 | C126: =SUM(D126:E126) -> 43475.383 | D126: 8634 | E126: 34841.383
A127: 42370 | B127: 2005.7405 | C127: =SUM(D127:E127) -> 51260.865 | D127: 7769 | E127: 43491.865 | H127: 314.8191 | I127: 359.59173 | J127: 117.67114 | K127: 158.28663 | L127: 48.296155
A128: 42401 | B128: 1959.4325 | C128: =SUM(D128:E128) -> 46597.958 | D128: 8292 | E128: 38305.958 | H128: 306.07246 | I128: 351.28957 | J128: 106.96727 | K128: 139.41277 | L128: 51.547396
A129: 42430 | B129: 2006.2735 | C129: =SUM(D129:E129) -> 43567.95 | D129: 10126 | E129: 33441.95 | H129: 311.62873 | I129: 359.68728 | J129: 100.01178 | K129: 121.71043 | L129: 62.948496
A130: 42461 | B130: 1990.6305 | C130: =SUM(D130:E130) -> 40977.19 | D130: 9141 | E130: 31836.19 | H130: 308.24261 | I130: 356.88279 | J130: 94.064601 | K130: 115.86634 | L130: 56.825222
A131: 42491 | B131: 2008.153 | C131: =SUM(D131:E131) -> 67693.51 | D131: 13032 | E131: 54661.51 | H131: 322.15279 | I131: 360.02424 | J131: 155.39287 | K131: 198.93804 | L131: 81.013707
A132: 42522 | B132: 1761.4615 | C132: =SUM(D132:E132) -> 57379.01 | D132: 10672 | E132: 46707.01 | H132: 281.72882 | I132: 315.79707 | J132: 131.71556 | K132: 169.98801 | L132: 66.342717
A133: 42552 | B133: 2061.3285 | C133: =SUM(D133:E133) -> 38606.548 | D133: 8433 | E133: 30173.548 | H133: 317.56455 | I133: 369.55761 | J133: 88.622708 | K133: 109.81523 | L133: 52.423925
A134: 42583 | B134: 2028.184 | C134: =SUM(D134:E134) -> 37751.408 | D134: 7325 | E134: 30426.408 | H134: 312.35879 | I134: 363.61543 | J134: 86.659704 | K134: 110.73551 | L134: 45.53602
A135: 42614 | B135: 1313.6615 | C135: =SUM(D135:E135) -> 25400.661 | D135: 7901 | E135: 17499.661 | H135: 202.71898 | I135: 235.51492 | J135: 58.308124 | K135: 63.68921 | L135: 49.116736
A136: 42644 | B136: 1805.072 | C136: =SUM(D136:E136) -> 26813.653 | D136: 7691 | E136: 19122.653 | H136: 275.11504 | I136: 323.61562 | J136: 61.551697 | K136: 69.596013 | L136: 47.811266
A137: 42675 | B137: 1843.7445 | C137: =SUM(D137:E137) -> 29282.293 | D137: 6497 | E137: 22785.293 | H137: 281.81392 | I137: 330.54888 | J137: 67.218548 | K137: 82.926022 | L137: 40.38874
A138: 42705 | B138: 2249.9145 | C138: =SUM(D138:E138) -> 37180.2 | D138: 7761 | E138: 29419.2 | H138: 344.51126 | I138: 403.36755 | J138: 85.348475 | K138: 107.06982 | L138: 48.246423
... A247: 46023 | B247: 2334.832 | C247: =SUM(D247:E247) -> 44814.612 | D247: 5635 | E247: 39179.612 | H247: 110.09631 | I247: 111.73661 | J247: 102.87354 | K247: 142.59239 | L247: 35.030098

Sheet Secteur Secondaire
A1: DIRECTION DE LA PREVISION ET DES ETUDES ECONOMIQUES
B3: =B247/B246-1 -> -0.0027715639 | C3: =C247/C246-1 -> -0.061808271 | D3: =D247/D246-1 -> -0.034246575 | E3: =E247/E246-1 -> -0.42649991 | F3: =F247/F246-1 -> 0.79262082 | G3: =G247/G246-1 -> 0.98505549 | H3: =H247/H246-1 -> -0.456704 | I3: =I247/I246-1 -> 1.1414931 | ... Y3: =Y247/Y246-1 -> 0.96556004
B4: PETROLE BRUT (PRODUCTION) | C4: Phosphates (PRODUCTION) | F4: Produits arachidiers (PRODUCTION) | J4: OR (PRODUCTION) | K4: Ventes d'électricité | P4: EAU | R4: CIMENT | U4: Produits chimiques (PRODUCTION) | W4: SEL | Z4: COTON
D5: phos. de calcium | E5: attapulgite | G5: huile brute | H5: huile raffinée | I5: tourteaux | L5: basse tension | M5: moyenne tension | N5: haute tension | O5: Exportations | P5: Production | Q5: Ventes | R5: Production | S5: Ventes locales | T5: Exportations | U5: Acide phosphorique | V5: Engrais solides | W5: Production | X5: Ventes locales | Y5: Exportations | Z5: Production | AA5: Ventes locales | AB5: Exportations
B6: (millions bbl) | C6: (1000 tonnes) | D6: (1000 tonnes) | E6: (1000 tonnes) | F6: (1000 tonnes) | G6: (1000 tonnes) | H6: (1000 tonnes) | I6: (1000 tonnes) | J6: (Kilogramme) | K6: (millions kwh) | L6: (millions kwh) | M6: (millions kwh) | N6: (millions kwh) | O6: (millions kwh) | P6: (millions m3) | Q6: (millions m3) | R6: (1000 tonnes) | S6: (1000 tonnes) | T6: (1000 tonnes) | U6: (1000 tonnes) | V6: (1000 tonnes) | W6: (tonnes) | X6: (tonnes) | Y6: (tonnes) | Z6: (tonnes) | AA6: (tonnes) | AB6: (tonnes)
A7: 38718 | C7: =D7+E7 -> 132.542 | D7: 119 | E7: 13.542 | F7: =G7+H7+I7 -> 5.156 | G7: 0 | H7: 5.156 | I7: 0 | K7: =SUM(L7:O7) -> 133.526 | L7: 87.019 | M7: 30 | N7: 16.507 | P7: 11.341169 | R7: =137.655+93.5461 -> 231.2011 | S7: =108.537+8.1739 -> 116.7109 | T7: =22.387+86.218 -> 108.605 | U7: 41.703 | V7: 1.87 | W7: 15493.7 | X7: 2074 | Y7: 13419 | Z7: 6266 | AA7: 58.2 | AB7: 395.9
A8: 38749 | C8: =D8+E8 -> 114.942 | D8: 100 | E8: 14.942 | F8: =G8+H8+I8 -> 8.568 | G8: 1.207 | H8: 6.019 | I8: 1.342 | K8: =SUM(L8:O8) -> 133.704 | L8: 82.717 | M8: 35.841 | N8: 15.146 | P8: 9.862406 | Q8: 16.808839 | R8: =92.2153+139.647 -> 231.8623 | S8: =57.2813+122.808 -> 180.0893 | T8: =37.0077+20.967 -> 57.9747 | U8: 26.695 | V8: 2.696 | W8: 16811 | X8: 2358 | Y8: 14453 | Z8: 5108 | AA8: 83.2 | AB8: 1560.4
A9: 38777 | C9: =D9+E9 -> 11.289 | D9: 0 | E9: 11.289 | F9: =G9+H9+I9 -> 22.755 | G9: 6.812 | H9: 7.425 | I9: 8.518 | K9: =SUM(L9:O9) -> 128.638 | L9: 79.245 | M9: 37.511 | N9: 11.882 | P9: 10.804051 | R9: =158.755+101.2842 -> 260.0392 | S9: =138.406+63.1343 -> 201.5403 | T9: =22.278+39.5518 -> 61.8298 | U9: 4.785 | V9: 2.784 | W9: 18405 | X9: 1919 | Y9: 16486 | Z9: 4680.3 | AA9: 55.5 | AB9: 4007
A10: 38808 | C10: =D10+E10 -> 9.451 | D10: 0 | E10: 9.451 | F10: =G10+H10+I10 -> 20.073 | G10: 5.009 | H10: 9.301 | I10: 5.763 | K10: =SUM(L10:O10) -> 118.925 | L10: 72.599 | M10: 35.183 | N10: 11.143 | P10: 10.769033 | Q10: 17.236263 | R10: =181.964+93.2032 -> 275.1672 | S10: =144.703+54.6277 -> 199.3307 | T10: =36.068+35.1807 -> 71.2487 | U10: 0 | V10: 2.093 | W10: 16801 | X10: 2197 | Y10: 14604 | Z10: 391.2 | AA10: 80.2 | AB10: 2400
A11: 38838 | C11: =D11+E11 -> 131.588 | D11: 121 | E11: 10.588 | F11: =G11+H11+I11 -> 19.989 | G11: 6.044 | H11: 8.346 | I11: 5.599 | K11: =SUM(L11:O11) -> 132.01 | L11: 76.559 | M11: 38.107 | N11: 17.344 | P11: 11.198387 | R11: =191.072+101.9546 -> 293.0266 | S11: =155.942+66.2339 -> 222.1759 | T11: =39.7+37.5798 -> 77.2798 | U11: 13.224 | V11: 2.845 | W11: 20128 | X11: 2368 | Y11: 17760 | Z11: 0 | AA11: 117.9 | AB11: 707.4
A12: 38869 | C12: =D12+E12 -> 64.229 | D12: 50 | E12: 14.229 | F12: =G12+H12+I12 -> 20.387 | G12: 7.076 | H12: 9.823 | I12: 3.488 | K12: =SUM(L12:O12) -> 134.494 | L12: 80.36 | M12: 41.105 | N12: 13.029 | P12: 11.056102 | Q12: 17.920596 | R12: =155.758+98.5608 -> 254.3188 | S12: =131.296+61.2307 -> 192.5267 | T12: =35.2253+29.515 -> 64.7403 | U12: 12.931 | V12: 3.521 | W12: 12726 | X12: 1910 | Y12: 10816 | Z12: 0 | AA12: 107.2 | AB12: 852.8
A13: 38899 | C13: =D13+E13 -> 12.347 | D13: 0 | E13: 12.347 | F13: =G13+H13+I13 -> 24.276 | G13: 6.41 | H13: 6.707 | I13: 11.159 | K13: =SUM(L13:O13) -> 147.465 | L13: 92.05 | M13: 45.098 | N13: 10.317 | P13: 11.135407 | R13: =101.2427+133.271 -> 234.5137 | S13: =108.666+69.7141 -> 178.3801 | T13: =31.9995+19.075 -> 51.0745 | U13: 0 | V13: 4.729 | W13: 17157 | X13: 1982 | Y13: 15175 | Z13: 0 | AA13: 73.1 | AB13: 1259.3
A14: 38930 | C14: =D14+E14 -> 16.741 | D14: 0 | E14: 16.741 | F14: =G14+H14+I14 -> 20.746 | G14: 5.121 | H14: 7.738 | I14: 7.887 | K14: =SUM(L14:O14) -> 147.493 | L14: 92.461 | M14: 46.028 | N14: 9.004 | P14: 10.48293 | Q14: 17.207542 | R14: =142.314+103.9511 -> 246.2651 | S14: =69.5017+127.057 -> 196.5587 | T14: =22.557+36.5121 -> 59.0691 | U14: 0 | V14: 1.684 | W14: 15808 | X14: 2365 | Y14: 13443 | Z14: 0 | AA14: 64.1 | AB14: 1786
A15: 38961 | C15: =D15+E15 -> 10.504 | D15: 0 | E15: 10.504 | F15: =G15+H15+I15 -> 14.972 | G15: 2.996 | H15: 7.182 | I15: 4.794 | K15: =SUM(L15:O15) -> 155.872 | L15: 102.654 | M15: 44.465 | N15: 8.753 | P15: 10.101425 | R15: =121.382+96.091 -> 217.473 | S15: =97.367+56.7947 -> 154.1617 | T15: =27.081+34.6539 -> 61.7349 | U15: 2.314 | V15: 0 | W15: 13745 | X15: 2173 | Y15: 11572 | Z15: 0 | AA15: 43.7 | AB15: 2871.2
A16: 38991 | C16: =D16+E16 -> 58.115 | D16: 51 | E16: 7.115 | F16: =G16+H16+I16 -> 24.362 | G16: 7.541 | H16: 8.185 | I16: 8.636 | K16: =SUM(L16:O16) -> 151.564 | L16: 96.131 | M16: 42.321 | N16: 13.112 | P16: 10.731093 | Q16: 17.008616 | R16: =76.5177+123.391 -> 199.9087 | S16: =42.5112+93.823 -> 136.3342 | T16: =29.8152+25.673 -> 55.4882 | U16: 28.573 | V16: 0 | W16: 14813 | X16: 2146 | Y16: 12667 | Z16: 0 | AA16: 51.2 | AB16: 1869.6
A17: 39022 | C17: =D17+E17 -> 76.583 | D17: 66 | E17: 10.583 | F17: =G17+H17+I17 -> 30.188 | G17: 9.153 | H17: 9.995 | I17: 11.04 | K17: =SUM(L17:O17) -> 160.998 | L17: 101.109 | M17: 45.17 | N17: 14.719 | P17: 10.936115 | R17: =138.824+85.3385 -> 224.1625 | S17: =107.496+55.3475 -> 162.8435 | T17: =39.0071+34.847 -> 73.8541 | U17: 28.527 | V17: 4.647 | W17: 14847 | X17: 2719 | Y17: 12128 | Z17: 0 | AA17: 59 | AB17: 956
A18: 39052 | C18: =D18+E18 -> 96.991 | D18: 77 | E18: 19.991 | F18: =G18+H18+I18 -> 22.988 | G18: 6.133 | H18: 8.859 | I18: 7.996 | K18: =SUM(L18:O18) -> 166.912 | L18: 103.716 | M18: 46.473 | N18: 16.723 | P18: 11.041675 | Q18: 17.49626 | R18: =95.969+169.875 -> 265.844 | S18: =57.381+133.29 -> 190.671 | T18: =30.563+38.1869 -> 68.7499 | U18: 21.608 | V18: 6.564 | W18: 21826 | X18: 2637 | Y18: 19189 | Z18: 2522 | AA18: 15 | AB18: 253.6
A19: 39083 | C19: =D19+E19 -> 82.152 | D19: 72 | E19: 10.152 | F19: =G19+H19+I19 -> 15.027 | G19: 4.239 | H19: 5.358 | I19: 5.43 | K19: =SUM(L19:O19) -> 120.104 | L19: 88.675 | M19: 14.778 | N19: 16.651 | P19: 11.695173 | R19: =155.983+94.8327 -> 250.8157 | S19: =131.307+60.4849 -> 191.7919 | T19: =36.473+25.764 -> 62.237 | U19: 20.348 | V19: 7.406 | W19: 14074 | X19: 2823 | Y19: 11251 | Z19: 7499.5 | AA19: 1.6 | AB19: 597.5
A20: 39114 | C20: =D20+E20 -> 70.25 | D20: 60 | E20: 10.25 | F20: =G20+H20+I20 -> 24.973 | G20: 6.652 | H20: 12.13 | I20: 6.191 | K20: =SUM(L20:O20) -> 133.348 | L20: 83.925 | M20: 36.871 | N20: 12.552 | P20: 10.417437 | Q20: 17.202009 | R20: =148.808+89.7297 -> 238.5377 | S20: =119.112+54.175 -> 173.287 | T20: =28.083+35.1925 -> 63.2755 | U20: 14.286 | V20: 0 | W20: 19005 | X20: 2710 | Y20: 16295 | Z20: 5222 | AA20: 20 | AB20: 778.2
A21: 39142 | C21: =D21+E21 -> 56.874 | D21: 50 | E21: 6.874 | F21: =G21+H21+I21 -> 25.197 | G21: 7.399 | H21: =8.998+0.16 -> 9.158 | I21: 8.64 | K21: =SUM(L21:O21) -> 133.085 | L21: 84.183 | M21: 40.008 | N21: 8.894 | P21: 11.688113 | R21: =137.341+99.612 -> 236.953 | S21: =115.718+67.0727 -> 182.7907 | T21: =23.827+33.3453 -> 57.1723 | U21: 22.349 | V21: 5.666 | W21: 21544 | X21: 2673 | Y21: 18871 | Z21: 13491.2 | AA21: 48 | AB21: 2066.2
A22: 39173 | C22: =D22+E22 -> 105.301 | D22: 96 | E22: 9.301 | F22: =G22+H22+I22 -> 23.675 | G22: 8.697 | H22: =3.673+0.345 -> 4.018 | I22: 10.96 | K22: =SUM(L22:O22) -> 130.345 | L22: 80.783 | M22: 40.422 | N22: 9.14 | P22: 11.202731 | Q22: 17.968486 | R22: =174.258+96.9052 -> 271.1632 | S22: =137.188+59.3145 -> 196.5025 | T22: =33.404+31.0476 -> 64.4516 | U22: 26.493 | V22: 5.754 | W22: 14575 | X22: 2738 | Y22: 11837 | Z22: 8282 | AA22: 39.5 | AB22: 239.7
A23: 39203 | C23: =D23+E23 -> 80.725 | D23: 70.3 | E23: 10.425 | F23: =G23+H23+I23 -> 24.241 | G23: 8.156 | H23: 6.824 | I23: 9.261 | K23: =SUM(L23:O23) -> 140.557 | L23: 88.816 | M23: 42.606 | N23: 9.135 | P23: 11.712704 | R23: =90.3906+161.549 -> 251.9396 | S23: =61.0006+134.069 -> 195.0696 | T23: =30.5479+30.586 -> 61.1339 | U23: 29.079 | V23: 10.96 | W23: 17231 | X23: 3252 | Y23: 13979 | Z23: 0 | AA23: 34 | AB23: 1579.4
A24: 39234 | C24: =D24+E24 -> 70.423 | D24: 56 | E24: 14.423 | F24: =G24+H24+I24 -> 21.025 | G24: 7.684 | H24: =3.306+0.185 -> 3.491 | I24: 9.85 | K24: =SUM(L24:O24) -> 135.758 | L24: 86.17 | M24: 40.428 | N24: 9.16 | P24: 11.351162 | Q24: 18.061358 | R24: =174.751+66.7315 -> 241.4825 | S24: =146.719+49.4817 -> 196.2007 | T24: =22.657+26.26 -> 48.917 | U24: 17.162 | V24: 12.513 | W24: 18468 | X24: 2094 | Y24: 16374 | Z24: 0 | AA24: 20.6 | AB24: 2740.5
A25: 39264 | C25: =D25+E25 -> 85.507 | D25: 73 | E25: 12.507 | F25: =G25+H25+I25 -> 11.048 | G25: 0.025 | H25: 9.359 | I25: 1.664 | K25: =SUM(L25:O25) -> 143.568 | L25: 88.297 | M25: 44.522 | N25: 10.749 | P25: 11.366838 | R25: =174.364+91.2834 -> 265.6474 | S25: =149.177+60.299 -> 209.476 | T25: =27.476+27.0548 -> 54.5308 | U25: 17.932 | V25: 8.84 | W25: 15908 | X25: 2615.8 | Y25: 13292 | Z25: 0 | AA25: 6 | AB25: 2811.4
A26: 39295 | C26: =D26+E26 -> 62.124 | D26: 51 | E26: 11.124 | F26: =G26+H26+I26 -> 12.348 | G26: 2.077 | H26: =8.766+0.101 -> 8.867 | I26: 1.404 | K26: =SUM(L26:O26) -> 151.284 | L26: 97.939 | M26: 44.026 | N26: 9.319 | P26: 10.928509 | Q26: 17.840605 | R26: =101.15234+177.67 -> 278.82234 | S26: =0.25+65.84362+137.1 -> 203.19362 | T26: =0.385+36.89185+33.5 -> 70.77685 | U26: 15.966 | V26: 7.245 | W26: =(W25+W24)/2 -> 17188 | X26: =(X25+X24)/2 -> 2354.9 | Y26: =(Y25+Y24)/2 -> 14833 | Z26: 0 | AA26: 15.3 | AB26: 219.8
A27: 39326 | C27: =D27+E27 -> 57.363 | D27: 47 | E27: 10.363 | F27: =G27+H27+I27 -> 8.343 | G27: 0 | H27: 7.582 | I27: 0.761 | K27: =SUM(L27:O27) -> 154.158 | L27: 99.644 | M27: 45.519 | N27: 8.995 | P27: 10.645413 | R27: =159.362+92.461 -> 251.823 | S27: =131.924+48.452 -> 180.376 | T27: =25.472+34.3461 -> 59.8181 | U27: 15.471 | V27: 4.105 | W27: 17401 | X27: 2390 | Y27: 15011 | Z27: 0 | AA27: 0.2 | AB27: 3.5
A28: 39356 | C28: =D28+E28 -> 57.188 | D28: 44 | E28: 13.188 | F28: =G28+H28+I28 -> 8.262 | G28: 0 | H28: =7.767+0.201 -> 7.968 | I28: 0.294 | K28: =SUM(L28:O28) -> 164.704 | L28: 107.103 | M28: 47.781 | N28: 9.82 | P28: 11.404618 | Q28: 18.499164 | R28: =150.6+82.3423 -> 232.9423 | S28: =121.9+48.2346 -> 170.1346 | T28: =28.7+37.8169 -> 66.5169 | U28: 15.156 | V28: 4.997 | W28: 18133 | X28: 2537 | Y28: 15596 | Z28: 0 | AA28: 20.3 | AB28: 3491.2
A29: 39387 | C29: =D29+E29 -> 67.506 | D29: 60 | E29: 7.506 | F29: =G29+H29+I29 -> 8.192 | G29: 0 | H29: 8.192 | I29: 0 | K29: =SUM(L29:O29) -> 167.609 | L29: 110.664 | M29: 46.967 | N29: 9.978 | P29: 11.499036 | R29: =167.813+97.7169 -> 265.5299 | S29: =140.914+50.7265 -> 191.6405 | T29: =30.76+51.3545 -> 82.1145 | U29: 19.749 | V29: 4.526 | W29: 20217 | X29: 2404 | Y29: 17813 | Z29: 0 | AA29: 5.7 | AB29: 661.2
A30: 39417 | C30: =D30+E30 -> 56.391 | D30: 38.9 | E30: 17.491 | F30: =G30+H30+I30 -> 9.285 | G30: 0 | H30: 9.285 | I30: 0 | K30: =SUM(L30:O30) -> 163.826 | L30: 108.824 | M30: 47.555 | N30: 7.447 | P30: 11.700825 | Q30: 18.59971 | R30: =162.687+1.32506+90.37428+0.03+0.50275 -> 254.91909 | S30: =125.125+44.72418+0.9084+0.71786 -> 171.47544 | T30: =35.141+0.485+42.51735+0.03 -> 78.17335 | U30: 20.137 | V30: 10.222 | W30: 17225 | X30: 2100 | Y30: 15125 | Z30: 1203.23 | AA30: 19.053 | AB30: 220
A31: 39448 | C31: =D31+E31 -> 68.349 | D31: 55 | E31: 13.349 | F31: =G31+H31+I31 -> 14.356 | G31: 3.585 | H31: =8.581+0.144 -> 8.725 | I31: 2.046 | K31: =SUM(L31:O31) -> 158.829 | L31: 101.575 | M31: 48.439 | N31: 8.815 | P31: 12.499291 | Q31: 9.9527397 | R31: =161.108+102.9307 -> 264.0387 | S31: =139.412+0.59965+58.53935+1.95952 -> 200.51052 | T31: =31.778+1.53+42.4453+0.04 -> 75.7933 | U31: 16.039 | V31: 3.42 | W31: 25053 | X31: 3603 | Y31: 19742.1 | Z31: 5385.1 | AA31: 16.1 | AB31: 1628.8
A32: 39479 | C32: =D32+E32 -> 74.042 | D32: 54 | E32: 20.042 | F32: =G32+H32+I32 -> 19.913 | G32: 4.727 | H32: =8.462+0 -> 8.462 | I32: 6.724 | K32: =SUM(L32:O32) -> 134.796 | L32: 91.941 | M32: 34.307 | N32: 8.548 | P32: 11.232945 | Q32: 8.9511401 | R32: =98.5763+167.819 -> 266.3953 | S32: =134.877+1.4052+55.00282+1.70105 -> 192.98607 | T32: =25.186+1.034+39.6577+0.08 -> 65.9577 | U32: 16.679 | V32: 5.397 | W32: 22370 | X32: 2997 | Y32: 22370 | Z32: 4333.2 | AA32: 14.7 | AB32: 1494.2
A33: 39508 | C33: =D33+E33 -> 57.504 | D33: 40 | E33: 17.504 | F33: =G33+H33+I33 -> 9.946 | G33: 0.332 | H33: =7.533+0.189 -> 7.722 | I33: 1.892 | K33: =SUM(L33:O33) -> 141.615 | L33: 86.809 | M33: 46.551 | N33: 8.255 | P33: 11.781936 | Q33: 9.1682036 | R33: =147.283+1.61572+97.34844+0.7994 -> 247.04656 | S33: =133.368+1.58002+55.77642+0.764 -> 191.48844 | T33: =13.197+0.046+37.2446+0.03 -> 50.5176 | U33: 14.779 | V33: 0 | W33: 19361 | X33: 2994 | Y33: 16367 | Z33: 3930.7 | AA33: 9.3 | AB33: 1622.3
A34: 39539 | C34: =D34+E34 -> 54.361 | D34: 44 | E34: 10.361 | F34: =G34+H34+I34 -> 11.547 | G34: 2.915 | H34: 4.367 | I34: 4.265 | K34: =SUM(L34:O34) -> 151.661 | L34: 100.04 | M34: 43.069 | N34: 8.552 | P34: 11.569475 | Q34: 9.2571065 | R34: =168.527+102.2512 -> 270.7782 | S34: =68.3068+152.295 -> 220.6018 | T34: =38.0999+22.471 -> 60.5709 | U34: 8.967 | V34: 7.358 | W34: 24009 | X34: 3323 | Y34: 20686 | Z34: 593 | AA34: 18.8 | AB34: 1718.3
A35: 39569 | C35: =D35+E35 -> 51.063 | D35: 38 | E35: 13.063 | F35: =G35+H35+I35 -> 7.114 | G35: 0 | H35: 6.922 | I35: 0.192 | K35: =SUM(L35:O35) -> 158.734 | L35: 104.725 | M35: 46.217 | N35: 7.792 | P35: 12.085955 | Q35: 9.7079807 | R35: =101.4756+174.557 -> 276.0326 | S35: =149.11+66.5737 -> 215.6837 | T35: =24.974+36.6496 -> 61.6236 | U35: 17.969 | V35: 12.178 | W35: 19698 | X35: 2565 | Y35: 17133 | Z35: 0 | AA35: 12.1 | AB35: 1508.7
A36: 39600 | C36: =D36+E36 -> 53.126 | D36: 37 | E36: 16.126 | F36: =G36+H36+I36 -> 3.149 | G36: 0 | H36: 3.075 | I36: 0.074 | K36: =SUM(L36:O36) -> 152.999 | L36: 99.329 | M36: 45.362 | N36: 8.308 | P36: 11.157268 | Q36: 8.9484204 | R36: =179.232+98.9123 -> 278.1443 | S36: =61.7947+143.044 -> 204.8387 | T36: =33.184+35.3751 -> 68.5591 | U36: 12.199 | V36: 13.232 | W36: 18669 | X36: 2988 | Y36: 15681 | Z36: 0 | AA36: 19.5 | AB36: 2010
A37: 39630 | C37: =D37+E37 -> 60.766 | D37: 51 | E37: 9.766 | F37: =G37+H37+I37 -> 5.134 | G37: 0 | H37: 5.134 | I37: 0 | K37: =SUM(L37:O37) -> 150.915 | L37: 94.252 | M37: 48.046 | N37: 8.617 | P37: 11.699402 | Q37: 9.2218857 | R37: =179.242+2.35648+95.9806+0.59861 -> 278.17769 | S37: =1.03648+61.26147+0.66+144.331 -> 207.28895 | T37: =37.387+1.32+36.4715 -> 75.1785 | U37: 19.338 | V37: 9.088 | W37: 19641 | X37: 3124 | Y37: 16517 | Z37: 0 | AA37: 17.4 | AB37: 1274
A38: 39661 | C38: =D38+E38 -> 50.223 | D38: 41 | E38: 9.223 | F38: =G38+H38+I38 -> 8.865 | G38: 0.736 | H38: 7.235 | I38: 0.894 | K38: =SUM(L38:O38) -> 165.378 | L38: 111.31 | M38: 46.67 | N38: 7.398 | P38: 10.993662 | Q38: 8.7721994 | R38: =168.846+86.4564 -> 255.3024 | S38: =43.2254+132.106 -> 175.3314 | T38: =40.4126+33.631 -> 74.0436 | U38: 13.665 | V38: 0 | W38: 14569 | X38: 2537 | Y38: 12032 | Z38: 0 | AA38: 9.5 | AB38: 1691
A39: 39692 | C39: =D39+E39 -> 47.848 | D39: 35 | E39: 12.848 | F39: =G39+H39+I39 -> 8.55 | G39: 1.119 | H39: 5.97 | I39: 1.461 | K39: =SUM(L39:O39) -> 156.474 | L39: 102.276 | M39: 46.731 | N39: 7.467 | P39: 10.878314 | Q39: 8.6263999 | R39: =137.783+1.73113+93.49888+0.015 -> 233.02801 | S39: =0.53659+34.55327+0.01+110.744 -> 145.84386 | T39: =25.509+1.03+56.9197 -> 83.4587 | U39: 13.867 | V39: 0 | W39: 18707 | X39: 3475 | Y39: 15232 | Z39: 0 | AA39: 11.65 | AB39: 722.806
A40: 39722 | C40: =D40+E40 -> 50.08 | D40: 43 | E40: =5.91+1.17 -> 7.08 | F40: =G40+H40+I40 -> 3.632 | G40: 0 | H40: 3.632 | I40: 0 | K40: =SUM(L40:O40) -> 166.646 | L40: 114.442 | M40: 43.411 | N40: 8.793 | P40: 11.669107 | Q40: 9.3158463 | R40: =91.7503+140.798 -> 232.5483 | S40: =121.348+33.7642 -> 155.1122 | T40: =48.8697+21.871 -> 70.7407 | U40: 12.61 | V40: 0 | W40: 17310 | X40: 3074 | Y40: 14236 | Z40: 0 | AA40: 12.747 | AB40: 689.425
A41: 39753 | C41: =D41+E41 -> 72.787 | D41: 50 | E41: =19.66+3.127 -> 22.787 | F41: =G41+H41+I41 -> 8.855 | G41: 0 | H41: 8.855 | I41: 0 | K41: =SUM(L41:O41) -> 164.618 | L41: 110.278 | M41: 46.188 | N41: 8.152 | P41: 11.374741 | Q41: 9.0510946 | R41: =179.8+86.5637 -> 266.3637 | S41: =37.1495+144.388 -> 181.5375 | T41: =46.1088+25.053 -> 71.1618 | U41: 9.477 | V41: 0 | W41: 20424 | X41: 2934 | Y41: 17490 | Z41: 0 | AA41: 0.374 | AB41: 400
A42: 39783 | C42: =D42+E42 -> 76.892 | D42: 64 | E42: =12.256+0.636 -> 12.892 | F42: =G42+H42+I42 -> 8.193 | G42: 0 | H42: 8.193 | I42: 0 | K42: =SUM(L42:O42) -> 164.071 | L42: 107.54 | M42: 47.449 | N42: 9.082 | P42: 11.202268 | Q42: 9.614971 | R42: =143.207+73.6481 -> 216.8551 | S42: =38.6082+125.012 -> 163.6202 | T42: =42.7001+25.473 -> 68.1731 | U42: 24.736 | V42: 0 | W42: 20765 | X42: 3255 | Y42: 17510 | Z42: 0 | AA42: 7.337 | AB42: 0
A43: 39814 | C43: =D43+E43 -> 70.731 | D43: 55 | E43: 15.731 | F43: =G43+H43+I43 -> 20.961 | G43: 7.179 | H43: 6.782 | I43: 7 | K43: =SUM(L43:O43) -> 158.23 | L43: 101.814 | M43: 48.164 | N43: 8.252 | P43: 12.122531 | Q43: 9.8431106 | R43: 269.9633 | S43: 192.8531 | T43: 91.1702 | U43: 22.79 | V43: 2.692 | W43: 19882 | X43: 3179 | Y43: 16672.7 | Z43: 2526.467 | AA43: 0 | AB43: 40
A44: 39845 | C44: =D44+E44 -> 75.273 | D44: 56 | E44: 19.273 | F44: =G44+H44+I44 -> 24.316 | G44: 8.155 | H44: =7.547+0 -> 7.547 | I44: 8.614 | K44: =SUM(L44:O44) -> 133.513 | L44: 92.894 | M44: 34.039 | N44: 6.58 | P44: 10.492427 | Q44: 8.5250073 | R44: 268.3642 | S44: 181.5657 | T44: 87.0383 | U44: 20.224 | V44: 6.914 | W44: 14459 | X44: 2827 | Y44: 11632 | Z44: 4049.337 | AA44: 0 | AB44: 0
A45: 39873 | C45: =D45+E45 -> 89.731 | D45: 77 | E45: =12.731 -> 12.731 | F45: =G45+H45+I45 -> 17.706 | G45: 4.983 | H45: =5.793+0.187 -> 5.98 | I45: 6.743 | K45: =SUM(L45:O45) -> 142.92 | L45: 90.426 | M45: 42.873 | N45: 9.621 | P45: 11.876301 | Q45: 9.1741294 | R45: 301.5731 | S45: 201.3075 | T45: 97.0551 | U45: 26.013 | V45: 9.738 | W45: 21963 | X45: 3799 | Y45: 18164 | Z45: 3399.282 | AA45: 6 | AB45: 0
A46: 39904 | C46: =D46+E46 -> 84.611 | D46: 68 | E46: 16.611 | F46: =G46+H46+I46 -> 5.391 | G46: 0 | H46: =5.391+0 -> 5.391 | I46: 0 | K46: =SUM(L46:O46) -> 134.804 | L46: 86.322 | M46: 40.142 | N46: 8.34 | P46: 11.497031 | Q46: 9.1591554 | R46: 297.2 | S46: 207.75049 | T46: 93.08235 | U46: 21.1244 | V46: 1.139 | W46: 17939 | X46: 3515 | Y46: 14424 | Z46: 1087.8 | AA46: 0 | AB46: 240.1
A47: 39934 | C47: =D47+E47 -> 104.887 | D47: 92 | E47: 12.887 | F47: =G47+H47+I47 -> 10.505 | G47: 1.753 | H47: =6.429+0.143 -> 6.572 | I47: 2.18 | K47: =SUM(L47:O47) -> 148.868 | L47: 93.277 | M47: 44.862 | N47: 10.729 | P47: 11.953486 | Q47: 9.5403662 | R47: 287.6195 | S47: 198.9654 | T47: 84.018 | U47: 21.829 | V47: 7.807 | W47: 21863 | X47: 2508 | Y47: 19355 | Z47: 0 | AA47: 16.5 | AB47: 1062.9
A48: 39965 | C48: =D48+E48 -> 98.528 | D48: 88 | E48: 10.528 | F48: =G48+H48+I48 -> 15.0134 | G48: 3.707 | H48: =5.683+0 -> 5.683 | I48: 5.6234 | K48: =SUM(L48:O48) -> 157.824 | L48: 100.256 | M48: 47.093 | N48: 10.475 | P48: 11.763409 | Q48: 8.3418751 | R48: 291.172 | S48: 210.0895 | T48: 80.7296 | U48: 25.066 | V48: 5.417 | W48: 14172 | X48: 2941 | Y48: 11231 | Z48: 0 | AA48: 10.6 | AB48: 325.4
A49: 39995 | C49: =D49+E49 -> 85.992 | D49: 76 | E49: 9.992 | F49: =G49+H49+I49 -> 4.804 | G49: 0.137 | H49: =4.603+0 -> 4.603 | I49: 0.064 | K49: =SUM(L49:O49) -> 164.339 | L49: 100.984 | M49: 52.78 | N49: 10.575 | P49: 11.790399 | Q49: 9.2574955 | R49: 307.3069 | S49: 219.3305 | T49: 83.6306 | U49: 23.601 | V49: 4.56 | W49: 21389 | X49: 3202 | Y49: 18187 | Z49: 0 | AA49: 1.4 | AB49: 449.5
A50: 40026 | C50: =D50+E50 -> 74.078 | D50: 59 | E50: 15.078 | F50: =G50+H50+I50 -> 8.869 | G50: 2.002 | H50: =4.582+0.281 -> 4.863 | I50: 2.004 | K50: =SUM(L50:O50) -> 173.29 | L50: 113.003 | M50: 50.018 | N50: 10.269 | P50: 11.141723 | Q50: 8.7855299 | R50: =256.2165 -> 256.2165 | S50: 168.82296 | T50: 73.0694 | U50: 17.055 | V50: 2.486 | W50: 16793 | X50: 2736 | Y50: 14057 | Z50: 0 | AA50: 0.214 | AB50: 1235.2
A51: 40057 | C51: =D51+E51 -> 76.056 | D51: 68 | E51: 8.056 | F51: =G51+H51+I51 -> 6.624 | G51: 1.113 | H51: =4.434+0 -> 4.434 | I51: 1.077 | K51: =SUM(L51:O51) -> 172.409 | L51: 111.113 | M51: 50.653 | N51: 10.643 | P51: 11.040756 | Q51: 9.4750986 | R51: 188.5243 | S51: 129.4854 | T51: 67.5398 | U51: 20.0293 | V51: 0.975 | W51: 19759 | X51: 2564 | Y51: 17195 | Z51: 0 | AA51: 0 | AB51: 1223.7
A52: 40087 | C52: =D52+E52 -> 92.048 | D52: 72 | E52: 20.048 | F52: =G52+H52+I52 -> 8.465 | G52: 0 | H52: 8.271 | I52: 0.194 | K52: =SUM(L52:O52) -> 175.5923 | L52: 120.036 | M52: 43.775 | N52: 11.7813 | P52: 12.295843 | Q52: 9.7228695 | R52: 275.8737 | S52: 186.6297 | T52: 97.6243 | U52: 29.14 | V52: 1.981 | W52: 18376 | X52: 3092 | Y52: 15284 | Z52: 0 | AA52: 0 | AB52: 2707.6
A53: 40118 | C53: =D53+E53 -> 115.065 | D53: 94 | E53: 21.065 | F53: =G53+H53+I53 -> 5.368 | G53: 0 | H53: =5.368+0 -> 5.368 | I53: 0 | K53: =SUM(L53:O53) -> 193.396 | L53: 125.812 | M53: 56.08 | N53: 11.504 | P53: 11.875029 | Q53: 9.3585005 | R53: 242.8402 | S53: 156.7361 | T53: 84.6641 | U53: 29.077 | V53: 0 | W53: 12157 | X53: 2528 | Y53: 9629 | Z53: =AVERAGE(Z50:Z52) -> 0 | AA53: =AVERAGE(AA50:AA52) -> 0.071333333 | AB53: 529.1
A54: 40148 | C54: =D54+E54 -> 116.744 | D54: 98 | E54: =18.298+0.446 -> 18.744 | F54: =G54+H54+I54 -> 7.3315 | G54: =AVERAGE(G50:G53) -> 0.77875 | H54: =AVERAGE(H50:H53) -> 5.734 | I54: =AVERAGE(I50:I53) -> 0.81875 | K54: =SUM(L54:O54) -> 187.223 | L54: 119.836 | M54: 54.509 | N54: 12.878 | P54: 11.8842 | Q54: 9.5501541 | R54: 324.9247 | S54: 209.5489 | T54: 113.1853 | U54: 27.286 | V54: 0 | W54: 23545 | X54: 4015 | Y54: 19530 | Z54: 356.5 | AA54: 0.2 | AB54: 1816.3
A55: 40179 | C55: =D55+E55 -> 118.702 | D55: 97 | E55: 21.702 | F55: =G55+H55+I55 -> 23.689 | G55: 9.49 | H55: =3.548+0.918 -> 4.466 | I55: 9.733 | K55: =SUM(L55:O55) -> 174.80983 | L55: 107.16598 | M55: 55.76362 | N55: 11.88023 | P55: 12.955447 | Q55: 10.275378 | R55: 355.491 | S55: 214.0947 | T55: 132.1624 | U55: 43.001 | V55: 0 | W55: 16744 | X55: 3520 | Y55: 13224 | Z55: 3342.3 | AA55: 2.6 | AB55: 597.2
A56: 40210 | C56: =D56+E56 -> 105.101 | D56: 87 | E56: 18.101 | F56: =G56+H56+I56 -> 6.363 | G56: 1.957 | H56: 2.339 | I56: 2.067 | K56: =SUM(L56:O56) -> 151.24409 | L56: 102.36495 | M56: 39.01369 | N56: 9.86545 | P56: 11.305816 | Q56: 8.9160349 | R56: =174.252+129.6002 -> 303.8522 | S56: 188.889 | T56: 112.1417 | U56: 23.694 | V56: 0 | W56: 18212 | X56: 3378 | Y56: 14834 | Z56: 3307.2 | AA56: 0.01 | AB56: 690.5
A57: 40238 | C57: =D57+E57 -> 107.127 | D57: 91 | E57: 16.127 | F57: =G57+H57+I57 -> 18.267 | G57: 5.895 | H57: =4.963+0.519 -> 5.482 | I57: 6.89 | K57: =SUM(L57:O57) -> 157.94458 | L57: 97.58185 | M57: 49.12695 | N57: 11.23578 | P57: 12.682116 | Q57: 9.954119 | R57: 370.416 | S57: 234.4961 | T57: 147.0185 | U57: 24.799 | V57: 0 | W57: 20145 | X57: 3337 | Y57: 16808 | Z57: 998 | AA57: 0 | AB57: 1881.4
A58: 40269 | C58: =D58+E58 -> 110.367 | D58: 100 | E58: =10.175+0.192 -> 10.367 | F58: =G58+H58+I58 -> 18.296384 | G58: 6.171 | H58: =2.419+0.368974 -> 2.787974 | I58: 9.33741 | K58: =SUM(L58:O58) -> 159.47273 | L58: 99.99249 | M58: 47.35464 | N58: 12.1256 | P58: 12.407839 | Q58: 9.760821 | R58: 389.7902 | S58: 229.0602 | T58: 158.3301 | U58: 24.947 | V58: 3.807 | W58: 17535.5 | X58: 3422 | Y58: 14113.5 | Z58: 0 | AA58: 0 | AB58: =AVERAGE(AB55:AB57) -> 1056.3667
A59: 40299 | C59: =D59+E59 -> 105.15 | D59: 93 | E59: =11.582+0.568 -> 12.15 | F59: =G59+H59+I59 -> 19.515 | G59: 7.152 | H59: 3.978 | I59: 8.385 | K59: =SUM(L59:O59) -> 168.05948 | L59: 105.00928 | M59: 52.22841 | N59: 10.82179 | P59: 12.972622 | Q59: 10.159215 | R59: 391.9685 | S59: 235.2638 | T59: 153.2546 | U59: 28.046 | V59: 0 | W59: 16449.5 | X59: 3332 | Y59: 13117 | Z59: 0 | AA59: 0 | AB59: 2673.8
A60: 40330 | C60: =D60+E60 -> 104.46 | D60: 87 | E60: 17.46 | F60: =G60+H60+I60 -> 15.469 | G60: 4.728 | H60: =4.094+0.471 -> 4.565 | I60: 6.176 | K60: =SUM(L60:O60) -> 170.78887 | L60: 111.02443 | M60: 49.24998 | N60: 10.51446 | P60: 12.030995 | Q60: 8.991308 | R60: 385.4658 | S60: 233.6898 | T60: 157.666 | U60: 30.378 | V60: 12.28 | W60: 19769 | X60: 3242 | Y60: 16527 | Z60: 0 | AA60: 0 | AB60: 2446.9
A61: 40360 | C61: =D61+E61 -> 100.613 | D61: 83 | E61: 17.613 | F61: =G61+H61+I61 -> 13 | G61: 4.36 | H61: =4.492+1.263 -> 5.755 | I61: 2.885 | K61: =SUM(L61:O61) -> 171.20585 | L61: 107.4934 | M61: 53.28739 | N61: 10.42506 | P61: 12.071757 | Q61: 9.440256 | R61: 369.8087 | S61: 204.115 | T61: 150.2378 | U61: 22.88 | V61: 5.967 | W61: 19627 | X61: 3422 | Y61: 16205 | Z61: 0 | AA61: 0 | AB61: 346.7
A62: 40391 | C62: =D62+E62 -> 80.307 | D62: 62 | E62: 18.307 | F62: =G62+H62+I62 -> 6.762 | G62: 2.53 | H62: =3.177+1.055 -> 4.232 | I62: 0 | K62: =SUM(L62:O62) -> 179.52538 | L62: 114.67338 | M62: 54.08017 | N62: 10.77183 | P62: 12.064092 | Q62: 9.44625 | R62: 310.202 | S62: 171.5718 | T62: 138.3008 | U62: 13.045 | V62: 0 | W62: 19457 | X62: 3539 | Y62: 15918 | Z62: 0 | AA62: 0 | AB62: 199.9
A63: 40422 | C63: =D63+E63 -> 76.801 | D63: 68 | E63: =8.159+0.642 -> 8.801 | F63: =G63+H63+I63 -> 17.827 | G63: 3.876 | H63: 4.102 | I63: 9.849 | K63: =SUM(L63:O63) -> 173.30154 | L63: 112.34244 | M63: 51.63794 | N63: 9.32116 | P63: 12.03212 | Q63: 9.333063 | R63: 229.2484 | S63: 143.01 | T63: 105.3571 | U63: 20.029 | V63: 0.975 | W63: 19730 | X63: 3366 | Y63: 16364 | Z63: 0 | AA63: 0 | AB63: 49.8
A64: 40452 | C64: =D64+E64 -> 116.377 | D64: 98.075 | E64: =17.129+1.173 -> 18.302 | F64: =G64+H64+I64 -> 16.602 | G64: 4.671 | H64: =8.772+0.097 -> 8.869 | I64: 3.062 | K64: =SUM(L64:O64) -> 182.86821 | L64: 121.76282 | M64: 50.05443 | N64: 11.05096 | P64: 12.316797 | Q64: 9.615451 | R64: 336.4086 | S64: 176.8279 | T64: 143.806 | U64: 27.78 | V64: 0.482 | W64: 21610 | X64: 3426 | Y64: 18184 | Z64: 0 | AA64: 0 | AB64: 137.7
A65: 40483 | C65: =D65+E65 -> 130.663 | D65: 102 | E65: 28.663 | F65: =G65+H65+I65 -> 15.515 | G65: 1.922 | H65: =6.519+0 -> 6.519 | I65: 7.074 | K65: =SUM(L65:O65) -> 185.87295 | L65: 121.21305 | M65: 53.32679 | N65: 11.33311 | P65: 12.256435 | Q65: 9.748985 | R65: =275.8424 -> 275.8424 | S65: 153.435 | T65: 117.3336 | U65: 30.275 | V65: 13.61 | W65: 19940 | X65: 3534 | Y65: 16406 | Z65: 0 | AA65: 0 | AB65: 0
A66: 40513 | C66: =D66+E66 -> 123.274 | D66: 103 | E66: 20.274 | F66: =G66+H66+I66 -> 6.059 | G66: 0.07 | H66: 3.985 | I66: 2.004 | K66: =SUM(L66:O66) -> 180.52324 | L66: 118.24038 | M66: 51.7841 | N66: 10.49876 | P66: 11.877953 | Q66: 10.363198 | R66: 358.2675 | S66: 210.8078 | T66: 153.5501 | U66: 29.039 | V66: 6.206 | W66: 22406 | X66: 3919 | Y66: 18487 | Z66: 1458.7 | AA66: =(AA18+AA30+AA42+AA54)/4 -> 10.3975 | AB66: 846.3
A67: 40544 | C67: =D67+E67 -> 127.131 | D67: 110 | E67: 17.131 | F67: =G67+H67+I67 -> 11.047 | G67: 3.401 | H67: 4.109 | I67: 3.537 | K67: =SUM(L67:O67) -> 169.81974 | L67: 109.76929 | M67: 48.326122 | N67: 11.72433 | P67: 12.95473 | Q67: 10.225168 | R67: 402.9476 | S67: 209.7173 | T67: 169.9154 | U67: 29.074 | V67: 0.389 | W67: 18926 | X67: 2932 | Y67: 15994 | Z67: 3033 | AA67: 0 | AB67: 1190.189
A68: 40575 | C68: =D68+E68 -> 109.181 | D68: 96 | E68: 13.181 | F68: =G68+H68+I68 -> 21.569 | G68: 7.891 | H68: =3.044+0.289 -> 3.333 | I68: 10.345 | K68: =SUM(L68:O68) -> 157.83244 | L68: 100.44056 | M68: 45.398938 | N68: 11.99294 | P68: 11.367902 | Q68: 8.993963 | R68: 384.9741 | S68: 214.4559 | T68: 185.4298 | U68: 25.446 | V68: 0 | W68: 20188 | X68: 3262 | Y68: 16926 | Z68: 2854.758 | AA68: 0.6 | AB68: 2451.46
A69: 40603 | C69: =D69+E69 -> 136.624 | D69: 117 | E69: 19.624 | F69: =G69+H69+I69 -> 20.595 | G69: 7.631 | H69: =2.559+0.48 -> 3.039 | I69: 9.925 | K69: =SUM(L69:O69) -> 140.545 | L69: 85.484389 | M69: 43.83971 | N69: 11.2209 | P69: 12.471585 | Q69: 9.862448 | R69: 458.4643 | S69: 261.7112 | T69: 200.5957 | U69: 28.749 | V69: 8.817 | W69: 21910 | X69: 3317 | Y69: 18593 | Z69: 2613.5 | AA69: 0.9 | AB69: 2503.223
A70: 40634 | C70: =D70+E70 -> 132.2 | D70: 112 | E70: 20.2 | F70: =G70+H70+I70 -> 14.053 | G70: 7.406 | H70: 3.872 | I70: 2.775 | K70: =SUM(L70:O70) -> 139.69315 | L70: 88.286384 | M70: 40.341063 | N70: 11.0657 | P70: 12.216418 | Q70: 9.701547 | R70: 418.394 | S70: 238.9296 | T70: 186.0491 | U70: 40.079 | V70: 2.586 | W70: 15461 | X70: 3138 | Y70: 12326 | Z70: 0 | AA70: 0 | AB70: 1144.963
A71: 40664 | C71: =D71+E71 -> 157.882 | D71: 146 | E71: 11.882 | F71: =G71+H71+I71 -> 22.791 | G71: 6.386 | H71: =0.842+0.808 -> 1.65 | I71: 14.755 | K71: =SUM(L71:O71) -> 157.67516 | L71: 95.066188 | M71: 49.888074 | N71: 12.7209 | P71: 12.566959 | Q71: 10.003602 | R71: 466.8282 | S71: 250.4428 | T71: 203.4468 | U71: 35.065 | V71: 0 | W71: 22206 | X71: 3287 | Y71: 18919 | Z71: 0 | AA71: 0 | AB71: 2103.614
A72: 40695 | C72: =D72+E72 -> 133.19 | D72: 122 | E72: 11.19 | F72: =G72+H72+I72 -> 16.023 | G72: 5.543 | H72: 4.108 | I72: 6.372 | K72: =SUM(L72:O72) -> 149.34466 | L72: 92.91521 | M72: 45.215329 | N72: 11.21412 | P72: 12.039912 | Q72: 9.524136 | R72: 432.62 | S72: 232.1034 | T72: 199.7378 | U72: 35.509 | V72: 0 | W72: 24279 | X72: 3330 | Y72: 20949 | Z72: 0 | AA72: 0 | AB72: 1893.023
A73: 40725 | C73: =D73+E73 -> 85.842 | D73: 71 | E73: 14.842 | F73: =G73+H73+I73 -> 15.7146 | G73: 6.14 | H73: =0.0046+1.594 -> 1.5986 | I73: 7.976 | K73: =SUM(L73:O73) -> 159.42197 | L73: 97.878068 | M73: 48.368096 | N73: 13.17581 | P73: 12.775905 | Q73: 10.318696 | R73: 423.5572 | S73: 227.9093 | T73: 176.472 | U73: 23.287 | V73: 14.778 | W73: 23999 | X73: 3543 | Y73: 20386 | Z73: 0 | AA73: 0 | AB73: 1177.52
A74: 40756 | C74: =D74+E74 -> 114.718 | D74: 105 | E74: 9.718 | F74: =G74+H74+I74 -> 7.366 | G74: 3.078 | H74: =2.591+0.42 -> 3.011 | I74: 1.277 | K74: =SUM(L74:O74) -> 171.29352 | L74: 110.12696 | M74: 48.958549 | N74: 12.20801 | P74: 12.219628 | Q74: 9.668828 | R74: 341.805 | S74: 179.1863 | T74: 160.2134 | U74: 32.15 | V74: 9.26 | W74: 25913 | X74: 3251 | Y74: 22662 | Z74: 0 | AA74: 0 | AB74: 335.833
A75: 40787 | C75: =D75+E75 -> 139.537 | D75: 125 | E75: 14.537 | F75: =G75+H75+I75 -> 9.281 | G75: 2.186 | H75: =1.89+0.222 -> 2.112 | I75: 4.983 | K75: =SUM(L75:O75) -> 180.57505 | L75: 110.59849 | M75: 58.128101 | N75: 11.84846 | P75: 11.817166 | Q75: 9.441976 | R75: 330.3081 | S75: 176.2937 | T75: 156.5337 | U75: 34.749 | V75: 0 | W75: 18814 | X75: 3305 | Y75: 15509 | Z75: 0 | AA75: 0 | AB75: 216.046
A76: 40817 | C76: =D76+E76 -> 148.738 | D76: 134 | E76: 14.738 | F76: =G76+H76+I76 -> 9.472 | G76: 1.108 | H76: 5.374 | I76: 2.99 | K76: =SUM(L76:O76) -> 194.86514 | L76: 127.60397 | M76: 53.100125 | N76: 14.16104 | P76: 13.147187 | Q76: 10.510895 | R76: 351.1944 | S76: 176.0151 | T76: 162.03 | U76: 36.484 | V76: 0 | W76: 24891 | X76: 3297 | Y76: 21594 | Z76: 0 | AA76: 0 | AB76: 241.165
A77: 40848 | C77: =D77+E77 -> 156.676 | D77: 145 | E77: 11.676 | F77: =G77+H77+I77 -> 5.993 | G77: 2.095 | H77: 0.019 | I77: 3.879 | K77: =SUM(L77:O77) -> 203.52396 | L77: 129.77712 | M77: 61.049697 | N77: 12.69714 | P77: 12.292496 | Q77: 9.867612 | R77: 300.6122 | S77: 176.0822 | T77: 144.287 | U77: 39.242 | V77: 0 | W77: 22746 | X77: =AVERAGE(X74:X76) -> 3284.3333 | Y77: =AVERAGE(Y74:Y76) -> 19921.667 | Z77: 0 | AA77: 0 | AB77: 242.224
A78: 40878 | C78: =D78+E78 -> 161.91 | D78: 129 | E78: 32.91 | F78: =G78+H78+I78 -> 10.287 | G78: 1.696 | H78: 3.501 | I78: 5.09 | K78: =SUM(L78:O78) -> 206.46582 | L78: 132.92302 | M78: 58.706424 | N78: 14.83638 | P78: 12.687816 | Q78: 10.683187 | R78: 408.6255 | S78: 226.8173 | T78: 196.3202 | U78: 32.561 | V78: 0 | W78: 18917 | X78: =AVERAGE(X75:X77) -> 3295.4444 | Y78: =AVERAGE(Y75:Y77) -> 19008.222 | Z78: 0 | AA78: 0 | AB78: 143.457
A79: 40909 | C79: =D79+E79 -> 157.837 | D79: 143 | E79: 14.837 | F79: =G79+H79+I79 -> 1.687 | G79: 0 | H79: =1.176+0.511 -> 1.687 | I79: 0 | K79: =SUM(L79:O79) -> 190.24172 | L79: 119.0038 | M79: 55.92589 | N79: 15.31203 | P79: 13.535273 | Q79: 10.827962 | R79: 449.936 | S79: 217.9707 | T79: 201.9947 | U79: 33.136 | V79: 13.131 | W79: 19017 | X79: 2813 | Y79: 16258 | Z79: 3916.6 | AA79: 0 | AB79: 847.868
A80: 40940 | C80: =D80+E80 -> 128.563 | D80: 115 | E80: 13.563 | F80: =G80+H80+I80 -> 2.765276 | G80: 0 | H80: 2.765276 | I80: 0 | K80: =SUM(L80:O80) -> 170.17103 | L80: 103.19211 | M80: 52.47656 | N80: 14.50236 | P80: 12.215842 | Q80: 9.767375 | R80: 426.4512 | S80: 217.9658 | T80: 210.089 | U80: 23.089 | V80: 0 | W80: 16700 | X80: 2720 | Y80: 13980 | Z80: 5124 | AA80: 0 | AB80: 2035.097
A81: 40969 | C81: =D81+E81 -> 144.944 | D81: 128 | E81: 16.944 | F81: =G81+H81+I81 -> 10.557 | G81: 3.314 | H81: =2.642+0.457 -> 3.099 | I81: 4.144 | K81: =SUM(L81:O81) -> 173.82304 | L81: 106.45676 | M81: 51.8156 | N81: 15.55068 | P81: 13.201226 | Q81: 10.21085 | R81: 453.9535 | S81: 248.2349 | T81: 199.0535 | U81: 31.395 | V81: 0 | W81: 21410 | X81: 2903 | Y81: 18507 | Z81: =1656+1134 -> 2790 | AA81: 0 | AB81: 2763.19
A82: 41000 | C82: =D82+E82 -> 135.436 | D82: 123 | E82: 12.436 | F82: =G82+H82+I82 -> 9.953572 | G82: 3.266119 | H82: =2.343503+0 -> 2.343503 | I82: 4.34395 | K82: =SUM(L82:O82) -> 175.13139 | L82: 108.54123 | M82: 52.8133 | N82: 13.77686 | P82: 12.48919 | Q82: 9.919871 | R82: 425.5633 | S82: 234.4649 | T82: 201.7357 | U82: 20.399 | V82: 0 | W82: 18337 | X82: 2810 | Y82: 15527 | Z82: 0 | AA82: 0 | AB82: 398.69
A83: 41030 | C83: =D83+E83 -> 136.874 | D83: 122 | E83: 14.874 | F83: =G83+H83+I83 -> 4.515408 | G83: 0.495779 | H83: =2.800905+0 -> 2.800905 | I83: 1.218724 | K83: =SUM(L83:O83) -> 173.27904 | L83: 104.09923 | M83: 54.30292 | N83: 14.87689 | P83: 13.234139 | Q83: 10.482954 | R83: 435.0901 | S83: 246.4565 | T83: 196.8194 | U83: 25.989 | V83: 14.106 | W83: 22700 | X83: 2743 | Y83: 19957 | Z83: 0 | AA83: 0 | AB83: 408.155
A84: 41061 | C84: =D84+E84 -> 139.491 | D84: 125 | E84: 14.491 | F84: =G84+H84+I84 -> 2.707 | G84: 0 | H84: 1.502 | I84: 1.205 | K84: =SUM(L84:O84) -> 186.58446 | L84: 116.3117 | M84: 55.44043 | N84: 14.83233 | P84: 12.943721 | Q84: 10.438302 | R84: 420.6825 | S84: 242.5924 | T84: 176.926 | U84: 27.219 | V84: 8.176 | W84: 22919 | X84: 2816 | Y84: 20103 | Z84: 0 | AA84: 0 | AB84: 87.232
A85: 41091 | C85: =D85+E85 -> 131.417 | D85: 116 | E85: 15.417 | F85: =G85+H85+I85 -> 1.649 | G85: 0 | H85: 1.649 | I85: 0 | K85: =SUM(L85:O85) -> 200.19708 | L85: 124.30853 | M85: 62.78512 | N85: 13.10343 | P85: 12.81874 | Q85: 10.241284 | R85: 388.6463 | S85: 215.1315 | T85: 158.1074 | U85: 43.183 | V85: 2.721 | W85: 18973 | X85: 3106 | Y85: 15867 | Z85: 0 | AA85: 0 | AB85: 1548.557
A86: 41122 | C86: =D86+E86 -> 102.505 | D86: 91 | E86: 11.505 | F86: =G86+H86+I86 -> 2.382 | G86: 0 | H86: =2.314+0.068 -> 2.382 | I86: 0 | K86: =SUM(L86:O86) -> 199.5857 | L86: 125.96249 | M86: 61.44663 | N86: 12.17658 | P86: 12.650931 | Q86: 10.012166 | R86: 303.0407 | S86: 158.5973 | T86: 158.3406 | U86: 35.017 | V86: 0 | W86: 19320 | X86: 2831 | Y86: 16489 | Z86: 0 | AA86: 0 | AB86: 734.235
A87: 41153 | C87: =D87+E87 -> 89.393 | D87: 76 | E87: 13.393 | F87: =G87+H87+I87 -> 4.952 | G87: 0.637 | H87: 3.244 | I87: 1.071 | K87: =SUM(L87:O87) -> 205.94049 | L87: 136.6835 | M87: 57.76531 | N87: 11.49168 | P87: 12.121009 | Q87: 9.437702 | R87: 340.8992 | S87: 176.5884 | T87: 167.5568 | U87: 28.366 | V87: 0.009 | W87: 20107 | X87: 2971 | Y87: 17136 | Z87: 0 | AA87: 0 | AB87: 707.233
A88: 41183 | C88: =D88+E88 -> 119.285 | D88: 103 | E88: 16.285 | F88: =G88+H88+I88 -> 2.548 | G88: 0 | H88: 2.548 | I88: 0 | K88: =SUM(L88:O88) -> 217.29743 | L88: 141.47496 | M88: 61.07126 | N88: 14.75121 | P88: 13.284272 | Q88: 10.595369 | R88: 336.913 | S88: 159.3308 | T88: 147.018 | U88: 30.081 | V88: 0 | W88: 19865 | X88: 2746 | Y88: 17119 | Z88: 0 | AA88: 0 | AB88: 221.522
A89: 41214 | C89: =D89+E89 -> 141.485 | D89: 121 | E89: 20.485 | F89: =G89+H89+I89 -> 1.807 | G89: 0 | H89: 1.807 | I89: 0 | K89: =SUM(L89:O89) -> 203.84972 | L89: 128.45019 | M89: 60.30208 | N89: 15.09745 | P89: 12.5103 | Q89: 9.982114 | R89: 362.275 | S89: 193.1096 | T89: 172.6038 | U89: 28.205 | V89: 11.704 | W89: 23874 | X89: 3329 | Y89: 20545 | Z89: 0 | AA89: 0 | AB89: 39.98
A90: 41244 | C90: =D90+E90 -> 130.545 | D90: 117 | E90: 13.545 | F90: =G90+H90+I90 -> 2.287 | G90: 0 | H90: 2.287 | I90: 0 | K90: =SUM(L90:O90) -> 217.31175 | L90: 141.88452 | M90: 60.39595 | N90: 15.03128 | P90: 12.863253 | Q90: 11.168202 | R90: 379.6098 | S90: 209.033 | T90: 177.878 | U90: 37.092 | V90: 7.943 | W90: 14109 | X90: 2617 | Y90: 11492 | Z90: 3110 | AA90: 0 | AB90: 558.662
A91: 41275 | C91: =D91+E91 -> 104.944 | D91: 103 | E91: 1.944 | F91: =G91+H91+I91 -> 7.113 | G91: 2.102 | H91: =3.17+0 -> 3.17 | I91: 1.841 | K91: =SUM(L91:O91) -> 198.49282 | L91: 127.59167 | M91: 57.781614 | N91: 13.119537 | P91: 13.536917 | Q91: 10.857262 | R91: 391.05535 | S91: 226.05534 | T91: 179.99425 | U91: 32.515 | V91: 3.2 | W91: 20473 | X91: 2811 | Y91: 17662 | Z91: 6209 | AA91: 0 | AB91: 545.646
A92: 41306 | C92: =D92+E92 -> 97.174 | D92: 75 | E92: 22.174 | F92: =G92+H92+I92 -> 13.327556 | G92: 5.214161 | H92: 1.702495 | I92: 6.4109 | K92: =SUM(L92:O92) -> 169.59363 | L92: 104.17446 | M92: 52.652064 | N92: 12.767108 | P92: 12.210216 | Q92: 9.7364589 | R92: 375.51526 | S92: 233.38113 | T92: 151.11635 | U92: 24.508 | V92: 0 | W92: 22441 | X92: 3136 | Y92: 19305 | Z92: 9229.8 | AA92: 0 | AB92: 1542.204
A93: 41334 | C93: =D93+E93 -> 104.528 | D93: 84 | E93: 20.528 | F93: =G93+H93+I93 -> 4.048335 | G93: 1.397989 | H93: 0.866076 | I93: 1.78427 | K93: =SUM(L93:O93) -> 180.68567 | L93: 112.01611 | M93: 55.039538 | N93: 13.630031 | P93: 13.375699 | Q93: 10.168336 | R93: 447.37594 | S93: 267.93529 | T93: 179.2971 | U93: 20.05 | V93: 12.574 | W93: 20890 | X93: =W93*14% -> 2924.6 | Y93: =W93*86% -> 17965.4 | Z93: 4308 | AA93: 0 | AB93: 2170.162
A94: 41365 | C94: =D94+E94 -> 128.6 | D94: 111 | E94: 17.6 | F94: =G94+H94+I94 -> 7.142257 | G94: 1.735566 | H94: 2.545001 | I94: 2.86169 | K94: =SUM(L94:O94) -> 180.73529 | L94: 112.59709 | M94: 52.99449 | N94: 15.143715 | P94: 13.072798 | Q94: 10.366956 | R94: 390.27328 | S94: 257.83893 | T94: 136.2104 | U94: 27.53084 | V94: 3.079 | W94: 17136 | X94: =W94*14% -> 2399.04 | Y94: =W94*86% -> 14736.96 | Z94: 0 | AA94: 0 | AB94: 1043.986
A95: 41395 | C95: =D95+E95 -> 135.201 | D95: 107 | E95: 28.201 | F95: =G95+H95+I95 -> 9.153299 | G95: 3.096804 | H95: 2.271615 | I95: 3.78488 | K95: =SUM(L95:O95) -> 183.72869 | L95: 109.18675 | M95: 58.296813 | N95: 16.245121 | P95: 13.852818 | Q95: 10.935107 | R95: 435.37452 | S95: 282.93157 | T95: 151.4501 | U95: 15.576802 | V95: 14.505 | W95: 18728 | X95: 2824 | Y95: =W95-X95 -> 15904 | Z95: 0 | AA95: 0 | AB95: 2941.43
A96: 41426 | C96: =D96+E96 -> 80.428 | D96: 68 | E96: 12.428 | F96: =G96+H96+I96 -> 1.491684 | G96: 0 | H96: 1.491684 | I96: 0 | K96: =SUM(L96:O96) -> 198.54307 | L96: 124.94978 | M96: 59.319182 | N96: 14.274102 | P96: 13.443734 | Q96: 10.628119 | R96: 437.0932 | S96: 263.50875 | T96: 150.1527 | U96: 7.044 | V96: 15.544 | W96: 18172 | X96: 2860 | Y96: 15312 | Z96: 0 | AA96: 0 | AB96: 2366.661
A97: 41456 | C97: =D97+E97 -> 95.857 | D97: 79 | E97: 16.857 | F97: =G97+H97+I97 -> 1.528 | G97: 0 | H97: 1.528 | I97: 0 | K97: =SUM(L97:O97) -> 212.97268 | L97: 131.18296 | M97: 66.715397 | N97: 15.074315 | P97: 13.67382 | Q97: 10.909287 | R97: 409.91152 | S97: 253.08286 | T97: 156.28445 | U97: 16.088 | V97: 13.085 | W97: 20332 | X97: 3632 | Y97: 16700 | Z97: 0 | AA97: 0 | AB97: 1167.76
A98: 41487 | C98: =D98+E98 -> 67.942 | D98: 45 | E98: 22.942 | F98: =G98+H98+I98 -> 5.46 | G98: 2.157 | H98: 1.081 | I98: 2.222 | K98: =SUM(L98:O98) -> 216.06069 | L98: 141.46798 | M98: 62.421926 | N98: 12.170784 | P98: 13.18948 | Q98: 10.442502 | R98: 313.14526 | S98: 184.13143 | T98: 116.71826 | U98: 31.508 | V98: 3.764 | W98: 17523 | X98: =W98*14% -> 2453.22 | Y98: =W98-X98 -> 15069.78 | Z98: 0 | AA98: 0 | AB98: 792.745
A99: 41518 | C99: =D99+E99 -> 83.798 | D99: 67 | E99: 16.798 | F99: =G99+H99+I99 -> 7.643971 | G99: 3.381533 | H99: 0.318938 | I99: 3.9435 | K99: =SUM(L99:O99) -> 213.40094 | L99: 143.45421 | M99: 59.412636 | N99: 10.53409 | P99: 10.715046 | Q99: 8.8037248 | R99: 319.501 | S99: 184.82817 | T99: 133.40316 | U99: 30.145 | V99: 0.613 | W99: 16331 | X99: 2880 | Y99: 13451 | Z99: 0 | AA99: 0 | AB99: 188.845
A100: 41548 | C100: =D100+E100 -> 74.04 | D100: 59 | E100: 15.04 | F100: =G100+H100+I100 -> 0.162924 | G100: 0 | H100: =0.04402+0.118904 -> 0.162924 | I100: 0 | K100: =SUM(L100:O100) -> 212.43313 | L100: 140.11231 | M100: 60.164143 | N100: 12.156684 | P100: 12.689085 | Q100: 9.9889968 | R100: 275.47614 | S100: 168.49171 | T100: 113.05983 | U100: 25.023 | V100: 6.2 | W100: 21531 | X100: 3271 | Y100: 18260 | Z100: 0 | AA100: 0 | AB100: 110.448
A101: 41579 | C101: =D101+E101 -> 40.777 | D101: 23 | E101: 17.777 | F101: =G101+H101+I101 -> 0.336139 | G101: 0 | H101: 0.336139 | I101: 0 | K101: =SUM(L101:O101) -> 214.68987 | L101: 144.05934 | M101: 59.282665 | N101: 11.347864 | P101: 12.726229 | Q101: 10.128133 | R101: 371.96113 | S101: 226.18159 | T101: 139.84794 | U101: 12.566 | V101: 2.922 | W101: 23647 | X101: =W101*14% -> 3310.58 | Y101: =W101-X101 -> 20336.42 | Z101: 0 | AA101: 0 | AB101: 57.928
...

Sheet Indice Secondaire
A1: DIRECTION DE LA PREVISION ET DES ETUDES ECONOMIQUES
B3: INDICE CHIFFRE D'AFFAIRES DU SECTEUR SECONDAIRE (base 100 = 2022)*
C4: INDUSTRIE | BA4: CONSTRUCTION
D5: ACTIVITES EXTRACTIVES | J5: FABRICATION DE PRODUITS AGRO-ALIMENTAIRES | X5: RAFFINAGE PETROLIER ET COKEFACTION | Y5: FABRICATION DE PRODUITS CHIMIQUES DE BASE | Z5: FABRICATION DE CIMENT ET D'AUTRES MATERIAUX DE CONSTRUCTION | AA5: PRODUCTION DE L'EGRENAGE DU COTON | AB5: PRODUCTION DE LA FILATURE, DU TISSAGE ET DE L'ENNOBLISSEMENT TEXTILE | AC5: TRAVAIL DU CUIR; FABRICATION D'ARTICLES DE VOYAGE ET DE CHAUSSURES | AD5: SCIAGE ET RABOTAGE DU BOIS | AE5: FABRICATION DE PAPIER CARTON ET D'ARTICLES EN PAPIER OU CARTON | AF5: FABRICATION DE PRODUITS PHARMACEUTIQUES | AG5: FABRICATION DE SAVONS, DETERGENTS ET PRODUITS D'ENTRETIEN | AH5: TRAVAIL DU CAOUTCHOUC ET DU PLASTIQUE | AI5: PRODUCTION DE METALLURGIE ET DE FONDERIE; FABRICATION D'OUVRAGES EN METAUX | AJ5: FABRICATION DE MATERIELS DE TRANSPORT | AM5: AUTRES INDUSTRIES MANUFACTURIERES | AW5: Production et distribution d'électricité et de supports énergétiques | AX5: PRODUCTION ET DISTRIBUTION D'EAU, ASSAINISSEMENT ET TRAITEMENT DES DECHETS | BB5: Génie civil | BC5: Activités spécialisées de construction | BD5: Construction de bâtiments et travaux de construction
E6: Extraction de phosphates naturels | F6: Extraction de minerais metalliques | G6: Extraction d'hydrocarbure | H6: Autres extractions | I6: Activités de soutien aux industries extractives | K6: Abattage, transformation, et conservation des viandes | L6: Transformation et conservation des poissons, crustacés et mollusques | M6: Fabrication de corps gras alimentaires | N6: Travail des grains | O6: Fabrication d'aliments pour animaux | P6: Fabrication de pain et de pâtisseries | Q6: Fabrication de produits alimentaires à base de céréales n.c.a | R6: Conserves de fruits et légumes | S6: Fabrication de produits laitiers et de glaces alimentaires | T6: Fabrication de sucre, chocolaterie et confiserie | U6: Fabrication d'autres produits alimentaires | V6: Fabrication de boissons | W6: Fabrication de produits à base de tabac | AK6: Construction de véhicules automobiles et composants | AL6: Fabrication d'autres matériels de transports | AN6: Imprimerie et activités annexes | AO6: Fabrication d'autres produits chimiques | AP6: Fabrication de produits électroniques et informatiques | AQ6: Fabrication d'équipements électriques | AR6: Fabrication de machines et matériels divers à usage général | AS6: Fabrication de machines et matériels divers à usage spécifique | AT6: Fabrication de meubles et matelas | AU6: Installation et réparation de machines et d'équipements | AV6: Autres industries manufacturières n.c.a | AY6: Captage, traitement et distribution d'eau | AZ6: Collecte et traitement des eaux usées; récupération des déchets
A7: 42370 | B7: 50.653394 | C7: 42.735981 | D7: 23.031184 | E7: 114.61377 | F7: 12.046074 | G7: 177.88455 | H7: 45.128746 | I7: 47.666892 | J7: 52.925083 | K7: 61.42906 | L7: 75.020525 | M7: 28.399064 | N7: 42.049432 | O7: 40.707747 | P7: 49.326822 | Q7: 92.851958 | R7: 80.701748 | S7: 55.15296 | T7: 52.330197 | U7: 52.152086 | V7: 83.9158 | W7: 130.05415 | X7: 37.095477 | Y7: 25.88567 | Z7: 67.897883 | AA7: 91.161615 | AB7: 83.875446 | AC7: 206.31856 | AD7: 279.36594 | AE7: 97.354264 | AF7: 116.17702 | AG7: 46.16779 | AH7: 95.924191 | AI7: 101.61967 | AJ7: 56.463779 | AK7: 0 | AL7: 0 | AM7: 52.349425 | AN7: 80.082164 | AO7: 34.27414 | AP7: 0 | AQ7: 74.364596 | AR7: 0 | AS7: 71.859081 | AT7: 0 | AU7: 0 | AV7: 75.844539 | AW7: 38.086066 | AX7: 105.15769 | AY7: 108.3982 | AZ7: 82.207084 | BA7: 164.1191 | BB7: 133.17576 | BC7: 142.12691 | BD7: 92.928945
A8: 42401 | B8: 49.54939 | C8: 41.511877 | D8: 22.726044 | E8: 164.82625 | F8: 44.143803 | G8: 278.38618 | H8: 44.530836 | I8: 49.073317 | J8: 52.283217 | K8: 82.936169 | L8: 76.216171 | M8: 31.037584 | N8: 38.269692 | O8: 37.048608 | P8: 47.573667 | Q8: 89.551848 | R8: 84.731268 | S8: 58.562162 | T8: 46.400468 | U8: 64.104472 | V8: 78.499812 | W8: 127.87778 | X8: 33.436865 | Y8: 20.360734 | Z8: 67.547603 | AA8: 221.53925 | AB8: 94.445975 | AC8: 179.81602 | AD8: 294.54411 | AE8: 110.65725 | AF8: 145.28501 | AG8: 57.186378 | AH8: 76.120346 | AI8: 105.64664 | AJ8: 89.920231 | AK8: 0 | AL8: 0 | AM8: 51.100527 | AN8: 89.216153 | AO8: 41.366457 | AP8: 0 | AQ8: 52.223443 | AR8: 0 | AS8: 50.463914 | AT8: 0 | AU8: 0 | AV8: 66.461711 | AW8: 35.902323 | AX8: 104.68518 | AY8: 95.846526 | AZ8: 158.88495 | BA8: 174.25758 | BB8: 148.46272 | BC8: 107.27732 | BD8: 89.906897
A9: 42430 | B9: 56.567739 | C9: 47.881504 | D9: 20.95448 | E9: 314.97477 | F9: 60.850631 | G9: 245.63119 | H9: 41.059523 | I9: 44.338461 | J9: 66.180776 | K9: 63.225369 | L9: 56.328314 | M9: 156.31708 | N9: 52.965329 | O9: 51.275346 | P9: 48.932495 | Q9: 92.109682 | R9: 73.109302 | S9: 49.171454 | T9: 60.930427 | U9: 75.290115 | V9: 73.873006 | W9: 127.53032 | X9: 37.926339 | Y9: 28.980269 | Z9: 77.248388 | AA9: 195.48172 | AB9: 81.175674 | AC9: 301.38566 | AD9: 240.99858 | AE9: 86.515036 | AF9: 131.77975 | AG9: 58.025808 | AH9: 115.01437 | AI9: 96.535353 | AJ9: 66.992904 | AK9: 0 | AL9: 0 | AM9: 63.917647 | AN9: 74.225703 | AO9: 42.599329 | AP9: 0 | AQ9: 50.954356 | AR9: 0 | AS9: 49.237586 | AT9: 0 | AU9: 0 | AV9: 79.530561 | AW9: 35.217584 | AX9: 126.0006 | AY9: 101.84113 | AZ9: 277.58529 | BA9: 175.98853 | BB9: 147.3061 | BC9: 124.60413 | BD9: 100.23749
A10: 42461 | B10: 52.171553 | C10: 43.390014 | D10: 23.729565 | E10: 211.74315 | F10: 20.914933 | G10: 267.24768 | H10: 46.497199 | I10: 51.968227 | J10: 56.720319 | K10: 80.574281 | L10: 60.19236 | M10: 30.43161 | N10: 45.553851 | O10: 44.100349 | P10: 43.911373 | Q10: 82.65801 | R10: 77.918352 | S10: 48.971898 | T10: 61.348074 | U10: 76.108645 | V10: 68.094651 | W10: 128.87576 | X10: 35.68131 | Y10: 15.611629 | Z10: 74.973461 | AA10: 174.17712 | AB10: 82.957309 | AC10: 226.0218 | AD10: 269.77293 | AE10: 91.529712 | AF10: 117.26613 | AG10: 54.543467 | AH10: 80.530438 | AI10: 112.55112 | AJ10: 88.844959 | AK10: 0 | AL10: 0 | AM10: 69.442111 | AN10: 78.667438 | AO10: 39.859148 | AP10: 0 | AQ10: 125.517 | AR10: 0 | AS10: 121.28804 | AT10: 0 | AU10: 0 | AV10: 87.172177 | AW10: 36.774816 | AX10: 96.358407 | AY10: 97.922592 | AZ10: 84.30193 | BA10: 198.41406 | BB10: 168.48151 | BC10: 125.62096 | BD10: 92.53188
A11: 42491 | B11: 57.916839 | C11: 48.116528 | D11: 23.681688 | E11: 258.95473 | F11: 36.596098 | G11: 377.2027 | H11: 46.403385 | I11: 48.312392 | J11: 63.818087 | K11: 72.43834 | L11: 83.434432 | M11: 45.431698 | N11: 55.161238 | O11: 53.40119 | P11: 53.146693 | Q11: 100.04242 | R11: 64.881471 | S11: 30.54648 | T11: 65.206247 | U11: 73.437167 | V11: 78.68367 | W11: 133.45181 | X11: 39.113119 | Y11: 42.076099 | Z11: 71.257181 | AA11: 26.434945 | AB11: 91.224196 | AC11: 210.52132 | AD11: 280.01578 | AE11: 64.569913 | AF11: 136.03515 | AG11: 48.342819 | AH11: 84.905006 | AI11: 118.10466 | AJ11: 66.186237 | AK11: 0 | AL11: 0 | AM11: 88.046613 | AN11: 71.982876 | AO11: 35.749168 | AP11: 0 | AQ11: 47.162674 | AR11: 0 | AS11: 45.573654 | AT11: 0 | AU11: 0 | AV11: 92.273611 | AW11: 36.106812 | AX11: 128.06493 | AY11: 142.95024 | AZ11: 30.256452 | BA11: 222.68798 | BB11: 161.63155 | BC11: 310.69889 | BD11: 101.80526
A12: 42522 | B12: 57.374722 | C12: 47.855974 | D12: 20.357432 | E12: 185.62745 | F12: 50.015206 | G12: 252.59215 | H12: 39.889628 | I12: 45.736319 | J12: 64.578332 | K12: 88.082995 | L12: 99.922015 | M12: 39.691259 | N12: 53.952612 | O12: 52.231128 | P12: 54.984196 | Q12: 103.5013 | R12: 57.858069 | S12: 54.719715 | T12: 71.211335 | U12: 81.418854 | V12: 78.990017 | W12: 116.37319 | X12: 37.486857 | Y12: 31.330072 | Z12: 65.038829 | AA12: 44.017269 | AB12: 91.84789 | AC12: 193.5822 | AD12: 261.1317 | AE12: 105.67153 | AF12: 129.08317 | AG12: 47.699983 | AH12: 83.42998 | AI12: 97.817721 | AJ12: 19.600743 | AK12: 0 | AL12: 0 | AM12: 66.303324 | AN12: 88.479599 | AO12: 38.283336 | AP12: 0 | AQ12: 69.751889 | AR12: 0 | AS12: 67.401787 | AT12: 0 | AU12: 0 | AV12: 106.556 | AW12: 40.659092 | AX12: 190.90121 | AY12: 197.59369 | AZ12: 144.06601 | BA12: 211.70729 | BB12: 180.39414 | BC12: 130.17603 | BD12: 95.988683
A13: 42552 | B13: 61.154547 | C13: 52.068444 | D13: 20.326071 | E13: 228.13144 | F13: 24.857987 | G13: 230.51336 | H13: 39.828179 | I13: 51.141128 | J13: 58.737013 | K13: 72.108435 | L13: 71.356954 | M13: 40.604858 | N13: 50.809217 | O13: 49.188031 | P13: 48.650127 | Q13: 91.578158 | R13: 57.221542 | S13: 47.257566 | T13: 56.183811 | U13: 60.347006 | V13: 79.69644 | W13: 130.43296 | X13: 70.296222 | Y13: 45.379956 | Z13: 61.572103 | AA13: 105.93572 | AB13: 87.397818 | AC13: 157.1599 | AD13: 271.08236 | AE13: 86.461243 | AF13: 140.1491 | AG13: 47.023933 | AH13: 73.641074 | AI13: 149.95102 | AJ13: 31.58176 | AK13: 0 | AL13: 0 | AM13: 80.760742 | AN13: 78.833434 | AO13: 31.961301 | AP13: 0 | AQ13: 36.181542 | AR13: 0 | AS13: 34.962502 | AT13: 0 | AU13: 0 | AV13: 74.687161 | AW13: 40.404411 | AX13: 102.15507 | AY13: 101.06373 | AZ13: 106.93303 | BA13: 175.99031 | BB13: 135.16547 | BC13: 199.64135 | BD13: 80.895635
A14: 42583 | B14: 58.312721 | C14: 49.419815 | D14: 21.355124 | E14: 122.74233 | F14: 34.670553 | G14: 250.76639 | H14: 41.84457 | I14: 48.986625 | J14: 60.99248 | K14: 87.03755 | L14: 64.773058 | M14: 18.612821 | N14: 47.269949 | O14: 45.761691 | P14: 44.916495 | Q14: 84.550034 | R14: 91.780842 | S14: 54.652206 | T14: 67.535832 | U14: 72.33879 | V14: 99.491397 | W14: 132.09337 | X14: 37.737151 | Y14: 26.030556 | Z14: 68.594217 | AA14: 48.521523 | AB14: 77.757932 | AC14: 129.00717 | AD14: 275.01261 | AE14: 95.358031 | AF14: 141.61357 | AG14: 58.313377 | AH14: 199.12611 | AI14: 201.7474 | AJ14: 53.796384 | AK14: 0 | AL14: 0 | AM14: 70.436396 | AN14: 68.84236 | AO14: 41.695148 | AP14: 0 | AQ14: 40.26173 | AR14: 0 | AS14: 38.905219 | AT14: 0 | AU14: 0 | AV14: 103.90642 | AW14: 42.499931 | AX14: 102.55136 | AY14: 112.13824 | AZ14: 39.127261 | BA14: 178.54552 | BB14: 141.07191 | BC14: 178.16698 | BD14: 147.37502
A15: 42614 | B15: 50.847476 | C15: 43.705837 | D15: 19.803298 | E15: 105.31949 | F15: 31.374167 | G15: 200.9284 | H15: 38.803823 | I15: 33.534222 | J15: 58.077081 | K15: 65.318907 | L15: 78.351017 | M15: 24.913278 | N15: 43.889842 | O15: 42.489434 | P15: 49.781481 | Q15: 93.7078 | R15: 76.458305 | S15: 45.526916 | T15: 62.479789 | U15: 73.69105 | V15: 90.72423 | W15: 141.75793 | X15: 36.77316 | Y15: 37.438392 | Z15: 50.35335 | AA15: 2.0605831 | AB15: 84.428744 | AC15: 248.04577 | AD15: 218.46417 | AE15: 81.628181 | AF15: 159.2184 | AG15: 46.721104 | AH15: 36.304329 | AI15: 72.760779 | AJ15: 97.280124 | AK15: 0 | AL15: 0 | AM15: 73.236424 | AN15: 117.65167 | AO15: 33.786337 | AP15: 0 | AQ15: 34.237286 | AR15: 0 | AS15: 33.083752 | AT15: 0 | AU15: 0 | AV15: 98.038192 | AW15: 39.586998 | AX15: 143.37484 | AY15: 149.31547 | AZ15: 102.3607 | BA15: 126.96984 | BB15: 100.48454 | BC15: 125.69044 | BD15: 93.992769
A16: 42644 | B16: 51.058351 | C16: 43.183142 | D16: 22.827414 | E16: 136.82689 | F16: 17.783186 | G16: 244.57619 | H16: 44.729468 | I16: 45.240142 | J16: 54.271674 | K16: 73.964771 | L16: 58.424236 | M16: 21.954202 | N16: 41.195007 | O16: 39.880584 | P16: 47.19931 | Q16: 88.847165 | R16: 72.258564 | S16: 49.129874 | T16: 67.015428 | U16: 71.293067 | V16: 83.423156 | W16: 115.45875 | X16: 37.054087 | Y16: 27.233411 | Z16: 62.804758 | AA16: 26.990154 | AB16: 74.423893 | AC16: 143.99408 | AD16: 316.42064 | AE16: 70.449664 | AF16: 145.77008 | AG16: 57.020707 | AH16: 67.365176 | AI16: 78.364624 | AJ16: 111.00366 | AK16: 0 | AL16: 0 | AM16: 67.910554 | AN16: 123.72258 | AO16: 39.881131 | AP16: 0 | AQ16: 32.94756 | AR16: 0 | AS16: 31.83748 | AT16: 0 | AU16: 0 | AV16: 101.3539 | AW16: 40.013794 | AX16: 108.08453 | AY16: 108.6185 | AZ16: 102.35567 | BA16: 160.48687 | BB16: 124.90109 | BC16: 171.90289 | BD16: 119.93399
A17: 42675 | B17: 54.808174 | C17: 45.07344 | D17: 25.0945 | E17: 36.135291 | F17: 28.132358 | G17: 205.7849 | H17: 49.171737 | I17: 36.933565 | J17: 55.653368 | K17: 69.377364 | L17: 44.348559 | M17: 30.856948 | N17: 42.272388 | O17: 40.923588 | P17: 48.738513 | Q17: 91.744534 | R17: 72.736945 | S17: 51.104085 | T17: 71.48115 | U17: 76.242986 | V17: 88.590698 | W17: 134.36976 | X17: 40.549531 | Y17: 26.19964 | Z17: 63.403684 | AA17: 1.0089759 | AB17: 128.71898 | AC17: 161.15067 | AD17: 276.68649 | AE17: 65.024743 | AF17: 129.18693 | AG17: 68.459563 | AH17: 74.42289 | AI17: 89.193393 | AJ17: 64.205614 | AK17: 0 | AL17: 0 | AM17: 72.459091 | AN17: 171.58727 | AO17: 42.734189 | AP17: 0 | AQ17: 87.662139 | AR17: 0 | AS17: 84.708599 | AT17: 0 | AU17: 0 | AV17: 92.813972 | AW17: 39.3828 | AX17: 147.05602 | AY17: 155.68461 | AZ17: 88.796957 | BA17: 232.3142 | BB17: 129.35734 | BC17: 566.75565 | BD17: 94.234105
A18: 42705 | B18: 60.10097 | C18: 47.986512 | D18: 29.463374 | E18: 123.40504 | F18: 55.898932 | G18: 196.08701 | H18: 57.732383 | I18: 62.480036 | J18: 62.292425 | K18: 93.940371 | L18: 54.584479 | M18: 61.150784 | N18: 49.319719 | O18: 47.746058 | P18: 33.528635 | Q18: 63.113722 | R18: 77.997901 | S18: 50.637917 | T18: 67.954779 | U18: 73.513522 | V18: 86.459426 | W18: 109.78975 | X18: 40.594372 | Y18: 26.765488 | Z18: 68.248966 | AA18: 10.019904 | AB18: 133.50924 | AC18: 174.31963 | AD18: 184.4167 | AE18: 83.776111 | AF18: 126.42168 | AG18: 66.716478 | AH18: 81.612691 | AI18: 110.77628 | AJ18: 151.9045 | AK18: 0 | AL18: 0 | AM18: 83.210213 | AN18: 82.696502 | AO18: 51.666617 | AP18: 0 | AQ18: 52.914322 | AR18: 0 | AS18: 51.131516 | AT18: 0 | AU18: 0 | AV18: 121.61015 | AW18: 40.168563 | AX18: 133.2937 | AY18: 135.73634 | AZ18: 114.8348 | BA18: 322.21713 | BB18: 280.30949 | BC18: 162.58848 | BD18: 298.5077
... A127: 46023 | B127: 89.962906 | C127: 91.791963 | D127: 85.056732 | E127: 129.86066 | F127: 96.759726 | G127: 89.553092 | H127: 54.914082 | I127: 26.852637 | J127: 97.436711 | K127: 93.620465 | L127: 88.30058 | M127: 60.371027 | N127: 98.544036 | O127: 86.884406 | P127: 128.47249 | Q127: 120.71506 | R127: 146.94931 | S127: 63.558343 | T127: 40.612724 | U127: 119.96868 | V127: 109.69166 | W127: 168.07432 | X127: 76.931267 | Y127: 99.482866 | Z127: 143.87942 | AA127: 23.880056 | AB127: 110.76521 | AC127: 1 | AD127: 44.458858 | AE127: 97.848925 | AF127: 68.02985 | AG127: 121.79056 | AH127: 85.578676 | AI127: 138.97836 | AJ127: 56.422011 | AK127: 22.908333 | AL127: 62.844584 | AM127: 90.142717 | AN127: 101.47934 | AO127: 130.28774 | AP127: 75.582988 | AQ127: 101.43023 | AR127: 23.20104 | AS127: 16.395149 | AT127: 48.423042 | AU127: 18.028898 | AV127: 66.077929 | AW127: 68.333186 | AX127: 132.25971 | AY127: 146.85149 | AZ127: 64.935988 | BA127: 72.811084 | BB127: 72.569503 | BC127: 74.175321 | BD127: 72.93456
C129: *Les données du mois de janvier sont provisoires et feront l'objet de révision

Sheet Transport
A1: DIRECTION DE LA PREVISION ET DES ETUDES ECONOMIQUES
B2: =B247/B246-1 -> -0.040300277 | C2: =C247/C246-1 -> 0.024612402 | D2: =D247/D246-1 -> 0.12505549 | E2: =E247/E246-1 -> -0.048462671 | F2: =F247/F246-1 -> -0.14412163 | G2: =G247/G246-1 -> 0.14355908 | H2: =H247/H246-1 -> 0.31540807 | I2: =I247/I246-1 -> 0.059363584 | ... Z2: =Z247/Z246-1 -> #DIV/0!
B3: Trafic aérien | J3: Trafic maritime | W3: Trafic ferroviaire
B4: Mouvements d'aéronefs | C4: Passagers | G4: Fret | J4: Embarquements | N4: Débarquements | U4: Liaison Dakar-Gorée-Dakar | W4: Voyageurs du PTB* | X4: Trafic international de
C5: Total | D5: Départs | E5: Arrivées | F5: En transit | G5: Total | H5: Départs | I5: Arrivées | J5: Total | K5: marchandises diverses | L5: phosphates | M5: produits de la mer | N5: Total | O5: marchandises diverses | P5: pétrole brut | Q5: hydrocarbures raffinées | R5: Produits de la mer | U5: Rotations* | V5: Billets vendus | X5: Total | Y5: Exportations | Z5: Importations
B6: (nombre) | C6: (nombre) | D6: (nombre) | E6: (nombre) | F6: (nombre) | G6: (tonnes) | H6: (tonnes) | I6: (tonnes) | J6: (1000 tonnes) | K6: (1000 tonnes) | L6: (1000 tonnes) | M6: (1000 tonnes) | N6: (1000 tonnes) | O6: (1000 tonnes) | P6: (1000 tonnes) | Q6: (1000 tonnes) | R6: (1000 tonnes) | S6: débarquement (1000 tonnes) | T6: transbordement (1000 tonnes) | U6: (nombre) | V6: (nombre) | W6: (nombre) | X6: (tonnes) | Y6: (tonnes) | Z6: (tonnes)
A7: 38718 | B7: 4375 | C7: =SUM(D7:F7) -> 177303 | D7: 87503 | E7: 76972 | F7: 12828 | G7: =H7+I7 -> 2157.066 | H7: 1325.721 | I7: 831.345 | J7: =K7+L7+M7 -> 246.48 | K7: 227.852 | L7: 13.2 | M7: 5.428 | N7: =O7+P7+Q7+R7 -> 568.47844 | O7: 539.04913 | P7: 2.895992 | Q7: 19.235323 | R7: =S7+T7 -> 7.298 | S7: 4.588 | T7: 2.71 | W7: 263697 | X7: =Y7+Z7 -> 24461 | Y7: 16884 | Z7: 7577
A8: 38749 | B8: 3706 | C8: =SUM(D8:F8) -> 134887 | D8: 70639 | E8: 55423 | F8: 8825 | G8: =H8+I8 -> 1982.973 | H8: 1289.234 | I8: 693.739 | J8: =K8+L8+M8 -> 240.236 | K8: 233.402 | L8: 2.2 | M8: 4.634 | N8: =O8+P8+Q8+R8 -> 546.37068 | O8: 375.6691 | P8: 116.3107 | Q8: 48.903882 | R8: =S8+T8 -> 5.487 | S8: 3.984 | T8: 1.503 | W8: 256565 | X8: =Y8+Z8 -> 25313 | Y8: 17117 | Z8: 8196
A9: 38777 | B9: 3551 | C9: =SUM(D9:F9) -> 144900 | D9: 77091 | E9: 54632 | F9: 13177 | G9: =H9+I9 -> 2161.287 | H9: 1506.996 | I9: 654.291 | J9: =K9+L9+M9 -> 194.88 | K9: 174.723 | L9: 12.8 | M9: 7.357 | N9: =O9+P9+Q9+R9 -> 696.675 | O9: 610.64883 | P9: 0.646389 | Q9: 77.313783 | R9: 8.066 | S9: 5.082 | T9: 2.984 | W9: 261655 | X9: =Y9+Z9 -> 26826 | Y9: 18949 | Z9: 7877
A10: 38808 | B10: 3565 | C10: =SUM(D10:F10) -> 143541 | D10: 75965 | E10: 55606 | F10: 11970 | G10: =H10+I10 -> 1856.016 | H10: 1281.46 | I10: 574.556 | J10: =K10+L10+M10 -> 187.856 | K10: 168.237 | L10: 11.5 | M10: 8.119 | N10: =O10+P10+Q10+R10 -> 485.963 | O10: 320.51612 | P10: 92.450548 | Q10: 56.876328 | R10: =S10+T10 -> 16.12 | S10: 6.457 | T10: 9.663 | W10: 229200 | X10: =Y10+Z10 -> 27490 | Y10: 19201 | Z10: 8289
A11: 38838 | B11: 3487 | C11: =SUM(D11:F11) -> 143864 | D11: 64562 | E11: 61981 | F11: 17321 | G11: =H11+I11 -> 1734.548 | H11: 1041.843 | I11: 692.705 | J11: =K11+L11+M11 -> 217.181 | K11: 185.865 | L11: 12.1 | M11: 19.216 | N11: =O11+P11+Q11+R11 -> 675.50933 | O11: 487.3197 | P11: 116.82256 | Q11: 56.000074 | R11: =S11+T11 -> 15.367 | S11: 5.456 | T11: 9.911 | W11: 258440 | X11: =Y11+Z11 -> 29600 | Y11: 24074 | Z11: 5526
A12: 38869 | B12: 3431 | C12: =SUM(D12:F12) -> 132051 | D12: 56335 | E12: 57602 | F12: 18114 | G12: =H12+I12 -> 1575.511 | H12: 979 | I12: 596.511 | J12: =K12+L12+M12 -> 181.415 | K12: 154.004 | L12: 13.9 | M12: 13.511 | N12: =O12+P12+Q12+R12 -> 746.825 | O12: 674.35743 | P12: 2.485442 | Q12: 59.974124 | R12: =S12+T12 -> 10.008 | S12: 4.763 | T12: 5.245 | W12: 250125 | X12: =Y12+Z12 -> 21120 | Y12: 16041 | Z12: 5079
A13: 38899 | B13: 3436 | C13: =SUM(D13:F13) -> 138735 | D13: 62456 | E13: 59731 | F13: 16548 | G13: =H13+I13 -> 1767.962 | H13: 1125.031 | I13: 642.931 | J13: =K13+L13+M13 -> 184.262 | K13: 164.681 | L13: 12.5 | M13: 7.081 | N13: =O13+P13+Q13+R13 -> 602.967 | O13: 510.94222 | P13: 0.40973 | Q13: 83.190048 | R13: =S13+T13 -> 8.425 | S13: 5.183 | T13: 3.242 | W13: 212851 | X13: =Y13+Z13 -> 24911 | Y13: 18267 | Z13: 6644
A14: 38930 | B14: 4082 | C14: =SUM(D14:F14) -> 160147 | D14: 77846 | E14: 54578 | F14: 27723 | G14: =H14+I14 -> 1513.46 | H14: 906.105 | I14: 607.355 | J14: =K14+L14+M14 -> 170.194 | K14: 156.539 | L14: 7.9 | M14: 5.755 | N14: =O14+P14+Q14+R14 -> 545.697 | O14: 369.45607 | P14: 0.032123 | Q14: 166.01681 | R14: =S14+T14 -> 10.192 | S14: 5.89 | T14: 4.302 | W14: 264443 | X14: =Y14+Z14 -> 26025 | Y14: 19867 | Z14: 6158
A15: 38961 | B15: 3732 | C15: =SUM(D15:F15) -> 143445 | D15: 67992 | E15: 52979 | F15: 22474 | G15: =H15+I15 -> 1320.724 | H15: 685.555 | I15: 635.169 | J15: =K15+L15+M15 -> 139.687 | K15: 119 | L15: 15.5 | M15: 5.187 | N15: =O15+P15+Q15+R15 -> 683.95789 | O15: 574.5 | P15: 0.003477 | Q15: 102.89541 | R15: =S15+T15 -> 6.559 | S15: 5.152 | T15: 1.407 | W15: 212512 | X15: =Y15+Z15 -> 22683 | Y15: 19978 | Z15: 2705
A16: 38991 | B16: 4008 | C16: =SUM(D16:F16) -> 136481 | D16: 52479 | E16: 60165 | F16: 23837 | G16: =H16+I16 -> 1754.694 | H16: 911.519 | I16: 843.175 | J16: =K16+L16+M16 -> 185.471 | K16: =180.902-L16 -> 172.902 | L16: 8 | M16: 4.569 | N16: =O16+P16+Q16+R16 -> 653.565 | O16: =649.291-(P16+Q16) -> 546.85823 | P16: 0.0439 | Q16: 102.38887 | R16: =T16+S16 -> 4.274 | S16: 2.839 | T16: 1.435 | W16: 209810 | X16: =Y16+Z16 -> 26212 | Y16: 23365 | Z16: 2847
A17: 39022 | B17: 3955 | C17: =SUM(D17:F17) -> 140032 | D17: 64372 | E17: 59572 | F17: 16088 | G17: =H17+I17 -> 1849.702 | H17: 1069.379 | I17: 780.323 | J17: =K17+L17+M17 -> 146.154 | K17: =141.954-L17 -> 132.654 | L17: 9.3 | M17: 4.2 | N17: =O17+P17+Q17+R17 -> 552.846 | O17: =545.494-(P17+Q17) -> 448.81593 | P17: 0.001466 | Q17: 96.676609 | R17: =T17+S17 -> 7.352 | S17: 5.107 | T17: 2.245 | W17: 264354 | X17: =Y17+Z17 -> 25548 | Y17: 24292 | Z17: 1256
A18: 39052 | B18: 4533 | C18: =SUM(D18:F18) -> 167255 | D18: 71772 | E18: 77572 | F18: 17911 | G18: =H18+I18 -> 2366.807 | H18: 1451.342 | I18: 915.465 | J18: =K18+L18+M18 -> 185.112 | K18: =180.612-L18 -> 163.212 | L18: 17.4 | M18: 4.5 | N18: =O18+P18+Q18+R18 -> 843.489 | O18: =836.525-(P18+Q18) -> 687.61613 | P18: 0 | Q18: 148.90887 | R18: =T18+S18 -> 6.964 | S18: 5.137 | T18: 1.827 | W18: 354265 | X18: =Y18+Z18 -> 29655 | Y18: 26088 | Z18: 3567
A19: 39083 | B19: 4390 | C19: =SUM(D19:F19) -> 190910 | D19: 74934 | E19: 97798 | F19: 18178 | G19: =H19+I19 -> 2119.081 | H19: 673.458 | I19: 1445.623 | J19: =K19+L19+M19 -> 181.287 | K19: =174.377-L19 -> 165.777 | L19: 8.6 | M19: 6.91 | N19: =O19+P19+Q19+R19 -> 643.71 | O19: =635.894-(P19+Q19) -> 582.54077 | P19: 0.282778 | Q19: 53.070455 | R19: =T19+S19 -> 7.816 | S19: 5.348 | T19: 2.468 | W19: 354265 | X19: =Y19+Z19 -> 38066 | Y19: 28907 | Z19: 9159 | DJ19: Trafic voyageurs du PTB (nbre)
A20: 39114 | B20: 3874 | C20: =SUM(D20:F20) -> 135832 | D20: 55286 | E20: 70696 | F20: 9850 | G20: =H20+I20 -> 2201.635 | H20: 759.036 | I20: 1442.599 | J20: =K20+L20+M20 -> 130.736 | K20: 110.101 | L20: 15.41 | M20: 5.225 | N20: =O20+P20+Q20+R20 -> 612.14299 | O20: 494.662 | P20: 0.155882 | Q20: 110.07311 | R20: =T20+S20 -> 7.252 | S20: 4.388 | T20: 2.864 | W20: 333084 | X20: =Y20+Z20 -> 33651 | Y20: 25160 | Z20: 8491
A21: 39142 | B21: 4430 | C21: =SUM(D21:F21) -> 158448 | D21: 58816 | E21: 84249 | F21: 15383 | G21: =H21+I21 -> 2293.441 | H21: 709.018 | I21: 1584.423 | J21: =K21+L21+M21 -> 178.2 | K21: 164.1 | L21: 5.5 | M21: 8.6 | N21: =O21+P21+Q21+R21 -> 917.87647 | O21: 762.2 | P21: 0.397099 | Q21: 146.17937 | R21: =T21+S21 -> 9.1 | S21: 5.5 | T21: 3.6 | W21: 275820 | X21: =Y21+Z21 -> 30806 | Y21: 23859 | Z21: 6947
A22: 39173 | B22: 4492 | C22: =SUM(D22:F22) -> 159187 | D22: 58968 | E22: 83233 | F22: 16986 | G22: =H22+I22 -> 2392.449 | H22: 710.032 | I22: 1682.417 | J22: =K22+L22+M22 -> 184.477 | K22: 157.4 | L22: 19.8 | M22: 7.277 | N22: =O22+P22+Q22+R22 -> 683.11418 | O22: 564.4 | P22: 16.766764 | Q22: 87.308419 | R22: =T22+S22 -> 14.639 | S22: 6.602 | T22: 8.037 | W22: 243864.99 | X22: =Y22+Z22 -> 31232 | Y22: 25594 | Z22: 5638
A23: 39203 | B23: 4375 | C23: =SUM(D23:F23) -> 143754 | D23: 62433 | E23: 65186 | F23: 16135 | G23: =H23+I23 -> 2054.554 | H23: 703.576 | I23: 1350.978 | J23: =K23+L23+M23 -> 247.3 | K23: 215.4 | L23: 16.3 | M23: 15.6 | N23: =O23+P23+Q23+R23 -> 826.84365 | O23: 619.9 | P23: 130.28229 | Q23: 62.661353 | R23: =T23+S23 -> 14 | S23: 5.7 | T23: 8.3 | W23: 305447 | X23: =Y23+Z23 -> 25877 | Y23: 20941 | Z23: 4936
A24: 39234 | B24: 3699 | C24: =SUM(D24:F24) -> 132300 | D24: 55643 | E24: 62421 | F24: 14236 | G24: =H24+I24 -> 2109.617 | H24: 745.246 | I24: 1364.371 | J24: =K24+L24+M24 -> 177.908 | K24: 157.9 | L24: 13 | M24: 7.008 | N24: =O24+P24+Q24+R24 -> 556.61495 | O24: 443.5 | P24: 0.052254 | Q24: 101.6137 | R24: =T24+S24 -> 11.449 | S24: 7.567 | T24: 3.882 | W24: 298833 | X24: =Y24+Z24 -> 24967 | Y24: 18415 | Z24: 6552
A25: 39264 | B25: 3406 | C25: =SUM(D25:F25) -> 157952 | D25: 71192 | E25: 68973 | F25: 17787 | G25: =H25+I25 -> 2214.646 | H25: 914.594 | I25: 1300.052 | J25: =K25+L25+M25 -> 183.284 | K25: 158.6 | L25: 14.22 | M25: 10.464 | N25: =O25+P25+Q25+R25 -> 876.16681 | O25: 643.2 | P25: 130.47684 | Q25: 90.749972 | R25: =T25+S25 -> 11.74 | S25: 7.04 | T25: 4.7 | W25: 302700 | X25: =Y25+Z25 -> 27677 | Y25: 22467 | Z25: 5210
A26: 39295 | B26: 3348 | C26: =SUM(D26:F26) -> 178031 | D26: 69690 | E26: 81186 | F26: 27155 | G26: =H26+I26 -> 1952.279 | H26: 821.9 | I26: 1130.379 | J26: =K26+L26+M26 -> 184.837 | K26: 160.1 | L26: 17.6 | M26: 7.137 | N26: =O26+P26+Q26+R26 -> 669.00607 | O26: 465.7 | P26: 130.23482 | Q26: 62.382252 | R26: =T26+S26 -> 10.689 | S26: 6.9 | T26: 3.789 | W26: 301012 | X26: =Y26+Z26 -> 27885 | Y26: 24159 | Z26: 3726
A27: 39326 | B27: 3091 | C27: =SUM(D27:F27) -> 145703 | D27: 59329 | E27: 70544 | F27: 15830 | G27: =H27+I27 -> 1752.211 | H27: 789.965 | I27: 962.246 | J27: =K27+L27+M27 -> 224.083 | K27: 204.8 | L27: 14.2 | M27: 5.083 | N27: =O27+P27+Q27+R27 -> 818.56154 | O27: 747.7 | P27: 0.007691 | Q27: 62.24385 | R27: =T27+S27 -> 8.61 | S27: 4.778 | T27: 3.832 | W27: 295001 | X27: =Y27+Z27 -> 26812 | Y27: 24664 | Z27: 2148
A28: 39356 | B28: 3811 | C28: =SUM(D28:F28) -> 138227 | D28: 68412 | E28: 54458 | F28: 15357 | G28: =H28+I28 -> 1619.698 | H28: 793.976 | I28: 825.722 | J28: =K28+L28+M28 -> 211.043 | K28: 190.436 | L28: 14.6 | M28: 6.007 | N28: =O28+P28+Q28+R28 -> 826.344 | O28: 635.0951 | P28: 131.26252 | Q28: 53.467382 | R28: =T28+S28 -> 6.519 | S28: 2.533 | T28: 3.986 | W28: 328263 | X28: =Y28+Z28 -> 27542 | Y28: 26316 | Z28: 1226
A29: 39387 | B29: 4341 | C29: =SUM(D29:F29) -> 175592 | D29: 67289 | E29: 94701 | F29: 13602 | G29: =H29+I29 -> 1899.616 | H29: 863.458 | I29: 1036.158 | J29: =K29+L29+M29 -> 206.599 | K29: 176.633 | L29: 24.7 | M29: 5.266 | N29: =O29+P29+Q29+R29 -> 643.787 | O29: 581.98398 | P29: 0 | Q29: 55.951015 | R29: =T29+S29 -> 5.852 | S29: 3.637 | T29: 2.215 | W29: 266832 | X29: =Y29+Z29 -> 25598 | Y29: 24319 | Z29: 1279
A30: 39417 | B30: 3687 | C30: =SUM(D30:F30) -> 181318 | D30: 92684 | E30: 72308 | F30: 16326 | G30: =H30+I30 -> 2177.552 | H30: 939.043 | I30: 1238.509 | J30: =K30+L30+M30 -> 212.593 | K30: =206.555-L30 -> 188.155 | L30: 18.4 | M30: 6.038 | N30: =O30+P30+Q30+R30 -> 713.213 | O30: =706.01-(P30+Q30) -> 504.26257 | P30: 130.25893 | Q30: 71.488508 | R30: =T30+S30 -> 7.203 | S30: 5.102 | T30: 2.101 | W30: 281920 | X30: =Y30+Z30 -> 26043 | Y30: 24620 | Z30: 1423
A31: 39448 | B31: 4253 | C31: =SUM(D31:F31) -> 182956 | D31: 96488 | E31: 70826 | F31: 15642 | G31: =H31+I31 -> 1972.757 | H31: 1141.188 | I31: 831.569 | J31: =K31+L31+M31 -> 149.376 | K31: =143.773-L31 -> 111.873 | L31: 31.9 | M31: 5.603 | N31: =O31+P31+Q31+R31 -> 704.165 | O31: =696.655-(P31+Q31) -> 529.59966 | P31: 108.50983 | Q31: 58.545514 | R31: =T31+S31 -> 7.51 | S31: 4.904 | T31: 2.606 | W31: 309509 | X31: =Y31+Z31 -> 28277 | Y31: 19709 | Z31: 8568
A32: 39479 | B32: 3610 | C32: =SUM(D32:F32) -> 165277 | D32: 78812 | E32: 74361 | F32: 12104 | G32: =H32+I32 -> 1972.171 | H32: 1074.226 | I32: 897.945 | J32: =K32+L32+M32 -> 159.128 | K32: 129.3 | L32: 22.71 | M32: 7.118 | N32: =O32+P32+Q32+R32 -> 773.15631 | O32: 707.5 | P32: 0.063645 | Q32: 58.515667 | R32: =T32+S32 -> 7.077 | S32: 3.807 | T32: 3.27 | W32: 250520 | X32: =Y32+Z32 -> 28440 | Y32: 19142 | Z32: 9298
A33: 39508 | B33: 3159 | C33: =SUM(D33:F33) -> 166883 | D33: 81409 | E33: 65906 | F33: 19568 | G33: =H33+I33 -> 1883.096 | H33: 1112.541 | I33: 770.555 | J33: =K33+L33+M33 -> 246.366 | K33: 196.487 | L33: 44 | M33: 5.879 | N33: =O33+P33+Q33+R33 -> 625.275 | O33: 546.58931 | P33: 0.04714 | Q33: 71.885552 | R33: =T33+S33 -> 6.753 | S33: 4.07 | T33: 2.683 | W33: 260941 | X33: =Y33+Z33 -> 29660 | Y33: 19707 | Z33: 9953
A34: 39539 | B34: 3521 | C34: =SUM(D34:F34) -> 159968 | D34: 79537 | E34: 62572 | F34: 17859 | G34: =H34+I34 -> 1793.954 | H34: 937.084 | I34: 856.87 | J34: =K34+L34+M34 -> 176.024 | K34: 142.433 | L34: 25.7 | M34: 7.891 | N34: =O34+P34+Q34+R34 -> 762.574 | O34: 575.45886 | P34: 126.07265 | Q34: 51.27549 | R34: =T34+S34 -> 9.767 | S34: 4.385 | T34: 5.382 | W34: 309509 | X34: =Y34+Z34 -> 28190 | Y34: 19272 | Z34: 8918
A35: 39569 | B35: 3455 | C35: =SUM(D35:F35) -> 149964 | D35: 71073 | E35: 57003 | F35: 21888 | G35: =H35+I35 -> 1914.183 | H35: 896.887 | I35: 1017.296 | J35: =K35+L35+M35 -> 186.183 | K35: 147.5 | L35: 29 | M35: 9.683 | N35: =O35+P35+Q35+R35 -> 691.18467 | O35: 501.6 | P35: 128.86834 | Q35: 50.161331 | R35: =T35+S35 -> 10.555 | S35: 4.678 | T35: 5.877 | W35: 357785 | X35: =Y35+Z35 -> 29303 | Y35: 22639 | Z35: 6664
A36: 39600 | B36: 3053 | C36: =SUM(D36:F36) -> 143090 | D36: 62337 | E36: 56862 | F36: 23891 | G36: =H36+I36 -> 1676.568 | H36: 928.274 | I36: 748.294 | J36: =K36+L36+M36 -> 228.247 | K36: 207.914 | L36: 10.55 | M36: 9.783 | N36: =O36+P36+Q36+R36 -> 658.664 | O36: 491.96508 | P36: 135.70957 | Q36: 22.897344 | R36: =T36+S36 -> 8.092 | S36: 4.653 | T36: 3.439 | W36: 371554 | X36: =Y36+Z36 -> 23441 | Y36: 21163 | Z36: 2278
A37: 39630 | B37: 2713 | C37: =SUM(D37:F37) -> 161430 | D37: 68815 | E37: 70828 | F37: 21787 | G37: =H37+I37 -> 1933.045 | H37: 1051.383 | I37: 881.662 | J37: =K37+L37+M37 -> 202.187 | K37: 147.943 | L37: 45.9 | M37: 8.344 | N37: =O37+P37+Q37+R37 -> 620.26 | O37: 592.43396 | P37: 0.126808 | Q37: 19.869236 | R37: =T37+S37 -> 7.83 | S37: 4.547 | T37: 3.283 | W37: 396859 | X37: =Y37+Z37 -> 26821 | Y37: 25109 | Z37: 1712
A38: 39661 | B38: 3194 | C38: =SUM(D38:F38) -> 167399 | D38: 86566 | E38: 59384 | F38: 21449 | G38: =H38+I38 -> 1745.593 | H38: 900.048 | I38: 845.545 | J38: =K38+L38+M38 -> 169.227 | K38: 131.09 | L38: 34.65 | M38: 3.487 | N38: =O38+P38+Q38+R38 -> 640.14874 | O38: 481.3 | P38: 135.74162 | Q38: 15.537124 | R38: =T38+S38 -> 7.57 | S38: 5.033 | T38: 2.537 | W38: 360152 | X38: =Y38+Z38 -> 27246 | Y38: 24959 | Z38: 2287
A39: 39692 | B39: 3226 | C39: =SUM(D39:F39) -> 141994 | D39: 62226 | E39: 56947 | F39: 22821 | G39: =H39+I39 -> 1752.905 | H39: 796.999 | I39: 955.906 | J39: =K39+L39+M39 -> 161.096 | K39: 149.067 | L39: 2.65 | M39: 9.379 | N39: =O39+P39+Q39+R39 -> 716.825 | O39: 561.98014 | P39: 128.82333 | Q39: 19.114527 | R39: =T39+S39 -> 6.907 | S39: 4.763 | T39: 2.144 | W39: 402303 | X39: =Y39+Z39 -> 20424 | Y39: 19106 | Z39: 1318
A40: 39722 | B40: 3636 | C40: =SUM(D40:F40) -> 136227 | D40: 56320 | E40: 60036 | F40: 19871 | G40: =H40+I40 -> 1459.721 | H40: 642.776 | I40: 816.945 | J40: =K40+L40+M40 -> 174.516 | K40: 144.234 | L40: 26.1 | M40: 4.182 | N40: =O40+P40+Q40+R40 -> 622.245 | O40: 473.14046 | P40: 130.73812 | Q40: 15.056415 | R40: =T40+S40 -> 3.31 | S40: 1.718 | T40: 1.592 | W40: 402300 | X40: =Y40+Z40 -> 16630 | Y40: 15470 | Z40: 1160
A41: 39753 | B41: 3507 | C41: =SUM(D41:F41) -> 148375 | D41: 66062 | E41: 69166 | F41: 13147 | G41: =H41+I41 -> 1913.297 | H41: 958.758 | I41: 954.539 | J41: =K41+L41+M41 -> 175.382 | K41: 152.084 | L41: 18.25 | M41: 5.048 | N41: =O41+P41+Q41+R41 -> 886.212 | O41: 873.8079 | P41: 0.43759 | Q41: 7.95051 | R41: =T41+S41 -> 4.016 | S41: 2.686 | T41: 1.33 | W41: 390399 | X41: =Y41+Z41 -> 17213 | Y41: 16334 | Z41: 879
A42: 39783 | B42: 3489 | C42: =SUM(D42:F42) -> 158679 | D42: 75709 | E42: 69929 | F42: 13041 | G42: =H42+I42 -> 1798.563 | H42: 882.887 | I42: 915.676 | J42: =K42+L42+M42 -> 204.644 | K42: 158.508 | L42: 39.8 | M42: 6.336 | N42: =O42+P42+Q42+R42 -> 657.151 | O42: 603.47625 | P42: 37.608612 | Q42: 8.638135 | R42: =T42+S42 -> 7.428 | S42: 5.56 | T42: 1.868 | U42: rot | V42: bil | W42: 342394 | X42: =Y42+Z42 -> 22431 | Y42: 21780 | Z42: 651
A43: 39814 | B43: 3976 | C43: =SUM(D43:F43) -> 160930 | D43: 80882 | E43: 71350 | F43: 8698 | G43: =H43+I43 -> 1643.598 | H43: 956.012 | I43: 687.586 | J43: =K43+L43+M43 -> 153.172 | K43: 129.885 | L43: 15.1 | M43: 8.187 | N43: =O43+P43+Q43+R43 -> 402.591 | O43: 267.78317 | P43: 122.71457 | Q43: 3.710262 | R43: =T43+S43 -> 8.383 | S43: 5.16 | T43: 3.223 | U43: 357 | V43: 28515 | W43: 419356 | X43: =Y43+Z43 -> 24628 | Y43: 22196 | Z43: 2432
A44: 39845 | B44: 3760 | C44: =SUM(D44:F44) -> 142361 | D44: 65488 | E44: 65710 | F44: 11163 | G44: =H44+I44 -> 1675.418 | H44: 973.342 | I44: 702.076 | J44: =K44+L44+M44 -> 160.053 | K44: 130.828 | L44: 22.75 | M44: 6.475 | N44: =O44+P44+Q44+R44 -> 449.396 | O44: 411.12832 | P44: 0.400412 | Q44: 30.57127 | R44: =T44+S44 -> 7.296 | S44: 5.329 | T44: 1.967 | U44: 331 | V44: 25026 | W44: 341520 | X44: =Y44+Z44 -> 22728 | Y44: 17930 | Z44: 4798
A45: 39873 | B45: 3963 | C45: =SUM(D45:F45) -> 150120 | D45: 83154 | E45: 56422 | F45: 10544 | G45: =H45+I45 -> 2017.081 | H45: 1147.908 | I45: 869.173 | J45: =K45+L45+M45 -> 194.124 | K45: 170.96 | L45: 16.2 | M45: 6.964 | N45: =O45+P45+Q45+R45 -> 731.473 | O45: 538.84537 | P45: 126.9473 | Q45: 56.839325 | R45: =T45+S45 -> 8.841 | S45: 6.206 | T45: 2.635 | U45: 376 | V45: 34325 | W45: 412497 | X45: =Y45+Z45 -> 28862.6 | Y45: 19284.6 | Z45: 9578
A46: 39904 | B46: 3333 | C46: =SUM(D46:F46) -> 141028 | D46: 75294 | E46: 59714 | F46: 6020 | G46: =H46+I46 -> 1907.232 | H46: 1116.899 | I46: 790.333 | J46: =K46+L46+M46 -> 137.184 | K46: 110.811 | L46: 15.2 | M46: 11.173 | N46: =O46+P46+Q46+R46 -> 660.44 | O46: 500.40338 | P46: 0.566393 | Q46: 146.59823 | R46: =T46+S46 -> 12.872 | S46: 5.213 | T46: 7.659 | U46: 362 | V46: 38275 | W46: 480274 | X46: =Y46+Z46 -> 23710.6 | Y46: 16817.6 | Z46: 6893
A47: 39934 | B47: 3295 | C47: =SUM(D47:F47) -> 120881 | D47: 66618 | E47: 46991 | F47: 7272 | G47: =H47+I47 -> 1704.581 | H47: 960.055 | I47: 744.526 | J47: =K47+L47+M47 -> 260.761 | K47: 237.046 | L47: 12.6 | M47: 11.115 | N47: =O47+P47+Q47+R47 -> 488.26 | O47: 424.91641 | P47: 0.009701 | Q47: 49.696885 | R47: =T47+S47 -> 13.637 | S47: 5.775 | T47: 7.862 | U47: 376 | V47: 41074 | W47: 467808 | X47: =Y47+Z47 -> 27453 | Y47: 21479 | Z47: 5974
A48: 39965 | B48: 2752 | C48: =SUM(D48:F48) -> 111088 | D48: 55521 | E48: 47999 | F48: 7568 | G48: =H48+I48 -> 1872.163 | H48: 1149.33 | I48: 722.833 | J48: =K48+L48+M48 -> 171.782 | K48: 147.532 | L48: 14.4 | M48: 9.85 | N48: =O48+P48+Q48+R48 -> 687.563 | O48: 484.39238 | P48: 129.28667 | Q48: 65.105948 | R48: =T48+S48 -> 8.778 | S48: 4.937 | T48: 3.841 | U48: 121 | V48: 46506 | W48: 419099 | X48: =Y48+Z48 -> 26348 | Y48: 23339 | Z48: 3009
A49: 39995 | B49: 3012 | C49: =SUM(D49:F49) -> 137081 | D49: 63658 | E49: 61653 | F49: 11770 | G49: =H49+I49 -> 2001.758 | H49: 1147.83 | I49: 853.928 | J49: =K49+L49+M49 -> 205.002 | K49: =194.78-L49 -> 181.53 | L49: 13.25 | M49: 10.222 | N49: =O49+P49+Q49+R49 -> 674.326 | O49: =666.728-(P49+Q49) -> 623.16315 | P49: 43.287588 | Q49: 0.27726 | R49: =T49+S49 -> 7.598 | S49: 4.586 | T49: 3.012 | U49: 267 | V49: 50288 | W49: 506715 | X49: =Y49+Z49 -> 29535 | Y49: 27429 | Z49: 2106
A50: 40026 | B50: 2970 | C50: =SUM(D50:F50) -> 140454 | D50: 75244 | E50: 52768 | F50: 12442 | G50: =H50+I50 -> 1694.68 | H50: 1035.154 | I50: 659.526 | J50: =K50+L50+M50 -> 164.776 | K50: =159.27-L50 -> 150.87 | L50: 8.4 | M50: 5.506 | N50: =O50+P50+Q50+R50 -> 983.175 | O50: =975.721-(P50+Q50) -> 935.33456 | P50: 0.607264 | Q50: 39.779179 | R50: =S50+T50 -> 7.454 | S50: 4.716 | T50: 2.738 | U50: 381 | V50: 50789 | W50: 399183 | X50: =Y50+Z50 -> 26869 | Y50: 25048 | Z50: 1821
A51: 40057 | B51: 2985 | C51: =SUM(D51:F51) -> 100214 | D51: 51276 | E51: 45028 | F51: 3910 | G51: =H51+I51 -> 1527.39 | H51: 765.677 | I51: 761.713 | J51: =K51+L51+M51 -> 158.953 | K51: =152.578-L51 -> 138.578 | L51: 14 | M51: 6.375 | N51: =O51+P51+Q51+R51 -> 724.671 | O51: =717.76-(P51+Q51) -> 477.15382 | P51: 128.84793 | Q51: 111.75825 | R51: =S51+T51 -> 6.911 | S51: 4.294 | T51: 2.617 | U51: 340 | V51: 20660 | W51: 362811 | X51: =Y51+Z51 -> 23255 | Y51: 22180 | Z51: 1075
A52: 40087 | B52: 3595 | C52: =SUM(D52:F52) -> 119838 | D52: 54625 | E52: 59989 | F52: 5224 | G52: =H52+I52 -> 1722.772 | H52: 829.524 | I52: 893.248 | J52: =K52+L52+M52 -> 140.707 | K52: 129.03 | L52: 6.9 | M52: 4.777 | N52: =O52+P52+Q52+R52 -> 572.47081 | O52: 539.69078 | P52: 0.016978 | Q52: 26.354059 | R52: =S52+T52 -> 6.409 | S52: 1.947 | T52: 4.462 | U52: 363 | V52: 26454 | W52: 388096 | X52: =Y52+Z52 -> 28034 | Y52: 26996 | Z52: 1038
A53: 40118 | B53: 3906 | C53: =SUM(D53:F53) -> 132119 | D53: 58714 | E53: 67443 | F53: 5962 | G53: =H53+I53 -> 1880.622 | H53: 945.591 | I53: 935.031 | J53: =K53+L53+M53 -> 172.335 | K53: 151.7 | L53: 17 | M53: 3.635 | N53: =O53+P53+Q53+R53 -> 531.634 | O53: 282.15546 | P53: 134.60412 | Q53: 109.29042 | R53: =S53+T53 -> 5.584 | S53: 3.849 | T53: 1.735 | U53: 332 | V53: 25137 | W53: 379024 | X53: =Y53+Z53 -> 23694 | Y53: 21894 | Z53: 1800
A54: 40148 | B54: 3701 | C54: =SUM(D54:F54) -> 142451 | D54: 63475 | E54: 68970 | F54: 10006 | G54: =H54+I54 -> 1941.155 | H54: 1043.6 | I54: 897.555 | J54: =K54+L54+M54 -> 166.649 | K54: 141.865 | L54: 18.75 | M54: 6.034 | N54: =O54+P54+Q54+R54 -> 447.767 | O54: 321.25682 | P54: 0.113858 | Q54: 119.47532 | R54: =S54+T54 -> 6.921 | S54: 4.372 | T54: 2.549 | U54: 300 | V54: 29513 | W54: 344133 | X54: =Y54+Z54 -> 22956 | Y54: 21901 | Z54: 1055
A55: 40179 | B55: 3693 | C55: =SUM(D55:F55) -> 151056 | D55: 71584 | E55: 68517 | F55: 10955 | G55: =H55+I55 -> 2032.698 | H55: 1220.672 | I55: 812.026 | J55: =+K55+L55+M55 -> 167.261 | K55: 129.199 | L55: 30.3 | M55: 7.762 | N55: =+O55+P55+Q55+R55 -> 775.96054 | O55: 710.31392 | P55: 0.921078 | Q55: 58.028535 | R55: 6.697 | S55: 3.183 | T55: 3.514 | U55: 353 | V55: 27826 | W55: 346753 | X55: =Y55+Z55 -> 23828 | Y55: 21007 | Z55: 2821
A56: 40210 | B56: 3439 | C56: =SUM(D56:F56) -> 131799 | D56: 66179 | E56: 62393 | F56: 3227 | G56: =H56+I56 -> 1882.789 | H56: 1125.94 | I56: 756.849 | J56: =+K56+L56+M56 -> 447.263 | K56: =440.32-L56 -> 424.72 | L56: 15.6 | M56: 6.943 | N56: =+O56+P56+Q56+R56 -> 591.958 | O56: =583.865-(P56+Q56) -> 396.1311 | P56: 128.41562 | Q56: 59.318283 | R56: =T56+S56 -> 8.093 | S56: 3.535 | T56: 4.558 | U56: 321 | V56: 27824 | W56: 250827 | X56: =Y56+Z56 -> 28313 | Y56: 22138 | Z56: 6175
A57: 40238 | B57: 3880 | C57: =SUM(D57:F57) -> 144316 | D57: 80436 | E57: 59811 | F57: 4069 | G57: =H57+I57 -> 2487.466 | H57: 1548.884 | I57: 938.582 | J57: =+K57+L57+M57 -> 215.413 | K57: =208.742-L57 -> 194.092 | L57: 14.65 | M57: 6.671 | N57: =+O57+P57+Q57+R57 -> 822.917 | O57: =813.279-(P57+Q57) -> 640.81761 | P57: 0.132824 | Q57: 172.32857 | R57: =T57+S57 -> 9.638 | S57: 6.196 | T57: 3.442 | U57: 365 | V57: 36048 | W57: 464442 | X57: =Y57+Z57 -> 34515.9 | Y57: 27371.9 | Z57: 7144
A58: 40269 | B58: 4495 | C58: =SUM(D58:F58) -> 131586 | D58: 73513 | E58: 53656 | F58: 4417 | G58: =H58+I58 -> 1874.12 | H58: 1048.889 | I58: 825.231 | J58: =+K58+L58+M58 -> 199.411 | K58: =188.988-L58 -> 176.488 | L58: 12.5 | M58: 10.423 | N58: =+O58+P58+Q58+R58 -> 876.705 | O58: =863.818-(P58+Q58) -> 791.8448 | P58: 0.573076 | Q58: 71.400121 | R58: =T58+S58 -> 12.887 | S58: 5.938 | T58: 6.949 | U58: 355 | V58: 40939 | W58: 434655 | X58: =Y58+Z58 -> 30730 | Y58: 24818 | Z58: 5912
A59: 40299 | B59: 3740 | C59: =SUM(D59:F59) -> 115845 | D59: 62402 | E59: 50453 | F59: 2990 | G59: =H59+I59 -> 2190.137 | H59: 1313.568 | I59: 876.569 | J59: =+K59+L59+M59 -> 216.567 | K59: =207.025-L59 -> 183.325 | L59: 23.7 | M59: 9.542 | N59: =+O59+P59+Q59+R59 -> 544.759 | O59: =527.421-(P59+Q59) -> 250.19518 | P59: 129.20416 | Q59: 148.02166 | R59: =T59+S59 -> 17.338 | S59: 6.056 | T59: 11.282 | U59: 367 | V59: 46684 | W59: 316832 | X59: =Y59+Z59 -> 30856 | Y59: 26334 | Z59: 4522
A60: 40330 | B60: 3231 | C60: =SUM(D60:F60) -> 112555 | D60: 53433 | E60: 49440 | F60: 9682 | G60: =H60+I60 -> 2089.128 | H60: 1193.353 | I60: 895.775 | J60: =+K60+L60+M60 -> 217.655 | K60: =207.519-L60 -> 194.719 | L60: 12.8 | M60: 10.136 | N60: =+O60+P60+Q60+R60 -> 861.444 | O60: =853.467-(P60+Q60) -> 825.7197 | P60: 0.35295 | Q60: 27.394355 | R60: =T60+S60 -> 7.977 | S60: 3.928 | T60: 4.049 | U60: 344 | V60: 44571 | W60: 326466 | X60: =Y60+Z60 -> 23555 | Y60: 21131 | Z60: 2424
A61: 40360 | B61: 3187 | C61: =SUM(D61:F61) -> 165500 | D61: 68856 | E61: 75489 | F61: 21155 | G61: =H61+I61 -> 2132.383 | H61: 1200.871 | I61: 931.512 | J61: =+K61+L61+M61 -> 140.574 | K61: =132.93-L61 -> 121.43 | L61: 11.5 | M61: 7.644 | N61: =+O61+P61+Q61+R61 -> 794.025 | O61: =786.132-(P61+Q61) -> 592.53875 | P61: 136.00513 | Q61: 57.588118 | R61: =T61+S61 -> 7.893 | S61: 4.741 | T61: 3.152 | U61: 393 | V61: 55686 | W61: 297892 | X61: =Y61+Z61 -> 30784 | Y61: 28989 | Z61: 1795
A62: 40391 | B62: 2840 | C62: =SUM(D62:F62) -> 158452 | D62: 82004 | E62: 55196 | F62: 21252 | G62: =H62+I62 -> 1965.299 | H62: 1065.111 | I62: 900.188 | J62: =+K62+L62+M62 -> 177.432 | K62: =170.731-L62 -> 154.631 | L62: 16.1 | M62: 6.701 | N62: =+O62+P62+Q62+R62 -> 472.614 | O62: =465.473-(P62+Q62) -> 381.23728 | P62: 0.034476 | Q62: 84.20124 | R62: =T62+S62 -> 7.141 | S62: 4.397 | T62: 2.744 | U62: 380 | V62: 44711 | W62: 281563 | X62: =Y62+Z62 -> 21982 | Y62: 19731 | Z62: 2251
A63: 40422 | B63: 2734 | C63: =SUM(D63:F63) -> 124086 | D63: 59813 | E63: 52015 | F63: 12258 | G63: =H63+I63 -> 1628.649 | H63: 904.835 | I63: 723.814 | J63: =+K63+L63+M63 -> 114.024 | K63: =108.251-L63 -> 102.751 | L63: 5.5 | M63: 5.773 | N63: =+O63+P63+Q63+R63 -> 817.454 | O63: =810.301-(P63+Q63) -> 595.74867 | P63: 135.32993 | Q63: 79.222402 | R63: =T63+S63 -> 7.153 | S63: 4.831 | T63: 2.322 | U63: 348 | V63: 23490 | W63: 266405 | X63: =Y63+Z63 -> 20793 | Y63: 19671 | Z63: 1122
A64: 40452 | B64: 3967 | C64: =SUM(D64:F64) -> 148187 | D64: 64024 | E64: 60888 | F64: 23275 | G64: =H64+I64 -> 1823.795 | H64: 933.963 | I64: 889.832 | J64: =+K64+L64+M64 -> 187.94 | K64: =182.579-L64 -> 163.079 | L64: 19.5 | M64: 5.361 | N64: =+O64+P64+Q64+R64 -> 618.599 | O64: =614.051-(P64+Q64) -> 545.37822 | P64: 0 | Q64: 68.672778 | R64: =T64+S64 -> 4.548 | S64: 2.311 | T64: 2.237 | U64: 371 | V64: 31083 | W64: 296074 | X64: =Y64+Z64 -> 24461 | Y64: 23031 | Z64: 1430
A65: 40483 | B65: 3746 | C65: =SUM(D65:F65) -> 162090 | D65: 66950 | E65: 70958 | F65: 24182 | G65: =H65+I65 -> 1871 | H65: 980 | I65: 891 | J65: =+K65+L65+M65 -> 239.503 | K65: =235.106-L65 -> 207.106 | L65: 28 | M65: 4.397 | N65: =+O65+P65+Q65+R65 -> 776.991 | O65: =770.878-(P65+Q65) -> 692.9972 | P65: 0.089156 | Q65: 77.791644 | R65: =T65+S65 -> 6.113 | S65: 4.428 | T65: 1.685 | U65: 356 | V65: 27697 | W65: 257401 | X65: =Y65+Z65 -> 22325 | Y65: 20989 | Z65: 1336
A66: 40513 | B66: 5222 | C66: =SUM(D66:F66) -> 187951 | D66: 84227 | E66: 78062 | F66: 25662 | G66: =H66+I66 -> 2422 | H66: 1506 | I66: 916 | J66: =+K66+L66+M66 -> 196.413 | K66: 170.486 | L66: 14.3 | M66: 11.627 | N66: =+O66+P66+Q66+R66 -> 704.854 | O66: 500.68791 | P66: 129.51595 | Q66: 59.105135 | R66: 15.545 | S66: 5.875 | T66: 9.67 | U66: 360 | V66: 30879 | W66: 271879 | X66: =Y66+Z66 -> 25190 | Y66: 21714 | Z66: 3476
A67: 40544 | B67: 3561 | C67: =SUM(D67:F67) -> 171286 | D67: 74768 | E67: 80027 | F67: 16491 | G67: =H67+I67 -> 2129.616 | H67: 1191.582 | I67: 938.034 | J67: =+K67+L67+M67 -> 228.968 | K67: 191.875 | L67: 25.78 | M67: 11.313 | N67: =+O67+P67+Q67+R67 -> 715.101 | O67: 575.95536 | P67: 0 | Q67: 127.92664 | R67: =T67+S67 -> 11.219 | S67: 5.476 | T67: 5.743 | U67: 360 | V67: 26843 | W67: 172482 | X67: =Y67+Z67 -> 30270 | Y67: 22096 | Z67: 8174
A68: 40575 | B68: 2795 | C68: =SUM(D68:F68) -> 169418 | D68: 78793 | E68: 78225 | F68: 12400 | G68: =H68+I68 -> 1968.612 | H68: 1079.797 | I68: 888.815 | J68: =+K68+L68+M68 -> 210.048 | K68: 188.177 | L68: 9.8 | M68: 12.071 | N68: =+O68+P68+Q68+R68 -> 775.428 | O68: 762.35311 | P68: 0 | Q68: 2.613893 | R68: =T68+S68 -> 10.461 | S68: 5.235 | T68: 5.226 | U68: 330 | V68: 30661 | W68: 193938 | X68: =Y68+Z68 -> 27879 | Y68: 21215 | Z68: 6664
A69: 40603 | B69: 3026 | C69: =SUM(D69:F69) -> 173761 | D69: 86591 | E69: 69858 | F69: 17312 | G69: =H69+I69 -> 2522.196 | H69: 1249.613 | I69: 1272.583 | J69: =+K69+L69+M69 -> 278.047 | K69: 242.709 | L69: 23.025 | M69: 12.313 | N69: =+O69+P69+Q69+R69 -> 743.765 | O69: 527.59275 | P69: 123.09335 | Q69: 76.126901 | R69: =T69+S69 -> 16.952 | S69: 5.622 | T69: 11.33 | U69: 362 | V69: 38873 | W69: 250305 | X69: =Y69+Z69 -> 32365 | Y69: 23940 | Z69: 8425
A70: 40634 | B70: 4093 | C70: =SUM(D70:F70) -> 163743 | D70: 78634 | E70: 69091 | F70: 16018 | G70: =H70+I70 -> 2231.201 | H70: 1115.821 | I70: 1115.38 | J70: =+K70+L70+M70 -> 868.327 | K70: 830.027 | L70: 22.66 | M70: 15.64 | N70: =+O70+P70+Q70+R70 -> 758.69 | O70: 663.36234 | P70: 0 | Q70: 59.569661 | R70: =T70+S70 -> 35.758 | S70: 6.212 | T70: 29.546 | U70: 383 | V70: 38538 | W70: 197838 | X70: =Y70+Z70 -> 27061 | Y70: 21888 | Z70: 5173
A71: 40664 | B71: 3626 | C71: =SUM(D71:F71) -> 144156 | D71: 73613 | E71: 60874 | F71: 9669 | G71: =H71+I71 -> 2276.077 | H71: 1077.158 | I71: 1198.919 | J71: =+K71+L71+M71 -> 285.175 | K71: 245.188 | L71: 23.6 | M71: 16.387 | N71: =+O71+P71+Q71+R71 -> 772.655 | O71: 573.27327 | P71: 122.11414 | Q71: 47.805586 | R71: =T71+S71 -> 29.462 | S71: 7.067 | T71: 22.395 | U71: 394 | V71: 42177 | W71: 246451 | X71: =Y71+Z71 -> 20803 | Y71: 18167 | Z71: 2636
A72: 40695 | B72: 2808 | C72: =SUM(D72:F72) -> 133283 | D72: 62640 | E72: 61801 | F72: 8842 | G72: =H72+I72 -> 2459.41 | H72: 1361.852 | I72: 1097.558 | J72: =+K72+L72+M72 -> 238.889 | K72: 199.502 | L72: 28.816 | M72: 10.571 | N72: =+O72+P72+Q72+R72 -> 582.111 | O72: 520.96434 | P72: 0.102774 | Q72: 42.727882 | R72: =T72+S72 -> 18.316 | S72: 6.16 | T72: 12.156 | U72: 363 | V72: 50287 | W72: 199244 | X72: =Y72+Z72 -> 24478 | Y72: 19017 | Z72: 5461
A73: 40725 | B73: 3179 | C73: =SUM(D73:F73) -> 161145 | D73: 74558 | E73: 74686 | F73: 11901 | G73: =H73+I73 -> 2146.598 | H73: 1275.15 | I73: 871.448 | J73: =+K73+L73+M73 -> 256.515 | K73: 242.801 | L73: 3.1 | M73: 10.614 | N73: =+O73+P73+Q73+R73 -> 1183.929 | O73: 1090.2582 | P73: 1.663363 | Q73: 82.598391 | R73: =T73+S73 -> 9.409 | S73: 6.941 | T73: 2.468 | U73: 466 | V73: 65294 | W73: 191088 | X73: =Y73+Z73 -> 22426 | Y73: 18581 | Z73: 3845
A74: 40756 | B74: 2675 | C74: =SUM(D74:F74) -> 141602 | D74: 72585 | E74: 58277 | F74: 10740 | G74: =H74+I74 -> 2069.69 | H74: 1086.602 | I74: 983.088 | J74: =+K74+L74+M74 -> 247.097 | K74: 216.755 | L74: 22.35 | M74: 7.992 | N74: =+O74+P74+Q74+R74 -> 703.219 | O74: 474.56366 | P74: 128.08727 | Q74: 90.988076 | R74: =T74+S74 -> 9.58 | S74: 6.575 | T74: 3.005 | U74: 349 | V74: 24980 | W74: 175009 | X74: =Y74+Z74 -> 23961 | Y74: 18647 | Z74: 5314
A75: 40787 | B75: 3084 | C75: =SUM(D75:F75) -> 135172 | D75: 67765 | E75: 61860 | F75: 5547 | G75: =H75+I75 -> 1903.493 | H75: 840.372 | I75: 1063.121 | J75: =+K75+L75+M75 -> 221.03 | K75: 193.085 | L75: 22.5 | M75: 5.445 | N75: =+O75+P75+Q75+R75 -> 821.92 | O75: 620.66859 | P75: 122.90211 | Q75: 67.773309 | R75: =T75+S75 -> 10.576 | S75: 6.347 | T75: 4.229 | U75: 342 | V75: 35563 | W75: 181067 | X75: =Y75+Z75 -> 17838 | Y75: 15322 | Z75: 2516
A76: 40817 | B76: 3476 | C76: =SUM(D76:F76) -> 149063 | D76: 63505 | E76: 73950 | F76: 11608 | G76: =H76+I76 -> 1803.995 | H76: 806.235 | I76: 997.76 | J76: =+K76+L76+M76 -> 206.884 | K76: 191.32 | L76: 8 | M76: 7.564 | N76: =+O76+P76+Q76+R76 -> 1051.212 | O76: 968.51109 | P76: 0.142833 | Q76: 76.892081 | R76: =T76+S76 -> 5.666 | S76: 3.515 | T76: 2.151 | U76: 351 | V76: 28645 | W76: 217351 | X76: =Y76+Z76 -> 17499 | Y76: 14040 | Z76: 3459
A77: 40848 | B77: 3704 | C77: =SUM(D77:F77) -> 162547 | D77: 70285 | E77: 80142 | F77: 12120 | G77: =H77+I77 -> 1504.086 | H77: 727.737 | I77: 776.349 | J77: =+K77+L77+M77 -> 217.783 | K77: 191.01 | L77: 23.72 | M77: 3.053 | N77: =+O77+P77+Q77+R77 -> 678.144 | O77: 566.44409 | P77: 0.198165 | Q77: 102.79274 | R77: =T77+S77 -> 8.709 | S77: 4.873 | T77: 3.836 | U77: 330 | V77: 24221 | W77: 187396 | X77: =Y77+Z77 -> 21227 | Y77: 19663 | Z77: 1564
A78: 40878 | B78: 3396 | C78: =SUM(D78:F78) -> 194587 | D78: 77813 | E78: 90920 | F78: 25854 | G78: =H78+I78 -> 1844.165 | H78: 1248.044 | I78: 596.121 | J78: =+K78+L78+M78 -> 346.542 | K78: 324.494 | L78: 15.5 | M78: 6.548 | N78: =+O78+P78+Q78+R78 -> 815.317 | O78: 498.71462 | P78: 124.49126 | Q78: 182.58212 | R78: =T78+S78 -> 9.529 | S78: 5.731 | T78: 3.798 | U78: 358 | V78: 29363 | W78: 222545 | X78: =Y78+Z78 -> 18286 | Y78: 14718 | Z78: 3568
... A90: 41244 | B90: 2803 | C90: =SUM(D90:F90) -> 182533 | D90: 74078 | E90: 94857 | F90: 13598 | G90: =H90+I90 -> 2194.357 | H90: 1243.713 | I90: 950.644 | J90: =+K90+L90+M90 -> 192.325 | K90: 147.39 | L90: 37.076 | M90: 7.859 | N90: =+O90+P90+Q90+R90 -> 708.656 | O90: 462.28905 | P90: 127.76763 | Q90: 111.36532 | R90: =T90+S90 -> 7.234 | S90: 4.171 | T90: 3.063 | U90: 377.7037 | V90: 27075 | W90: 181270 | X90: =Y90+Z90 -> 25125 | Y90: 19507 | Z90: 5618
A91: 41275 | B91: 3070 | C91: =SUM(D91:F91) -> 156022 | D91: 74098 | E91: 69103 | F91: 12821 | G91: =H91+I91 -> 2385.373 | H91: 1267.396 | I91: 1117.977 | J91: =+K91+L91+M91 -> 234.992 | K91: =223.646-L91 -> 223.646 | L91: 0 | M91: 11.346 | N91: =+O91+P91+Q91+R91 -> 682.1 | O91: =674.486-(P91+Q91) -> 598.46337 | P91: 0.027426 | Q91: 75.995202 | R91: =T91+S91 -> 7.614 | S91: 4.842 | T91: 2.772 | U91: 362 | V91: 24171 | W91: 175250 | X91: =Y91+Z91 -> 31685 | Y91: 21602 | Z91: 10083
A92: 41306 | B92: 3154 | C92: =SUM(D92:F92) -> 156374 | D92: 74282 | E92: 69269 | F92: 12823 | G92: =H92+I92 -> 2149.23 | H92: 1237.886 | I92: 911.344 | J92: =+K92+L92+M92 -> 508.619 | K92: =497.236-L92 -> 383.132 | L92: 114.104 | M92: 11.383 | N92: =+O92+P92+Q92+R92 -> 493.299 | O92: =486.481-(P92+Q92) -> 312.52694 | P92: 128.82814 | Q92: 45.125919 | R92: =T92+S92 -> 6.818 | S92: 4.184 | T92: 2.634 | U92: 329 | V92: 21465 | W92: 206878 | X92: =Y92+Z92 -> 28672 | Y92: 19520 | Z92: 9152
A93: 41334 | B93: 3084 | C93: =SUM(D93:F93) -> 186061 | D93: 94132 | E93: 76078 | F93: 15851 | G93: =H93+I93 -> 3189.834 | H93: 1986.497 | I93: 1203.337 | J93: =+K93+L93+M93 -> 545.12 | K93: =533.634-L93 -> 503.734 | L93: 29.9 | M93: 11.486 | N93: =+O93+P93+Q93+R93 -> 928.416 | O93: =919.975-(P93+Q93) -> 874.91701 | P93: 0.708715 | Q93: 44.349279 | R93: =T93+S93 -> 8.441 | S93: 5.453 | T93: 2.988 | U93: 399 | V93: 37377 | W93: 226721 | X93: =Y93+Z93 -> 31773 | Y93: 20228 | Z93: 11545
A94: 41365 | B94: 3228 | C94: =SUM(D94:F94) -> 158129 | D94: 77154 | E94: 66347 | F94: 14628 | G94: =H94+I94 -> 2292.373 | H94: 1449.404 | I94: 842.969 | J94: =+K94+L94+M94 -> 222.13 | K94: =207.888-L94 -> 189.488 | L94: 18.4 | M94: 14.242 | N94: =+O94+P94+Q94+R94 -> 768.485 | O94: =756.88-(P94+Q94) -> 574.63773 | P94: 127.51981 | Q94: 54.722456 | R94: =T94+S94 -> 11.605 | S94: 7.799 | T94: 3.806 | U94: 340 | V94: 34114 | W94: 221378 | X94: =Y94+Z94 -> 24661 | Y94: 14669 | Z94: 9992
A95: 41395 | B95: 3666 | C95: =SUM(D95:F95) -> 140542 | D95: 71084 | E95: 58732 | F95: 10726 | G95: =H95+I95 -> 2005.306 | H95: 988.027 | I95: 1017.279 | J95: =+K95+L95+M95 -> 319.39 | K95: =298.056-L95 -> 252.792 | L95: 45.264 | M95: 21.334 | N95: =+O95+P95+Q95+R95 -> 784.588 | O95: =766.785-(P95+Q95) -> 600.3692 | P95: 127.60501 | Q95: 38.810783 | R95: =T95+S95 -> 17.803 | S95: 7.288 | T95: 10.515 | U95: 419 | V95: 43808 | W95: 213904 | X95: =Y95+Z95 -> 28927 | Y95: 18791 | Z95: 10136
A96: 41426 | B96: 2615 | C96: =SUM(D96:F96) -> 144750 | D96: 65372 | E96: 66926 | F96: 12452 | G96: =H96+I96 -> 2013.33 | H96: 1101.683 | I96: 911.647 | J96: =+K96+L96+M96 -> 283.771 | K96: 226.153 | L96: 43.234 | M96: 14.384 | N96: =+O96+P96+Q96+R96 -> 876.27579 | O96: =865.152785-(P96+Q96) -> 799.8658 | P96: 0.391893 | Q96: 64.895095 | R96: =T96+S96 -> 11.123 | S96: 5.645 | T96: 5.478 | U96: 177 | V96: 39410 | W96: 219302 | X96: =Y96+Z96 -> 24214 | Y96: 17375 | Z96: 6839
A97: 41456 | B97: 2703 | C97: =SUM(D97:F97) -> 157784 | D97: 68158 | E97: 72587 | F97: 17039 | G97: =H97+I97 -> 2416.081 | H97: 1412.332 | I97: 1003.749 | J97: =+K97+L97+M97 -> 282.667 | K97: 244.538 | L97: 32 | M97: 6.129 | N97: =+O97+P97+Q97+R97 -> 963.27 | O97: =945.629-(P97+Q97) -> 755.79402 | P97: 88.176239 | Q97: 101.65874 | R97: =T97+S97 -> 17.641 | S97: 5.609 | T97: 12.032 | U97: 387 | V97: 38272 | W97: 245843 | X97: =Y97+Z97 -> 20274 | Y97: 17368 | Z97: 2906
A98: 41487 | B98: 2403 | C98: =SUM(D98:F98) -> 160993 | D98: 79429 | E98: 68546 | F98: 13018 | G98: =H98+I98 -> 1830.859 | H98: 974.658 | I98: 856.201 | J98: =+K98+L98+M98 -> 298.637 | K98: 272.435 | L98: 18.58 | M98: 7.622 | N98: =+O98+P98+Q98+R98 -> 1736.58 | O98: 1662.5067 | P98: 0.630509 | Q98: 47.363823 | R98: =T98+S98 -> 26.079 | S98: 6.004 | T98: 20.075 | U98: 400 | V98: 44645 | W98: 206460 | X98: =Y98+Z98 -> 17675 | Y98: 15861 | Z98: 1814
A99: 41518 | B99: 2795 | C99: =SUM(D99:F99) -> 151910 | D99: 75463 | E99: 65090 | F99: 11357 | G99: =H99+I99 -> 2008.164 | H99: 894.903 | I99: 1113.261 | J99: =+K99+L99+M99 -> 268.665 | K99: 221.1497 | L99: 34.854297 | M99: 12.661 | N99: =+O99+P99+Q99+R99 -> 876.97 | O99: 589.65867 | P99: 128.56874 | Q99: 132.58659 | R99: =T99+S99 -> 26.156 | S99: 5.507 | T99: 20.649 | U99: 381 | V99: 40233 | W99: 245053 | X99: =Y99+Z99 -> 13465 | Y99: 11486 | Z99: 1979
A100: 41548 | B100: 2903 | C100: =SUM(D100:F100) -> 161044 | D100: 61881 | E100: 84835 | F100: 14328 | G100: =H100+I100 -> 1952.183 | H100: 852.055 | I100: 1100.128 | J100: =+K100+L100+M100 -> 303.041 | K100: 176.134 | L100: 118.93 | M100: 7.977 | N100: =+O100+P100+Q100+R100 -> 797.443 | O100: 665.62856 | P100: 91.044104 | Q100: 32.835337 | R100: =T100+S100 -> 7.935 | S100: 2.206 | T100: 5.729 | U100: 359 | V100: 26022 | W100: 202028 | X100: =Y100+Z100 -> 17113 | Y100: 15492 | Z100: 1621
A101: 41579 | B101: 3007 | C101: =SUM(D101:F101) -> 162740 | D101: 69830 | E101: 73703 | F101: 19207 | G101: =H101+I101 -> 3064.578 | H101: 2057.104 | I101: 1007.474 | J101: =+K101+L101+M101 -> 335.239 | K101: 283.235 | L101: 43.5 | M101: 8.504 | N101: =+O101+P101+Q101+R101 -> 918.898 | O101: 763.70961 | P101: 0.074091 | Q101: 146.1943 | R101: =T101+S101 -> 8.92 | S101: 4.444 | T101: 4.476 | U101: 353 | V101: 23516 | W101: 206067 | X101: =Y101+Z101 -> 23678 | Y101: 20510 | Z101: 3168
A102: 41609 | B102: 3260 | C102: =SUM(D102:F102) -> 186970 | D102: 69097 | E102: 97433 | F102: 20440 | G102: =H102+I102 -> 2714.847 | H102: 1705.153 | I102: 1009.694 | J102: =+K102+L102+M102 -> 208.878 | K102: 180.139 | L102: 20.875 | M102: 7.864 | N102: =+O102+P102+Q102+R102 -> 1108.376 | O102: 890.37567 | P102: 128.67424 | Q102: 80.589094 | R102: =T102+S102 -> 8.737 | S102: 5.19 | T102: 3.547 | U102: 367 | V102: 25722 | W102: 193834 | X102: =Y102+Z102 -> 25949 | Y102: 20605 | Z102: 5344
A103: 41640 | B103: 3198 | C103: =SUM(D103:F103) -> 183707 | D103: 79774 | E103: 80177 | F103: 23756 | G103: =H103+I103 -> 2506.994 | H103: 1516.586 | I103: 990.408 | J103: =+K103+L103+M103 -> 366.742 | K103: 307.081 | L103: 47.97 | M103: 11.691 | N103: =+O103+P103+Q103+R103 -> 794.928 | O103: 724.51784 | P103: 0.100537 | Q103: 60.286625 | R103: =T103+S103 -> 10.023 | S103: 5.456 | T103: 4.567 | U103: 258 | V103: 26056 | W103: 216560 | X103: =Y103+Z103 -> 26353 | Y103: 19273 | Z103: 7080
A104: 41671 | B104: 2954 | C104: =SUM(D104:F104) -> 157216 | D104: 67584 | E104: 70737 | F104: 18895 | G104: =H104+I104 -> 2318.033 | H104: 1364.143 | I104: 953.89 | J104: =+K104+L104+M104 -> 298.424 | K104: 214.257 | L104: 74.53 | M104: 9.637 | N104: =+O104+P104+Q104+R104 -> 818.875 | O104: 615.88261 | P104: 132.46429 | Q104: 61.706099 | R104: =T104+S104 -> 8.822 | S104: 4.983 | T104: 3.839 | U104: 329 | V104: 23087 | W104: 229543 | X104: =Y104+Z104 -> 25818 | Y104: 19498 | Z104: 6320
A105: 41699 | B105: 2860 | C105: =SUM(D105:F105) -> 183499 | D105: 91157 | E105: 73720 | F105: 18622 | G105: =H105+I105 -> 3072.125 | H105: 1916.816 | I105: 1155.309 | J105: =+K105+L105+M105 -> 289.878 | K105: 258.166 | L105: 21.5 | M105: 10.212 | N105: =+O105+P105+Q105+R105 -> 675.423 | O105: 622.49912 | P105: 0.12867 | Q105: 40.912213 | R105: =T105+S105 -> 11.883 | S105: 6.197 | T105: 5.686 | U105: 401 | V105: 35574 | W105: 252211 | X105: =Y105+Z105 -> 29374 | Y105: 18554 | Z105: 10820
A106: 41730 | B106: 3163 | C106: =SUM(D106:F106) -> 162298 | D106: 78558 | E106: 69640 | F106: 14100 | G106: =H106+I106 -> 2781.454 | H106: 1550.999 | I106: 1230.455 | J106: =+K106+L106+M106 -> 369.194 | K106: 337.416 | L106: 15.45 | M106: 16.328 | N106: =+O106+P106+Q106+R106 -> 1120.819 | O106: 872.57976 | P106: 128.60765 | Q106: 102.17759 | R106: =T106+S106 -> 17.454 | S106: 7.674 | T106: 9.78 | U106: 456 | V106: 34395 | W106: 244482 | X106: =Y106+Z106 -> 22197 | Y106: 14663 | Z106: 7534
A107: 41760 | B107: 3025 | C107: =SUM(D107:F107) -> 151026 | D107: 74747 | E107: 63816 | F107: 12463 | G107: =H107+I107 -> 2396.441 | H107: 1243.469 | I107: 1152.972 | J107: =+K107+L107+M107 -> 405.644 | K107: 355.357 | L107: 25.96 | M107: 24.327 | N107: =+O107+P107+Q107+R107 -> 885.526 | O107: 756.37997 | P107: 0 | Q107: 111.85503 | R107: =T107+S107 -> 17.291 | S107: 7.381 | T107: 9.91 | U107: 460 | V107: 42821 | W107: 248379 | X107: =Y107+Z107 -> 19995 | Y107: 12729 | Z107: 7266
A108: 41791 | B108: 2904 | C108: =SUM(D108:F108) -> 151102 | D108: 68560 | E108: 68359 | F108: 14183 | G108: =H108+I108 -> 2599.915 | H108: 1346.622 | I108: 1253.293 | J108: =+K108+L108+M108 -> 265.202 | K108: 219.675 | L108: 21.2 | M108: 24.327 | N108: =+O108+P108+Q108+R108 -> 922.479 | O108: 810.50483 | P108: 0.259365 | Q108: 96.366804 | R108: =T108+S108 -> 15.348 | S108: 7.056 | T108: 8.292 | U108: 445 | V108: 54921 | W108: 229984 | X108: =Y108+Z108 -> 17867 | Y108: 13610 | Z108: 4257
A109: 41821 | B109: 3511 | C109: =SUM(D109:F109) -> 150966 | D109: 63295 | E109: 71849 | F109: 15822 | G109: =H109+I109 -> 2802.863 | H109: 1605.918 | I109: 1196.945 | J109: =+K109+L109+M109 -> 271.419 | K109: 207.51 | L109: 46.8 | M109: 17.109 | N109: =+O109+P109+Q109+R109 -> 892.457 | O109: 748.11703 | P109: 0 | Q109: 118.67197 | R109: =T109+S109 -> 25.668 | S109: 6.942 | T109: 18.726 | U109: 268.38501 | V109: 23574 | W109: 225230 | X109: =Y109+Z109 -> 13899 | Y109: 12434 | Z109: 1465
... A117: 42064 | B117: 3195 | C117: =SUM(D117:F117) -> 167766 | D117: 83441 | E117: 67223 | F117: 17102 | G117: =H117+I117 -> 3772.885 | H117: 2646.042 | I117: 1126.843 | J117: =+K117+L117+M117 -> 364.301 | K117: 330.591 | L117: 16.99 | M117: 16.72 | N117: =+O117+P117+Q117+R117 -> 781.137 | O117: 704.8495 | P117: 0 | Q117: 63.4605 | R117: =T117+S117 -> 12.827 | S117: 6.701 | T117: 6.126 | U117: 353 | V117: 32102 | W117: 251045 | X117: =Y117+Z117 -> 18258 | Y117: 9096 | Z117: 9162
A118: 42095 | B118: 2916 | C118: =SUM(D118:F118) -> 157476 | D118: 77561 | E118: 64338 | F118: 15577 | G118: =H118+I118 -> 3116.728 | H118: 1970.468 | I118: 1146.26 | J118: =+K118+L118+M118 -> 420.974 | K118: 365.064 | L118: 35.6 | M118: 20.31 | N118: =+O118+P118+Q118+R118 -> 954.742 | O118: 779.04463 | P118: 127.24819 | Q118: 28.685178 | R118: 19.764 | S118: 9.598 | T118: 10.166 | U118: 375 | V118: 32541 | W118: 213449 | X118: =Y118+Z118 -> 21290 | Y118: 11642 | Z118: 9648
...

Sheet ICAS et ICAC
A1: DIRECTION DE LA PREVISION ET DES ETUDES ECONOMIQUES
B3: INDICE CHIFFRE D'AFFAIRES DU SECTEUR TERTIAIRE (base 100 = 2022)*
C4: SERVICES | AO4: COMMERCE
C5: ICAS=Indice Chiffre d'Affaire des Services | D5: Transport | K5: HEBERGEMENT ET RESTAURATION | N5: Information et Communication | U5: Activités financières et d'Assurance | Y5: Activités Immobilières | Z5: Activités Spécialisées, scientifiques et techniques | AD5: ACTIVITES DE SERVICES ET DE SOUTIEN ET DE BUREAU | AI5: ACTIVITES D'ADMINISTRATION PUBLIQUE | AJ5: ENSEIGNEMENT | AK5: ACTIVITÉS POUR LA SANTÉ HUMAINE ET L'ACTION SOCIALE | AM5: ACTIVITÉS ARTISTIQUES, CULTURELLES, SPORTIVES ET RECREATIVES | AN5: AUTRES ACTIVITES N.C.A | AP5: Commerce et réparation d'automobiles et de motocycles | AQ5: Commerce de gros | AR5: Commerce de détail
E6: Transports ferroviaires | F6: Transports routiers | G6: Transports par eau | H6: Transport aérien | I6: Entreposage et activités des auxilliaires de transport | J6: Activités de poste et de courrier | L6: Hôtel et Hebergement | M6: Restauration et debits de boisson | O6: Edition | P6: Production audio et video: télévision, cinéma et son | Q6: Programmation télévisuelle ; radiodiffusion | R6: Télécommunications | S6: Activités informatiques : conseil, programmation | T6: Activités de fournitures d'information | V6: Activités financières | W6: Assurances | X6: Activités des auxiliaires financiers et d'assurance | AA6: Recherche-developpement | AB6: Activités vétérinaires | AC6: Autres activités spécialisées scientifiques et techniques | AE6: Location et location-bail | AF6: Activités des agences de reservation et voyagistes | AG6: Activités d'Enquêtes et de sécurite | AH6: Autres activités de soutien aux entreprises; activités de bureau | AL6: Activités pour la santé humaine | AO6: ICAC= Indice Chiffre d'Affaires du Commerce
A7: 39083 | C7: 56.996544 | D7: 58.556865 | E7: 15.284175 | F7: 48.29729 | G7: 0 | H7: 46.252823 | I7: 58.121028 | J7: 0 | K7: 60.013696 | L7: 0 | M7: 0 | N7: 0 | O7: 0 | P7: 0 | Q7: 0 | R7: 80.880028 | S7: 0 | T7: 0 | U7: 23.553649 | V7: 0 | W7: 0 | X7: 0 | Y7: 117.02682 | Z7: 0 | AA7: 0 | AB7: 0 | AC7: 0 | AD7: 0 | AE7: 0 | AF7: 0 | AG7: 0 | AH7: 0 | AI7: 0 | AJ7: 0 | AK7: 74.511281 | AL7: 74.511281 | AM7: 0 | AN7: 0 | AO7: 41.75884 | AP7: 54.079655 | AQ7: 33.228274 | AR7: 31.630909
A8: 39114 | C8: 59.116801 | D8: 69.240625 | E8: 18.998748 | F8: 48.659626 | G8: 0 | H8: 81.297369 | I8: 69.074733 | J8: 0 | K8: 65.746931 | L8: 0 | M8: 0 | N8: 0 | O8: 0 | P8: 0 | Q8: 0 | R8: 73.046866 | S8: 0 | T8: 0 | U8: 32.022161 | V8: 0 | W8: 0 | X8: 0 | Y8: 131.88267 | Z8: 0 | AA8: 0 | AB8: 0 | AC8: 0 | AD8: 0 | AE8: 0 | AF8: 0 | AG8: 0 | AH8: 0 | AI8: 0 | AJ8: 0 | AK8: 76.153261 | AL8: 76.153261 | AM8: 0 | AN8: 0 | AO8: 32.730908 | AP8: 47.359402 | AQ8: 34.284144 | AR8: 37.195551
A9: 39142 | C9: 62.649823 | D9: 62.463499 | E9: 20.115332 | F9: 41.221468 | G9: 0 | H9: 84.504266 | I9: 61.866098 | J9: 0 | K9: 65.127647 | L9: 0 | M9: 0 | N9: 0 | O9: 0 | P9: 0 | Q9: 0 | R9: 88.361109 | S9: 0 | T9: 0 | U9: 29.896955 | V9: 0 | W9: 0 | X9: 0 | Y9: 137.04942 | Z9: 0 | AA9: 0 | AB9: 0 | AC9: 0 | AD9: 0 | AE9: 0 | AF9: 0 | AG9: 0 | AH9: 0 | AI9: 0 | AJ9: 0 | AK9: 54.632829 | AL9: 54.632829 | AM9: 0 | AN9: 0 | AO9: 35.56015 | AP9: 58.77256 | AQ9: 29.912456 | AR9: 41.127072
A10: 39173 | C10: 60.186367 | D10: 62.754664 | E10: 17.136704 | F10: 59.083927 | G10: 0 | H10: 35.901462 | I10: 61.42593 | J10: 0 | K10: 72.136262 | L10: 0 | M10: 0 | N10: 0 | O10: 0 | P10: 0 | Q10: 0 | R10: 80.68311 | S10: 0 | T10: 0 | U10: 26.986768 | V10: 0 | W10: 0 | X10: 0 | Y10: 157.92468 | Z10: 0 | AA10: 0 | AB10: 0 | AC10: 0 | AD10: 0 | AE10: 0 | AF10: 0 | AG10: 0 | AH10: 0 | AI10: 0 | AJ10: 0 | AK10: 52.325655 | AL10: 52.325655 | AM10: 0 | AN10: 0 | AO10: 39.155626 | AP10: 56.699783 | AQ10: 27.459645 | AR10: 36.353736
A11: 39203 | C11: 62.528219 | D11: 60.332824 | E11: 16.209289 | F11: 50.823322 | G11: 0 | H11: 56.100686 | I11: 59.383621 | J11: 0 | K11: 53.487777 | L11: 0 | M11: 0 | N11: 0 | O11: 0 | P11: 0 | Q11: 0 | R11: 85.533768 | S11: 0 | T11: 0 | U11: 38.584697 | V11: 0 | W11: 0 | X11: 0 | Y11: 141.45513 | Z11: 0 | AA11: 0 | AB11: 0 | AC11: 0 | AD11: 0 | AE11: 0 | AF11: 0 | AG11: 0 | AH11: 0 | AI11: 0 | AJ11: 0 | AK11: 52.154719 | AL11: 52.154719 | AM11: 0 | AN11: 0 | AO11: 36.513749 | AP11: 59.661646 | AQ11: 32.000741 | AR11: 38.151846
A12: 39234 | C12: 66.441967 | D12: 62.336401 | E12: 14.603197 | F12: 42.597593 | G12: 0 | H12: 64.260067 | I12: 63.086875 | J12: 0 | K12: 61.031761 | L12: 0 | M12: 0 | N12: 0 | O12: 0 | P12: 0 | Q12: 0 | R12: 93.845653 | S12: 0 | T12: 0 | U12: 30.639487 | V12: 0 | W12: 0 | X12: 0 | Y12: 222.92029 | Z12: 0 | AA12: 0 | AB12: 0 | AC12: 0 | AD12: 0 | AE12: 0 | AF12: 0 | AG12: 0 | AH12: 0 | AI12: 0 | AJ12: 0 | AK12: 73.361447 | AL12: 73.361447 | AM12: 0 | AN12: 0 | AO12: 35.032558 | AP12: 61.01762 | AQ12: 28.889755 | AR12: 37.613915
A13: 39264 | C13: 59.137788 | D13: 55.499962 | E13: 14.792007 | F13: 46.859505 | G13: 0 | H13: 72.889601 | I13: 53.99257 | J13: 0 | K13: 46.722765 | L13: 0 | M13: 0 | N13: 0 | O13: 0 | P13: 0 | Q13: 0 | R13: 85.676279 | S13: 0 | T13: 0 | U13: 27.252743 | V13: 0 | W13: 0 | X13: 0 | Y13: 166.06176 | Z13: 0 | AA13: 0 | AB13: 0 | AC13: 0 | AD13: 0 | AE13: 0 | AF13: 0 | AG13: 0 | AH13: 0 | AI13: 0 | AJ13: 0 | AK13: 36.656948 | AL13: 36.656948 | AM13: 0 | AN13: 0 | AO13: 31.98164 | AP13: 58.278952 | AQ13: 32.897245 | AR13: 31.316308
A14: 39295 | C14: 57.315865 | D14: 62.352181 | E14: 16.005325 | F14: 22.885405 | G14: 0 | H14: 48.240616 | I14: 66.398772 | J14: 0 | K14: 37.055182 | L14: 0 | M14: 0 | N14: 0 | O14: 0 | P14: 0 | Q14: 0 | R14: 72.550206 | S14: 0 | T14: 0 | U14: 38.860141 | V14: 0 | W14: 0 | X14: 0 | Y14: 178.04155 | Z14: 0 | AA14: 0 | AB14: 0 | AC14: 0 | AD14: 0 | AE14: 0 | AF14: 0 | AG14: 0 | AH14: 0 | AI14: 0 | AJ14: 0 | AK14: 103.44704 | AL14: 103.44704 | AM14: 0 | AN14: 0 | AO14: 40.761505 | AP14: 58.509053 | AQ14: 35.207619 | AR14: 32.318336
A15: 39326 | C15: 64.953012 | D15: 62.076169 | E15: 15.555277 | F15: 26.63004 | G15: 0 | H15: 62.084004 | I15: 65.153062 | J15: 0 | K15: 46.29625 | L15: 0 | M15: 0 | N15: 0 | O15: 0 | P15: 0 | Q15: 0 | R15: 100.57914 | S15: 0 | T15: 0 | U15: 27.24291 | V15: 0 | W15: 0 | X15: 0 | Y15: 169.74873 | Z15: 0 | AA15: 0 | AB15: 0 | AC15: 0 | AD15: 0 | AE15: 0 | AF15: 0 | AG15: 0 | AH15: 0 | AI15: 0 | AJ15: 0 | AK15: 76.578446 | AL15: 76.578446 | AM15: 0 | AN15: 0 | AO15: 33.111383 | AP15: 57.683509 | AQ15: 29.852516 | AR15: 33.401636
A16: 39356 | C16: 70.219775 | D16: 69.775704 | E16: 18.98549 | F16: 61.389762 | G16: 0 | H16: 48.79335 | I16: 68.712617 | J16: 0 | K16: 63.336414 | L16: 0 | M16: 0 | N16: 0 | O16: 0 | P16: 0 | Q16: 0 | R16: 105.54065 | S16: 0 | T16: 0 | U16: 31.695718 | V16: 0 | W16: 0 | X16: 0 | Y16: 177.35699 | Z16: 0 | AA16: 0 | AB16: 0 | AC16: 0 | AD16: 0 | AE16: 0 | AF16: 0 | AG16: 0 | AH16: 0 | AI16: 0 | AJ16: 0 | AK16: 67.946626 | AL16: 67.946626 | AM16: 0 | AN16: 0 | AO16: 39.126348 | AP16: 65.281751 | AQ16: 27.819072 | AR16: 32.372782
A17: 39387 | C17: 70.822442 | D17: 78.124174 | E17: 22.166193 | F17: 62.357621 | G17: 0 | H17: 94.439412 | I17: 76.568338 | J17: 0 | K17: 61.956165 | L17: 0 | M17: 0 | N17: 0 | O17: 0 | P17: 0 | Q17: 0 | R17: 91.120168 | S17: 0 | T17: 0 | U17: 48.583981 | V17: 0 | W17: 0 | X17: 0 | Y17: 98.833351 | Z17: 0 | AA17: 0 | AB17: 0 | AC17: 0 | AD17: 0 | AE17: 0 | AF17: 0 | AG17: 0 | AH17: 0 | AI17: 0 | AJ17: 0 | AK17: 74.832805 | AL17: 74.832805 | AM17: 0 | AN17: 0 | AO17: 39.373732 | AP17: 69.848777 | AQ17: 31.905652 | AR17: 32.662345
A18: 39417 | C18: 67.365224 | D18: 84.358303 | E18: 30.554548 | F18: 47.120422 | G18: 0 | H18: 40.641747 | I18: 86.483004 | J18: 0 | K18: 67.247685 | L18: 0 | M18: 0 | N18: 0 | O18: 0 | P18: 0 | Q18: 0 | R18: 80.960252 | S18: 0 | T18: 0 | U18: 40.934277 | V18: 0 | W18: 0 | X18: 0 | Y18: 155.14809 | Z18: 0 | AA18: 0 | AB18: 0 | AC18: 0 | AD18: 0 | AE18: 0 | AF18: 0 | AG18: 0 | AH18: 0 | AI18: 0 | AJ18: 0 | AK18: 103.74373 | AL18: 103.74373 | AM18: 0 | AN18: 0 | AO18: 39.704027 | AP18: 69.063044 | AQ18: 36.100066 | AR18: 36.273838
... A114: 42339 | C114: 89.173256 | D114: 87.137978 | E114: 40.653819 | F114: 69.578052 | G114: 0 | H114: 53.781846 | I114: 84.726152 | J114: 0 | K114: 88.417906 | L114: 0 | M114: 0 | N114: 0 | O114: 0 | P114: 0 | Q114: 0 | R114: 125.65659 | S114: 0 | T114: 0 | U114: 53.275702 | V114: 0 | W114: 0 | X114: 0 | Y114: 90.774687 | Z114: 0 | AA114: 0 | AB114: 0 | AC114: 0 | AD114: 0 | AE114: 0 | AF114: 0 | AG114: 0 | AH114: 0 | AI114: 0 | AJ114: 0 | AK114: 94.251709 | AL114: 94.251709 | AM114: 0 | AN114: 0 | AO114: 62.55719 | AP114: 90.177958 | AQ114: 58.802966 | AR114: 53.193613
A115: 42370 | B115: =(C115*41.5+AO115*58.5)/100 -> 61.437903 | C115: 82.427167 | D115: 76.290497 | E115: 12.133412 | F115: 53.512746 | H115: 53.410617 | I115: 82.345636 | K115: 76.498395 | R115: 113.39593 | U115: 53.436566 | Y115: 143.04993 | AK115: 188.28401 | AL115: 188.28401 | AO115: 46.548084 | AP115: 70.057043 | AQ115: 38.542859 | AR115: 33.001526
A116: 42401 | B116: =(C116*41.5+AO116*58.5)/100 -> 63.938425 | C116: 88.269933 | D116: 72.945397 | E116: 9.6051543 | F116: 37.860488 | H116: 68.411991 | I116: 79.792246 | K116: 77.978749 | R116: 116.12443 | U116: 73.930795 | Y116: 103.31949 | AK116: 108.06812 | AL116: 108.06812 | AO116: 46.677612 | AP116: 60.304796 | AQ116: 40.733529 | AR116: 36.819605
A117: 42430 | B117: =(C117*41.5+AO117*58.5)/100 -> 66.170681 | C117: 85.365894 | D117: 83.094223 | E117: 11.001277 | F117: 55.930619 | H117: 70.414584 | I117: 88.761115 | K117: 62.437937 | R117: 118.27186 | U117: 56.552431 | Y117: 69.822644 | AK117: 100.98574 | AL117: 100.98574 | AO117: 52.553564 | AP117: 82.738116 | AQ117: 46.450242 | AR117: 41.636849
A118: 42461 | B118: =(C118*41.5+AO118*58.5)/100 -> 68.424255 | C118: 94.825274 | D118: 83.152625 | E118: 11.18367 | F118: 54.563453 | H118: 77.123385 | I118: 88.022806 | K118: 70.692272 | R118: 129.35306 | U118: 70.312822 | Y118: 67.725507 | AK118: 110.88157 | AL118: 110.88157 | AO118: 49.695327 | AP118: 84.140352 | AQ118: 39.848269 | AR118: 49.133861
A119: 42491 | B119: =(C119*41.5+AO119*58.5)/100 -> 67.19382 | C119: 89.621283 | D119: 84.864351 | E119: 12.932689 | F119: 54.227216 | H119: 79.417617 | I119: 89.739496 | K119: 54.466183 | R119: 114.28599 | U119: 76.47083 | Y119: 87.307164 | AK119: 94.120573 | AL119: 94.120573 | AO119: 51.283739 | AP119: 84.977735 | AQ119: 44.910664 | AR119: 48.051871
A120: 42522 | B120: =(C120*41.5+AO120*58.5)/100 -> 67.001432 | C120: 89.2359 | D120: 78.649644 | E120: 13.106764 | F120: 57.17625 | H120: 72.937597 | I120: 81.177654 | K120: 55.090938 | R120: 116.93945 | U120: 77.744939 | Y120: 66.908416 | AK120: 109.92538 | AL120: 109.92538 | AO120: 51.228262 | AP120: 77.54978 | AQ120: 42.706208 | AR120: 45.957588
A121: 42552 | B121: =(C121*41.5+AO121*58.5)/100 -> 67.130113 | C121: 94.623197 | D121: 111.8121 | E121: 14.746639 | F121: 44.97979 | H121: 70.477163 | I121: 131.60968 | K121: 64.58455 | R121: 123.1171 | U121: 62.418107 | Y121: 63.300368 | AK121: 97.7255 | AL121: 97.7255 | AO121: 47.626473 | AP121: 63.168683 | AQ121: 39.185877 | AR121: 42.468557
A122: 42583 | B122: =(C122*41.5+AO122*58.5)/100 -> 65.682649 | C122: 90.753064 | D122: 78.536434 | E122: 13.115085 | F122: 40.022986 | H122: 65.607967 | I122: 86.810687 | K122: 56.684678 | R122: 119.27732 | U122: 76.959882 | Y122: 108.64576 | AK122: 112.31652 | AL122: 112.31652 | AO122: 47.897653 | AP122: 72.135511 | AQ122: 42.043922 | AR122: 26.608374
A123: 42614 | B123: =(C123*41.5+AO123*58.5)/100 -> 64.650988 | C123: 91.592298 | D123: 81.804446 | E123: 14.060609 | F123: 48.665116 | H123: 57.002901 | I123: 90.40404 | K123: 63.431267 | R123: 122.58012 | U123: 76.625981 | Y123: 87.853211 | AK123: 91.070935 | AL123: 91.070935 | AO123: 45.538777 | AP123: 71.207563 | AQ123: 39.108986 | AR123: 41.331497
A124: 42644 | B124: =(C124*41.5+AO124*58.5)/100 -> 64.280739 | C124: 88.510846 | D124: 79.840113 | E124: 14.658424 | F124: 62.332339 | H124: 54.610475 | I124: 84.248831 | K124: 89.206744 | R124: 108.61815 | U124: 78.789093 | Y124: 118.98948 | AK124: 86.601319 | AL124: 86.601319 | AO124: 47.09186 | AP124: 72.211583 | AQ124: 40.440723 | AR124: 47.574924
A125: 42675 | B125: =(C125*41.5+AO125*58.5)/100 -> 77.539312 | C125: 110.68189 | D125: 92.096303 | E125: 24.418754 | F125: 72.608362 | H125: 48.131763 | I125: 97.729298 | K125: 96.974827 | R125: 123.02894 | U125: 121.15104 | Y125: 118.80839 | AK125: 142.65913 | AL125: 142.65913 | AO125: 54.02791 | AP125: 109.3009 | AQ125: 47.389473 | AR125: 46.507965
A126: 42705 | B126: =(C126*41.5+AO126*58.5)/100 -> 80.342538 | C126: 110.68189 | D126: 92.096303 | E126: 24.418754 | F126: 72.608362 | H126: 118.01256 | I126: 97.729298 | J126: 63.780217 | K126: 96.974827 | L126: 97.91643 | M126: 112.96184 | N126: 123.04538 | Q126: 150.1849 | R126: 123.02894 | S126: 302.39562 | U126: 121.15104 | V126: 123.21293 | W126: 55.791185 | X126: 209.93406 | Y126: 118.80839 | Z126: 105.61423 | AB126: 50.043024 | AC126: 111.12462 | AD126: 100.76411 | AE126: 64.395882 | AG126: 108.13413 | AH126: 96.139117 | AJ126: 91.903807 | AK126: 142.65913 | AL126: 142.65913 | AM126: 34.670083 | AO126: 58.819748 | AP126: 109.54009 | AQ126: 54.366074 | AR126: 57.400579
A127: 42736 | B127: =(C127*41.5+AO127*58.5)/100 -> 69.85196 | C127: 89.646317 | D127: 73.215633 | E127: 13.709985 | F127: 51.979243 | H127: 63.059098 | I127: 80.475477 | J127: 103.10693 | K127: 85.038011 | L127: 85.604519 | M127: 108.48203 | N127: 112.38545 | Q127: 150.1849 | R127: 114.78326 | S127: 63.070159 | U127: 81.044011 | V127: 82.215215 | W127: 96.839627 | X127: 193.40311 | Y127: 96.017498 | Z127: 64.194981 | AB127: 57.988655 | AC127: 64.548419 | AD127: 82.736458 | AE127: 68.496503 | AG127: 57.004074 | AH127: 88.972818 | AJ127: 103.65652 | AK127: 142.66186 | AL127: 142.66186 | AM127: 39.096191 | AO127: 55.809808 | AP127: 65.028934 | AQ127: 46.846047 | AR127: 60.086926
A128: 42767 | B128: =(C128*41.5+AO128*58.5)/100 -> 67.44647 | C128: 85.229786 | D128: 71.962937 | E128: 13.600982 | F128: 67.809047 | H128: 93.326828 | I128: 73.321687 | J128: 107.11148 | K128: 85.08978 | L128: 85.774807 | M128: 104.25093 | N128: 106.83772 | Q128: 150.1849 | R128: 108.96556 | S128: 71.617758 | U128: 75.301057 | V128: 76.274775 | W128: 122.72431 | X128: 156.34047 | Y128: 44.767666 | Z128: 57.755398 | AB128: 49.723485 | AC128: 58.3394 | AD128: 77.406503 | AE128: 68.653174 | AG128: 57.524666 | AH128: 81.917464 | AJ128: 108.17374 | AK128: 145.84443 | AL128: 145.84443 | AM128: 38.370169 | AO128: 54.830954 | AP128: 83.7967 | AQ128: 46.332998 | AR128: 57.230374
A129: 42795 | B129: =(C129*41.5+AO129*58.5)/100 -> 72.316583 | C129: 90.618834 | D129: 78.78641 | E129: 13.789936 | F129: 61.627196 | H129: 78.020258 | I129: 85.468339 | J129: 97.315569 | K129: 101.28592 | L129: 102.1848 | M129: 121.05945 | N129: 110.29214 | Q129: 150.1849 | R129: 112.55212 | S129: 69.431175 | U129: 82.061574 | V129: 83.230119 | W129: 103.02213 | X129: 145.85767 | Y129: 41.701912 | Z129: 56.850315 | AB129: 48.645446 | AC129: 57.457637 | AD129: 81.758025 | AE129: 68.595131 | AG129: 71.209734 | AH129: 83.223208 | AJ129: 114.2544 | AK129: 144.25314 | AL129: 144.25314 | AM129: 43.467794 | AO129: 59.332935 | AP129: 77.419461 | AQ129: 48.989634 | AR129: 63.608463
A130: 42826 | B130: =(C130*41.5+AO130*58.5)/100 -> 70.579726 | C130: 90.146117 | D130: 77.110231 | E130: 13.539732 | F130: 70.429789 | H130: 70.548329 | I130: 82.953713 | J130: 96.086955 | K130: 86.179876 | L130: 86.678192 | M130: 112.69494 | N130: 117.90247 | Q130: 81.995496 | R130: 120.68669 | S130: 58.617215 | U130: 73.153169 | V130: 74.202833 | W130: 89.557717 | X130: 147.34463 | Y130: 75.660733 | Z130: 44.736693 | AB130: 48.896999 | AC130: 44.060966 | AD130: 83.116958 | AE130: 74.667111 | AG130: 68.973647 | AH130: 85.686063 | AJ130: 70.575403 | AK130: 145.04879 | AL130: 145.04879 | AM130: 43.89478 | AO130: 56.699295 | AP130: 102.65498 | AQ130: 39.79951 | AR130: 61.978941
A131: 42856 | B131: =(C131*41.5+AO131*58.5)/100 -> 70.667095 | C131: 88.671367 | D131: 75.160186 | E131: 13.733529 | F131: 68.963771 | H131: 95.022587 | I131: 78.220746 | J131: 85.497068 | K131: 79.933201 | L131: 80.411299 | M131: 103.94809 | N131: 108.43346 | Q131: 74.349548 | R131: 111.03233 | S131: 50.796234 | U131: 84.293602 | V131: 85.547795 | W131: 90.418192 | X131: 141.25609 | Y131: 61.344277 | Z131: 50.208628 | AB131: 45.238223 | AC131: 50.497695 | AD131: 81.46673 | AE131: 79.325439 | AG131: 61.254861 | AH131: 85.98927 | AJ131: 63.929428 | AK131: 144.65096 | AL131: 144.65096 | AM131: 43.698199 | AO131: 57.894833 | AP131: 82.175105 | AQ131: 43.339382 | AR131: 63.78581
A132: 42887 | B132: =(C132*41.5+AO132*58.5)/100 -> 72.993118 | C132: 92.117849 | D132: 76.992019 | E132: 16.124888 | F132: 74.163261 | H132: 83.934547 | I132: 80.66485 | J132: 91.635088 | K132: 60.278089 | L132: 59.724078 | M132: 111.64331 | N132: 115.22161 | Q132: 76.876901 | R132: 117.92543 | S132: 59.458563 | U132: 89.741613 | V132: 91.098635 | W132: 90.035668 | X132: 147.89939 | Y132: 64.199202 | Z132: 62.6837 | AB132: 76.73177 | AC132: 60.843831 | AD132: 74.784264 | AE132: 76.385296 | AG132: 72.023611 | AH132: 73.950019 | AJ132: 99.229226 | AK132: 144.84987 | AL132: 144.84987 | AM132: 37.435736 | AO132: 59.426002 | AP132: 85.084094 | AQ132: 44.206609 | AR132: 65.553701
A133: 42917 | B133: =(C133*41.5+AO133*58.5)/100 -> 73.135529 | C133: 91.878546 | D133: 75.384383 | E133: 18.395663 | F133: 69.945447 | H133: 66.576383 | I133: 79.907608 | J133: 107.45013 | K133: 82.390693 | L133: 82.174461 | M133: 132.92614 | N133: 114.60798 | Q133: 113.92437 | R133: 117.15662 | S133: 63.545162 | U133: 86.896661 | V133: 88.167028 | W133: 99.661726 | X133: 150.75484 | Y133: 66.600927 | Z133: 60.900482 | AB133: 69.811199 | AC133: 59.627759 | AD133: 80.220939 | AE133: 77.108531 | AG133: 71.788766 | AH133: 81.05314 | AJ133: 73.639568 | AK133: 144.75042 | AL133: 144.75042 | AM133: 34.908688 | AO133: 59.839201 | AP133: 82.388881 | AQ133: 47.429483 | AR133: 64.800002
A134: 42948 | B134: =(C134*41.5+AO134*58.5)/100 -> 73.692462 | C134: 97.625146 | D134: 84.165247 | E134: 18.395663 | F134: 68.210966 | H134: 61.924932 | I134: 93.285858 | J134: 91.553513 | K134: 73.530215 | L134: 73.526636 | M134: 111.74394 | N134: 115.77292 | Q134: 100.58295 | R134: 118.39442 | S134: 63.143396 | U134: 100.36334 | V134: 101.86605 | W134: 104.96413 | X134: 162.73466 | Y134: 66.933152 | Z134: 64.200388 | AB134: 66.099625 | AC134: 63.673041 | AD134: 82.381129 | AE134: 77.329141 | AG134: 60.806094 | AH134: 87.313152 | AJ134: 74.684006 | AK134: 144.80015 | AL134: 144.80015 | AM134: 29.466402 | AO134: 56.714575 | AP134: 79.113251 | AQ134: 46.53918 | AR134: 60.52553
A135: 42979 | B135: =(C135*41.5+AO135*58.5)/100 -> 71.783061 | C135: 90.888213 | D135: 74.516397 | E135: 16.103951 | F135: 75.940547 | H135: 75.165618 | I135: 78.482052 | J135: 79.926094 | K135: 87.934755 | L135: 88.179727 | M135: 124.571 | N135: 116.67451 | Q135: 108.05407 | R135: 118.98363 | S135: 91.249281 | U135: 79.502146 | V135: 80.642075 | W135: 97.569292 | X135: 141.90127 | Y135: 70.271254 | Z135: 65.29589 | AB135: 58.307024 | AC135: 65.728855 | AD135: 79.129315 | AE135: 72.762273 | AG135: 61.158202 | AH135: 82.99778 | AJ135: 82.36319 | AK135: 144.77528 | AL135: 144.77528 | AM135: 35.958827 | AO135: 58.229834 | AP135: 79.853352 | AQ135: 47.019448 | AR135: 62.643882
A136: 43009 | B136: =(C136*41.5+AO136*58.5)/100 -> 73.288478 | C136: 87.866075 | D136: 71.632524 | E136: 16.135192 | F136: 67.748928 | H136: 72.123681 | I136: 75.631917 | J136: 86.653678 | K136: 98.02541 | L136: 99.253691 | M136: 104.13213 | N136: 106.04863 | Q136: 173.30867 | R136: 108.11861 | S136: 69.670183 | U136: 81.181035 | V136: 82.410905 | W136: 80.790172 | X136: 140.99223 | Y136: 86.33839 | Z136: 56.138666 | AB136: 68.184755 | AC136: 54.549058 | AD136: 91.581678 | AE136: 73.786124 | AG136: 69.160223 | AH136: 96.571053 | AJ136: 103.12614 | AK136: 144.0791 | AL136: 144.0791 | AM136: 44.363763 | AO136: 62.947106 | AP136: 87.151549 | AQ136: 47.03725 | AR136: 69.57639
A137: 43040 | B137: =(C137*41.5+AO137*58.5)/100 -> 78.378971 | C137: 95.741008 | D137: 78.094688 | E137: 16.695367 | F137: 56.093884 | H137: 79.956548 | I137: 85.855697 | J137: 66.037183 | K137: 105.20818 | L137: 106.01483 | M137: 130.36705 | N137: 116.52422 | Q137: 175.21266 | R137: 119.15457 | S137: 48.716894 | U137: 95.925709 | V137: 97.674185 | W137: 11.023349 | X137: 139.69106 | Y137: 96.164754 | Z137: 75.843212 | AB137: 47.325741 | AC137: 78.562763 | AD137: 67.942369 | AE137: 73.030338 | AG137: 63.936617 | AH137: 67.657249 | AJ137: 103.71179 | AK137: 144.8996 | AL137: 144.8996 | AM137: 36.94955 | AO137: 66.062313 | AP137: 108.22666 | AQ137: 43.857599 | AR137: 74.432011
... A174: 44166 | B174: =(C174*41.5+AO174*58.5)/100 -> 90.095842 | C174: 112.15161 | D174: 94.177089 | E174: 14.239131 | F174: 63.485838 | H174: 81.438465 | I174: 106.51588 | J174: 80.731104 | K174: 81.491956 | L174: 82.137157 | M174: 100.23786 | N174: 127.76943 | Q174: 153.18239 | R174: 129.97014 | S174: 121.20151 | U174: 117.75528 | V174: 119.71106 | W174: 68.045223 | X174: 102.24989 | Y174: 99.723952 | Z174: 134.94841 | AB174: 107.59075 | AC174: 137.24643 | AD174: 98.622397 | AE174: 84.319603 | AG174: 105.08736 | AH174: 94.331975 | AJ174: 101.39393 | AK174: 149.18056 | AL174: 149.18056 | AM174: 18.832106 | AO174: 74.449444 | AP174: 98.250223 | AQ174: 55.054576 | AR174: 82.982684
A175: 44197 | B175: =(C175*41.5+AO175*58.5)/100 -> 69.957826 | C175: 79.446568 | D175: 76.944193 | E175: 11.626899 | F175: 57.192074 | G175: 80.14822 | H175: 78.453836 | I175: 85.849732 | J175: 85.04804 | K175: 56.290953 | L175: 56.781541 | M175: 54.477512 | N175: 88.468721 | O175: 89.172137 | P175: 65.601576 | Q175: 99.876726 | R175: 91.561832 | S175: 52.574254 | T175: 94.672159 | U175: 78.429794 | V175: 79.1963 | W175: 83.775051 | X175: 73.298767 | Y175: 109.61136 | Z175: 70.127488 | AA175: 83.049353 | AB175: 54.537932 | AC175: 70.197523 | AD175: 81.689791 | AE175: 99.212171 | AF175: 61.894618 | AG175: 75.660944 | AH175: 80.695632 | AI175: 139.10145 | AJ175: 88.711581 | AK175: 152.54124 | AL175: 152.54124 | AM175: 28.265622 | AN175: 44.426069 | AO175: 63.226497 | AP175: 68.515924 | AQ175: 51.109868 | AR175: 69.554769
A176: 44228 | B176: =(C176*41.5+AO176*58.5)/100 -> 68.525729 | C176: 78.635113 | D176: 75.761506 | E176: 6.707009 | F176: 60.470817 | G176: 80.04424 | H176: 83.334226 | I176: 83.655478 | J176: 70.137773 | K176: 56.828813 | L176: 57.579538 | M176: 54.053783 | N176: 83.71443 | O176: 95.328299 | P176: 85.639328 | Q176: 94.827877 | R176: 83.935904 | S176: 83.143738 | T176: 65.943764 | U176: 80.172742 | V176: 78.633251 | W176: 79.293026 | X176: 89.195059 | Y176: 88.305982 | Z176: 77.509601 | AA176: 87.690744 | AB176: 52.230391 | AC176: 77.711715 | AD176: 81.168729 | AE176: 96.842744 | AF176: 61.125242 | AG176: 88.383844 | AH176: 77.828981 | AI176: 163.44916 | AJ176: 103.65639 | AK176: 139.17541 | AL176: 139.17541 | AM176: 25.623154 | AN176: 41.819024 | AO176: 61.354115 | AP176: 69.976477 | AQ176: 50.11415 | AR176: 66.919413
A177: 44256 | B177: =(C177*41.5+AO177*58.5)/100 -> 83.359984 | C177: 97.682523 | D177: 82.812529 | E177: 12.831074 | F177: 65.585918 | G177: 70.387112 | H177: 79.264336 | I177: 91.985648 | J177: 89.035849 | K177: 66.902159 | L177: 66.305874 | M177: 69.106305 | N177: 93.057997 | O177: 99.788377 | P177: 91.772907 | Q177: 120.6793 | R177: 95.191599 | S177: 66.845418 | T177: 88.566128 | U177: 130.42869 | V177: 139.6936 | W177: 76.033473 | X177: 83.901606 | Y177: 97.559362 | Z177: 81.194441 | AA177: 78.919719 | AB177: 102.15515 | AC177: 80.97616 | AD177: 92.833098 | AE177: 93.754845 | AF177: 66.615905 | AG177: 86.581748 | AH177: 95.064616 | AI177: 181.81735 | AJ177: 103.36732 | AK177: 136.75564 | AL177: 136.75564 | AM177: 26.43693 | AN177: 98.443911 | AO177: 73.19955 | AP177: 91.402627 | AQ177: 61.416563 | AR177: 78.281204
A178: 44287 | B178: =(C178*41.5+AO178*58.5)/100 -> 76.69658 | C178: 84.108286 | D178: 86.59745 | E178: 7.9419641 | F178: 58.593529 | G178: 75.247122 | H178: 72.984593 | I178: 99.876579 | J178: 85.856912 | K178: 60.780177 | L178: 61.700824 | M178: 57.377041 | N178: 90.634351 | O178: 115.06612 | P178: 94.713597 | Q178: 107.28738 | R178: 92.414547 | S178: 72.32822 | T178: 69.640012 | U178: 79.549663 | V178: 80.802359 | W178: 40.898995 | X178: 77.333121 | Y178: 114.06876 | Z178: 80.10279 | AA178: 73.011838 | AB178: 102.11835 | AC178: 79.912172 | AD178: 85.393155 | AE178: 112.69218 | AF178: 62.988969 | AG178: 87.22638 | AH178: 81.210038 | AI178: 194.65217 | AJ178: 97.059597 | AK178: 167.38662 | AL178: 167.38662 | AM178: 27.310437 | AN178: 72.85909 | AO178: 71.438703 | AP178: 98.285717 | AQ178: 57.930778 | AR178: 76.773294
A179: 44317 | B179: =(C179*41.5+AO179*58.5)/100 -> 73.4044 | C179: 83.082244 | D179: 84.211611 | E179: 14.03525 | F179: 74.800557 | G179: 58.178981 | H179: 87.432218 | I179: 91.20037 | J179: 94.370758 | K179: 75.566904 | L179: 76.175354 | M179: 73.317792 | N179: 87.524213 | O179: 104.31538 | P179: 95.866666 | Q179: 124.64937 | R179: 88.760684 | S179: 71.64808 | T179: 71.668912 | U179: 80.958654 | V179: 80.43389 | W179: 109.35103 | X179: 80.298728 | Y179: 91.02578 | Z179: 79.795885 | AA179: 62.512657 | AB179: 90.966963 | AC179: 79.811655 | AD179: 85.234353 | AE179: 104.19935 | AF179: 66.380455 | AG179: 78.066737 | AH179: 84.177711 | AI179: 202.39974 | AJ179: 70.497178 | AK179: 140.24485 | AL179: 140.24485 | AM179: 26.604728 | AN179: 92.987611 | AO179: 66.538922 | AP179: 89.46599 | AQ179: 49.457371 | AR179: 74.189935
A180: 44348 | B180: =(C180*41.5+AO180*58.5)/100 -> 84.616023 | C180: 93.242364 | D180: 86.879299 | E180: 35.64404 | F180: 66.679158 | G180: 76.758149 | H180: 71.268642 | I180: 96.454621 | J180: 86.235152 | K180: 82.721654 | L180: 84.219691 | M180: 77.184219 | N180: 97.442151 | O180: 112.60556 | P180: 85.614018 | Q180: 116.72296 | R180: 97.966885 | S180: 92.938091 | T180: 79.76148 | U180: 102.22876 | V180: 102.14135 | W180: 93.133393 | X180: 103.91859 | Y180: 114.94906 | Z180: 89.193446 | AA180: 69.235888 | AB180: 88.247061 | AC180: 89.368197 | AD180: 88.137804 | AE180: 100.36382 | AF180: 66.249677 | AG180: 97.990695 | AH180: 84.94696 | AI180: 205.50621 | AJ180: 83.160825 | AK180: 136.45351 | AL180: 136.45351 | AM180: 23.082727 | AN180: 85.375974 | AO180: 78.496483 | AP180: 92.702578 | AQ180: 64.259364 | AR180: 85.276065
A181: 44378 | B181: =(C181*41.5+AO181*58.5)/100 -> 80.63786 | C181: 85.873296 | D181: 82.744988 | E181: 15.239425 | F181: 69.908086 | G181: 85.571248 | H181: 75.304496 | I181: 89.907352 | J181: 102.88499 | K181: 81.905857 | L181: 85.068038 | M181: 70.216973 | N181: 97.286745 | O181: 102.88298 | P181: 97.472789 | Q181: 97.926873 | R181: 99.813505 | S181: 73.736787 | T181: 75.600722 | U181: 80.832127 | V181: 78.461662 | W181: 128.72919 | X181: 88.312539 | Y181: 98.494619 | Z181: 80.543385 | AA181: 80.614831 | AB181: 84.68119 | AC181: 80.496016 | AD181: 88.042159 | AE181: 104.97159 | AF181: 66.155934 | AG181: 86.099442 | AH181: 86.414957 | AI181: 204.41772 | AJ181: 75.232653 | AK181: 145.09154 | AL181: 145.09154 | AM181: 29.163595 | AN181: 132.1567 | AO181: 76.923833 | AP181: 79.778486 | AQ181: 64.45254 | AR181: 83.649985
A182: 44409 | B182: =(C182*41.5+AO182*58.5)/100 -> 87.506303 | C182: 98.911943 | D182: 135.73254 | E182: 15.841513 | F182: 71.865429 | G182: 125.24657 | H182: 68.23282 | I182: 164.52178 | J182: 103.05805 | K182: 79.381924 | L182: 82.093103 | M182: 69.360154 | N182: 90.012941 | O182: 84.361028 | P182: 80.206858 | Q182: 96.608751 | R182: 92.416172 | S182: 65.109549 | T182: 81.507145 | U182: 81.149585 | V182: 83.751367 | W182: 71.549755 | X182: 67.344941 | Y182: 117.44716 | Z182: 95.433057 | AA182: 73.861931 | AB182: 95.534116 | AC182: 95.60923 | AD182: 89.08179 | AE182: 103.60709 | AF182: 62.093271 | AG182: 91.706259 | AH182: 87.170638 | AI182: 199.58039 | AJ182: 55.732714 | AK182: 151.1904 | AL182: 151.1904 | AM182: 19.143394 | AN182: 209.3014 | AO182: 79.415122 | AP182: 86.226827 | AQ182: 73.34264 | AR182: 82.244993
A183: 44440 | B183: =(C183*41.5+AO183*58.5)/100 -> 82.29776 | C183: 92.188051 | D183: 87.534956 | E183: 16.443601 | F183: 78.662162 | G183: 106.9686 | H183: 74.282515 | I183: 93.77015 | J183: 97.593154 | K183: 80.369116 | L183: 79.331006 | M183: 84.206449 | N183: 96.998895 | O183: 104.50863 | P183: 109.10088 | Q183: 88.601692 | R183: 99.31774 | S183: 73.807571 | T183: 87.133738 | U183: 92.458744 | V183: 93.886557 | W183: 72.365535 | X183: 86.813006 | Y183: 105.03705 | Z183: 105.94661 | AA183: 82.676349 | AB183: 81.646514 | AC183: 106.41263 | AD183: 95.003125 | AE183: 105.55965 | AF183: 60.299137 | AG183: 84.000049 | AH183: 96.875537 | AI183: 191.44038 | AJ183: 91.137425 | AK183: 120.62023 | AL183: 120.62023 | AM183: 19.329781 | AN183: 110.46362 | AO183: 75.28157 | AP183: 80.667522 | AQ183: 59.685684 | AR183: 83.543783
A184: 44470 | B184: =(C184*41.5+AO184*58.5)/100 -> 84.110746 | C184: 89.386484 | D184: 94.368863 | E184: 6.7513426 | F184: 84.655344 | G184: 101.13126 | H184: 70.775641 | I184: 102.26656 | J184: 117.35066 | K184: 87.629363 | L184: 91.418671 | M184: 73.622327 | N184: 90.966582 | O184: 110.37918 | P184: 99.767613 | Q184: 84.708481 | R184: 93.480667 | S184: 67.419364 | T184: 69.998418 | U184: 76.96628 | V184: 76.655062 | W184: 105.77592 | X184: 75.016417 | Y184: 98.269014 | Z184: 112.76706 | AA184: 79.358904 | AB184: 93.910817 | AC184: 113.25486 | AD184: 95.263917 | AE184: 107.46912 | AF184: 74.524341 | AG184: 88.051482 | AH184: 95.480131 | AI184: 180.44381 | AJ184: 118.77556 | AK184: 151.21122 | AL184: 151.21122 | AM184: 26.436091 | AN184: 33.950315 | AO184: 80.368128 | AP184: 86.736456 | AQ184: 64.638331 | AR184: 88.624413
A185: 44501 | B185: =(C185*41.5+AO185*58.5)/100 -> 86.603351 | C185: 94.938093 | D185: 91.878672 | E185: 17.647777 | F185: 81.866996 | G185: 89.729229 | H185: 74.470591 | I185: 99.030004 | J185: 118.36944 | K185: 98.74573 | L185: 102.26638 | M185: 85.731769 | N185: 103.31709 | O185: 101.47985 | P185: 105.21524 | Q185: 88.921319 | R185: 106.6874 | S185: 73.361041 | T185: 77.779856 | U185: 83.841458 | V185: 83.424527 | W185: 79.083476 | X185: 86.873328 | Y185: 103.38979 | Z185: 119.56042 | AA185: 75.311034 | AB185: 121.98314 | AC185: 119.89676 | AD185: 97.681646 | AE185: 102.56324 | AF185: 70.876489 | AG185: 92.838578 | AH185: 98.960727 | AI185: 167.03682 | AJ185: 119.35488 | AK185: 137.47945 | AL185: 137.47945 | AM185: 39.779953 | AN185: 68.661485 | AO185: 80.69067 | AP185: 93.63836 | AQ185: 68.917136 | AR185: 86.198593
A186: 44531 | B186: =(C186*41.5+AO186*58.5)/100 -> 103.34246 | C186: 110.5638 | D186: 94.55606 | E186: 11.024811 | F186: 99.769213 | G186: 102.79911 | H186: 58.542274 | I186: 98.879018 | J186: 100.67132 | K186: 114.04324 | L186: 113.14826 | M186: 117.35151 | N186: 109.77439 | O186: 128.08952 | P186: 140.50421 | Q186: 114.00811 | R186: 109.32585 | S186: 109.23837 | T186: 124.01852 | U186: 123.99668 | V186: 130.41342 | W186: 159.60547 | X186: 82.2324 | Y186: 159.29259 | Z186: 121.89784 | AA186: 88.729744 | AB186: 73.726337 | AC186: 122.7151 | AD186: 113.59673 | AE186: 149.67331 | AF186: 87.434819 | AG186: 97.659831 | AH186: 111.63504 | AI186: 300.07628 | AJ186: 122.10454 | AK186: 218.89765 | AL186: 218.89765 | AM186: 30.658933 | AN186: 75.393738 | AO186: 98.219629 | AP186: 97.44067 | AQ186: 84.111876 | AR186: 106.15751
... A235: 46023 | B235: =(C235*41.5+AO235*58.5)/100 -> 103.5993 | C235: 123.00144 | D235: 119.68087 | E235: 66.843368 | F235: 116.97682 | G235: 176.84671 | H235: 101.59323 | I235: 124.13113 | J235: 51.349901 | K235: 115.08782 | L235: 118.37249 | M235: 102.94616 | N235: 121.27939 | O235: 102.12777 | P235: 159.56208 | Q235: 165.06638 | R235: 121.07063 | S235: 125.91768 | T235: 79.828817 | U235: 141.0888 | V235: 123.69486 | W235: 115.65613 | X235: 245.04452 | Y235: 127.42697 | Z235: 104.72361 | AA235: 236.32059 | AB235: 137.48643 | AC235: 103.27147 | AD235: 110.79903 | AE235: 76.768071 | AF235: 107.20402 | AG235: 75.805802 | AH235: 123.98776 | AI235: 4.8432737 | AJ235: 157.51118 | AK235: 270.02405 | AL235: 270.02405 | AM235: 20.523165 | AN235: 182.22584 | AO235: 89.835383 | AP235: 99.24618 | AQ235: 63.970049 | AR235: 103.49875
C237: *Les données du mois de janvier sont provisoires et feront l'objet de révision

Sheet Prix Intérieurs
A1: DIRECTION DE LA PREVISION ET DES ETUDES ECONOMIQUES
B3: OIGNON* | D3: CEREALES LOCALES* | G3: RIZ BRISE*
B4: Local | C4: Importé | D4: Souna | E4: Sorgho | F4: Maïs | G4: Parfumé | I4: Non parfumé | J4: Indien ordinaire | K4: Local
G5: Luxe | H5: Ordinaire | N5: ANNEES
B6: (FCFA/Kg) | C6: (FCFA/Kg) | D6: (FCFA/Kg) | E6: (FCFA/Kg) | F6: (FCFA/Kg) | G6: (FCFA/Kg) | H6: (FCFA/Kg) | I6: (FCFA/Kg) | J6: (FCFA/Kg) | K6: (FCFA/Kg)
A7: 39814 | B7: 241.42857 | C7: 336.36364 | D7: 207.42424 | E7: 203.48485 | F7: 194.54545 | G7: 455 | H7: 414.69697 | I7: 356.9697 | K7: 340.2381 | N7: 2009
A8: 39845 | B8: 246 | C8: 319.69697 | D8: 216 | E8: 206 | F8: 199 | G8: 478 | H8: 407 | I8: 316 | J8: 278 | K8: 310 | R8: TENDANCES DES MARCHES | AB8: TENDANCES DES MARCHES | AL8: TENDANCES DES MARCHES | AV8: TENDANCES DES MARCHES | BG8: TENDANCES DES MARCHES | BQ8: TENDANCES DES MARCHES | CA8: TENDANCES DES MARCHES | CK8: TENDANCES DES MARCHES | CU8: TENDANCES DES MARCHES | DG8: TENDANCES DES MARCHES | DQ8: TENDANCES DES MARCHES | EC8: TENDANCES DES MARCHES
A9: 39873 | B9: 230 | C9: 311 | D9: 212 | E9: 207 | F9: 201 | G9: 458 | H9: 409 | I9: 322 | J9: 280 | K9: 306 | R9: Prix moyens du mois de janvier 2009 | AB9: Prix moyens du mois de février 2009 | AL9: Prix moyens du mois de mars 2009 | AV9: Prix moyens du mois d'avril 2009 | BG9: Prix moyens du mois de mai 2009 | BQ9: Prix moyens du mois de juin 2009 | CA9: Prix moyens du mois de juillet 2009 | CK9: Prix moyens du mois d'août 2009 | CU9: Prix moyens du mois de septembre 2009 | DG9: Prix moyens du mois d'octobre 2009 | DQ9: Prix moyens du mois de novembre 2009 | EC9: Prix moyens du mois de décembre 2009
A10: 39904 | B10: 198.86364 | C10: 293.18182 | D10: 221 | E10: 217 | F10: 215 | G10: 469 | H10: 406 | I10: 308 | J10: - | K10: 308 | N10: régions | O10: OIGNON | Q10: CEREALES LOCALES | T10: RIZ BRISE 100 % | Y10: OIGNON | AA10: CEREALES LOCALES | AD10: RIZ BRISE 100 % | AI10: OIGNON | AK10: CEREALES LOCALES | AN10: RIZ BRISE 100 % | AS10: OIGNON | AU10: CEREALES LOCALES | AX10: RIZ BRISE 100 % | BC10: OIGNON | BE10: CEREALES LOCALES | BH10: RIZ BRISE 100 % | BM10: OIGNON | BO10: CEREALES LOCALES | BR10: RIZ BRISE 100 % | BW10: OIGNON | BY10: CEREALES LOCALES | CB10: RIZ BRISE 100 % | CG10: OIGNON | CI10: CEREALES LOCALES | CL10: RIZ BRISE 100 % | CQ10: OIGNON | CS10: CEREALES LOCALES | CV10: RIZ BRISE 100 % | DA10: OIGNON | DC10: CEREALES LOCALES | DH10: RIZ BRISE 100 % | DM10: OIGNON | DO10: CEREALES LOCALES | DR10: RIZ BRISE 100 % | DX10: OIGNON | EA10: CEREALES LOCALES | ED10: RIZ BRISE 100 %
A11: 39934 | B11: 195 | C11: 301 | D11: 223 | E11: 221 | F11: 208 | G11: 463 | H11: 398 | I11: 291 | J11: - | K11: 300 | O11: prix dominant (Fcfa/ Kg) | Q11: prix dominant (Fcfa/ Kg) | T11: prix dominant (Fcfa/ Kg) | Y11: prix dominant (Fcfa/ Kg) | AA11: prix dominant (Fcfa/ Kg) | AD11: prix dominant (Fcfa/ Kg) | AI11: prix dominant (Fcfa/ Kg) | AK11: prix dominant (Fcfa/ Kg) | AN11: prix dominant (Fcfa/ Kg) | AS11: prix dominant (Fcfa/ Kg) | AU11: prix dominant (Fcfa/ Kg) | AX11: prix dominant (Fcfa/ Kg) | BC11: prix dominant (Fcfa/ Kg) | BE11: prix dominant (Fcfa/ Kg) | BH11: prix dominant (Fcfa/ Kg) | BM11: prix dominant (Fcfa/ Kg) | BO11: prix dominant (Fcfa/ Kg) | BR11: prix dominant (Fcfa/ Kg) | BW11: prix dominant (Fcfa/ Kg) | BY11: prix dominant (Fcfa/ Kg) | CB11: prix dominant (Fcfa/ Kg) | CG11: prix dominant (Fcfa/ Kg) | CI11: prix dominant (Fcfa/ Kg) | CL11: prix dominant (Fcfa/ Kg) | CQ11: prix dominant (Fcfa/ Kg) | CS11: prix dominant (Fcfa/ Kg) | CV11: prix dominant (Fcfa/ Kg) | DA11: prix dominant (Fcfa/ Kg) | DC11: prix dominant (Fcfa/ Kg) | DH11: prix dominant (Fcfa/ Kg) | DM11: prix dominant (Fcfa/ Kg) | DO11: prix dominant (Fcfa/ Kg) | DR11: prix dominant (Fcfa/ Kg) | DX11: prix dominant (Fcfa/ Kg) | EA11: prix dominant (Fcfa/ Kg) | ED11: prix dominant (Fcfa/ Kg)
A12: 39965 | B12: 266 | C12: 300 | D12: 227 | E12: 222 | F12: 206 | G12: 439 | H12: 389 | I12: 288 | J12: - | K12: 293 | O12: Local | P12: Importé | Q12: Souna | R12: Sorgho | S12: Maïs | T12: parfumé | V12: Non Parfumé | W12: Indien ordinaire | X12: Local | Y12: Local | Z12: Importé | AA12: Souna | AB12: Sorgho | AC12: Maïs | AD12: parfumé | AF12: Non Parfumé | AG12: Indien ordinaire | AH12: Local | AI12: Local | AJ12: Importé | AK12: Souna | AL12: Sorgho | AM12: Maïs | AN12: parfumé | AP12: Non Parfumé | AQ12: Indien ordinaire | AR12: Local | AS12: Local | AT12: Importé | AU12: Souna | AV12: Sorgho | AW12: Maïs | AX12: parfumé | AZ12: Non Parfumé | BA12: Indien ordinaire | BB12: Local | BC12: Local | BD12: Importé | BE12: Souna | BF12: Sorgho | BG12: Maïs | BH12: parfumé | BJ12: Non Parfumé | BK12: Indien ordinaire | BL12: Local | BM12: Local | BN12: Importé | BO12: Souna | BP12: Sorgho | BQ12: Maïs | BR12: parfumé | BT12: Non Parfumé | BU12: Indien ordinaire | BV12: Local | BW12: Local | BX12: Importé | BY12: Souna | BZ12: Sorgho | CA12: Maïs | CB12: parfumé | CD12: Non Parfumé | CE12: Indien ordinaire | CF12: Local | CG12: Local | CH12: Importé | CI12: Souna | CJ12: Sorgho | CK12: Maïs | CL12: parfumé | CN12: Non Parfumé | CO12: Indien ordinaire | CP12: Local | CQ12: Local | CR12: Importé | CS12: Souna | CT12: Sorgho | CU12: Maïs | CV12: parfumé | CX12: Non Parfumé | CY12: Indien ordinaire | CZ12: Local | DA12: Local | DB12: Importé | DC12: Souna | DD12: Sorgho | DG12: Maïs | DH12: parfumé | DJ12: Non Parfumé | DK12: Indien ordinaire | DL12: Local | DM12: Local | DN12: Importé | DO12: Souna | DP12: Sorgho | DQ12: Maïs | DR12: parfumé | DU12: Non Parfumé | DV12: Indien ordinaire | DW12: Local | DX12: Local | DZ12: Importé | EA12: Souna | EB12: Sorgho | EC12: Maïs | ED12: parfumé | EF12: Non Parfumé | EG12: Indien ordinaire | EH12: Local
A13: 39995 | B13: 327 | C13: 325 | D13: 226 | E13: 227 | F13: 211 | G13: 450 | H13: 384 | I13: 280 | J13: 277 | K13: 279 | T13: Luxe | U13: Ordinaire | AD13: Luxe | AE13: Ordinaire | AN13: Luxe | AO13: Ordinaire | AX13: Luxe | AY13: Ordinaire | BH13: Luxe | BI13: Ordinaire | BR13: Luxe | BS13: Ordinaire | CB13: Luxe | CC13: Ordinaire | CL13: Luxe | CM13: Ordinaire | CV13: Luxe | CW13: Ordinaire | DH13: Luxe | DI13: Ordinaire | DR13: Luxe | DS13: Ordinaire | ED13: Luxe | EE13: Ordinaire
A14: 40026 | B14: 376 | C14: - | D14: 226 | E14: 230 | F14: 213 | G14: 433 | H14: 377 | I14: 278 | J14: 250 | K14: 271 | N14: Dakar | O14: 165 | P14: 283.33333 | Q14: 233.33333 | R14: 250 | S14: 225 | T14: 450 | U14: 400 | V14: 383.33333 | X14: 350 | Y14: 212.5 | Z14: 300 | AA14: 225 | AB14: 250 | AC14: 216.66667 | AD14: 450 | AE14: 400 | AF14: 350 | AG14: 275 | AH14: 316.66667 | AI14: 212.5 | AJ14: 287.5 | AK14: 225 | AL14: 231.25 | AM14: 225 | AN14: 450 | AO14: 400 | AP14: 343.75 | AR14: 300 | AS14: 200 | AT14: 250 | AU14: 225 | AV14: 237.5 | AW14: 225 | AX14: 450 | AY14: 400 | AZ14: 325 | BB14: 300 | BC14: 193.75 | BD14: 312.5 | BE14: 231.25 | BF14: 243.75 | BG14: 212.5 | BH14: 450 | BI14: 400 | BJ14: 300 | BL14: 300 | BM14: 287.5 | BO14: 250 | BP14: 250 | BQ14: 225 | BR14: 437.5 | BS14: 362.5 | BT14: 300 | BV14: 300 | BW14: 325 | BY14: 233.33333 | BZ14: 250 | CA14: 216.66667 | CB14: 425 | CC14: 350 | CD14: 275 | CE14: 275 | CF14: 300 | CG14: 375 | CI14: 225 | CJ14: 250 | CK14: 225 | CL14: 425 | CM14: 362.5 | CN14: 275 | CO14: 250 | CP14: 300 | CQ14: 200 | CR14: 325 | CS14: 250 | CT14: 250 | CU14: 225 | CV14: 425 | CW14: 350 | CX14: 275 | CZ14: 287.5 | DB14: 275 | DC14: 250 | DD14: 250 | DG14: 225 | DH14: 425 | DI14: 350 | DJ14: 250 | DK14: 258.33333 | DL14: 266.66667 | DN14: 300 | DO14: 243.75 | DP14: 237.5 | DQ14: 225 | DR14: 400 | DS14: 350 | DU14: 250 | DV14: 250 | DW14: 275 | DZ14: 316.66667 | EA14: 233.33333 | EB14: 233.33333 | EC14: 241.66667 | ED14: 400 | EE14: 350 | EF14: 250 | EG14: 250 | EH14: 258.33333
A15: 40057 | B15: 319 | C15: 386 | D15: 225 | E15: 217 | F15: 211 | G15: 433 | H15: 360 | I15: 273 | J15: - | K15: 267 | N15: Thiès | O15: 250 | P15: 300 | Q15: 225 | R15: 200 | S15: 196.66667 | T15: 440 | U15: 396.66667 | V15: 333.33333 | Y15: 250 | Z15: 300 | AA15: 225 | AB15: 200 | AC15: 200 | AD15: 450 | AE15: 390 | AF15: 300 | AI15: 212.5 | AJ15: 312.5 | AK15: 212.5 | AL15: 200 | AM15: 200 | AN15: 450 | AO15: 390 | AP15: 300 | AS15: 150 | AT15: 275 | AU15: 200 | AV15: 205 | AW15: 200 | AX15: 450 | AY15: 387.5 | AZ15: 287.5 | BB15: 300 | BC15: 150 | BD15: 187.5 | BE15: 212.5 | BF15: 212.5 | BG15: 200 | BH15: 450 | BI15: 382.5 | BJ15: 272.5 | BL15: 281.25 | BM15: 225 | BO15: 225 | BP15: 225 | BQ15: 200 | BR15: 430 | BS15: 375 | BT15: 275 | BV15: 275 | BW15: 333.33333 | BY15: 225 | BZ15: 225 | CA15: 220 | CB15: 425 | CC15: 375 | CD15: 275 | CG15: 350 | CI15: 225 | CJ15: 225 | CK15: 200 | CL15: 425 | CM15: 362.5 | CN15: 250 | CP15: 250 | CR15: 300 | CS15: 225 | CT15: 225 | CU15: 225 | CV15: 425 | CW15: 350 | CX15: 250 | CZ15: 250 | DB15: 283.33333 | DC15: 200 | DD15: 216.66667 | DG15: 213.33333 | DH15: 416.66667 | DI15: 350 | DJ15: 250 | DL15: 258.33333 | DN15: 300 | DO15: 193.75 | DP15: 225 | DQ15: 205 | DR15: 400 | DS15: 325 | DU15: 250 | DW15: 250 | DZ15: 308.33333 | EA15: 183.33333 | EB15: 200 | EC15: 200 | ED15: 400 | EE15: 333.33333 | EF15: 250 | EH15: 250
A16: 40087 | B16: - | C16: 323 | D16: 204 | E16: 215 | F16: 204 | G16: 431 | H16: 357 | I16: 261 | J16: 279 | K16: 259 | N16: Diourbel | O16: 225 | P16: 283.33333 | Q16: 205 | R16: 200 | S16: 200 | U16: 408.33333 | V16: 325 | X16: 308.33333 | Y16: 225 | Z16: 283.33333 | AA16: 206.66667 | AB16: 200 | AC16: 200 | AE16: 400 | AF16: 300 | AH16: 280 | AI16: 200 | AJ16: 281.25 | AK16: 202.5 | AL16: 200 | AM16: 195 | AO16: 400 | AP16: 305 | AR16: 295 | AS16: 150 | AT16: 250 | AU16: 210 | AV16: 200 | AW16: 200 | AY16: 400 | AZ16: 287.5 | BB16: 300 | BC16: 150 | BD16: 275 | BE16: 215 | BF16: 202.5 | BG16: 200 | BI16: 383.75 | BJ16: 275 | BL16: 280 | BM16: 250 | BN16: 350 | BO16: 220 | BP16: 210 | BQ16: 200 | BS16: 375 | BT16: 267.5 | BV16: 260 | BW16: 300 | BY16: 223.33333 | BZ16: 220 | CA16: 190 | CC16: 366.66667 | CD16: 275 | CF16: 255 | CG16: 350 | CI16: 217.5 | CJ16: 225 | CK16: 200 | CM16: 375 | CN16: 275 | CP16: 245 | CR16: 300 | CS16: 200 | CT16: 200 | CU16: 200 | CW16: 350 | CX16: 250 | CZ16: 225 | DB16: 283.33333 | DC16: 171.66667 | DD16: 212.5 | DI16: 350 | DJ16: 250 | DL16: 233.33333 | DN16: 312.5 | DO16: 175 | DP16: 181.25 | DS16: 350 | DU16: 250 | DW16: 218.75 | DZ16: 333.33333 | EA16: 175 | EB16: 175 | EC16: 175 | EE16: 350 | EF16: 266.66667 | EH16: 233.33333
A17: 40118 | B17: - | C17: 335 | D17: 194 | E17: 208 | F17: 194 | G17: 417 | H17: 352 | I17: 257 | J17: 250 | K17: 250 | N17: Louga | P17: 300 | Q17: 203.33333 | R17: 193.33333 | S17: 196.66667 | U17: 425 | V17: 341.66667 | X17: 316.66667 | Y17: 250 | Z17: 308.33333 | AA17: 210 | AB17: 200 | AC17: 200 | AE17: 425 | AF17: 325 | AH17: 275 | AI17: 212.5 | AJ17: 306.25 | AK17: 210 | AL17: 200 | AM17: 200 | AO17: 425 | AP17: 318.75 | AR17: 293.75 | AS17: 150 | AT17: 250 | AU17: 205 | AV17: 200 | AY17: 400 | AZ17: 300 | BB17: 300 | BC17: 150 | BD17: 250 | BE17: 215 | BF17: 205 | BI17: 400 | BJ17: 308.75 | BL17: 300 | BM17: 225 | BO17: 220 | BP17: 225 | BQ17: 200 | BS17: 400 | BT17: 275 | BV17: 300 | BW17: 283.33333 | BY17: 223.33333 | BZ17: 225 | CA17: 225 | CC17: 400 | CD17: 275 | CF17: 250 | CG17: 337.5 | CI17: 217.5 | CJ17: 210 | CK17: 225 | CM17: 350 | CN17: 275 | CP17: 300 | CQ17: 375 | CR17: 350 | CS17: 225 | CT17: 220 | CW17: 350 | CX17: 275 | CZ17: 250 | DB17: 300 | DC17: 218.33333 | DD17: 216.66667 | DI17: 350 | DJ17: 275 | DL17: 250 | DN17: 337.5 | DO17: 200 | DP17: 208.75 | DQ17: 191.66667 | DS17: 350 | DU17: 275 | DW17: 250 | DZ17: 333.33333 | EA17: 188.33333 | EB17: 195 | EC17: 191.66667 | EE17: 350 | EF17: 275 | EH17: 216.66667
A18: 40148 | B18: - | C18: 349 | D18: 195 | E18: 199 | F18: 189 | G18: 406 | H18: 350 | I18: 266 | J18: 250 | K18: 244 | N18: St louis | O18: 250 | P18: 383.33333 | Q18: 283.33333 | R18: 250 | S18: 191.66667 | U18: 433.33333 | V18: 391.66667 | X18: 300 | Y18: 250 | Z18: 316.66667 | AA18: 300 | AB18: 250 | AC18: 191.66667 | AE18: 400 | AF18: 325 | AH18: 300 | AI18: 200 | AJ18: 300 | AK18: 287.5 | AL18: 231.25 | AM18: 200 | AO18: 402.5 | AP18: 343.75 | AR18: 300 | AS18: 200 | AT18: 300 | AU18: 250 | AV18: 200 | AW18: 265 | AY18: 400 | AZ18: 300 | BB18: 300 | BC18: 150 | BD18: 300 | BE18: 250 | BF18: 243.75 | BG18: 206.25 | BI18: 400 | BJ18: 306.25 | BL18: 325 | BM18: 237.5 | BN18: 300 | BO18: 250 | BP18: 200 | BQ18: 200 | BS18: 400 | BT18: 325 | BV18: 325 | BW18: 300 | BX18: 325 | BY18: 250 | BZ18: 233.33333 | CA18: 183.33333 | CC18: 408.33333 | CD18: 291.66667 | CE18: 300 | CF18: 286.66667 | CG18: 300 | CI18: 275 | CJ18: 250 | CK18: 200 | CM18: 400 | CN18: 300 | CP18: 275 | CQ18: 300 | CR18: 450 | CS18: 300 | CT18: 225 | CU18: 200 | CW18: 400 | CX18: 300 | CY18: 300 | CZ18: 300 | DB18: 400 | DC18: 241.66667 | DD18: 233.33333 | DG18: 225 | DI18: 400 | DJ18: 300 | DK18: 300 | DL18: 266.66667 | DN18: 387.5 | DO18: 256.25 | DP18: 243.75 | DQ18: 243.75 | DS18: 400 | DU18: 300 | DW18: 250 | DZ18: 433.33333 | EA18: 275 | EB18: 241.66667 | EC18: 216.66667 | ED18: 400 | EE18: 350 | EF18: 325 | EH18: 250
A19: 40179 | B19: - | C19: 365 | D19: 201 | E19: 201 | F19: 196 | G19: 411 | H19: 351 | I19: 273 | J19: 300 | K19: 253 | N19: Matam | O19: 300 | P19: 316.66667 | Q19: 250 | R19: 250 | S19: 241.66667 | U19: 416.66667 | V19: 358.33333 | X19: 400 | Y19: 250 | Z19: 300 | AA19: 250 | AB19: 250 | AC19: 241.66667 | AE19: 408.33333 | AF19: 333.33333 | AH19: 325 | AI19: 200 | AJ19: 300 | AK19: 237.5 | AL19: 250 | AM19: 250 | AO19: 431.25 | AP19: 337.5 | AR19: 325 | AS19: 150 | AT19: 300 | AU19: 237.5 | AV19: 237.5 | AW19: 237.5 | AY19: 412.5 | AZ19: 312.5 | BC19: 162.5 | BD19: 300 | BE19: 250 | BF19: 250 | BG19: 250 | BI19: 400 | BJ19: 275 | BM19: 275 | BO19: 250 | BP19: 250 | BQ19: 250 | BS19: 400 | BT19: 275 | BW19: 366.66667 | BY19: 250 | BZ19: 250 | CA19: 250 | CC19: 400 | CD19: 275 | CF19: 275 | CG19: 450 | CI19: 250 | CJ19: 250 | CK19: 250 | CM19: 400 | CN19: 275 | CP19: 275 | CR19: 350 | CS19: 250 | CT19: 250 | CU19: 237.5 | CW19: 362.5 | CX19: 275 | CZ19: 275 | DB19: 316.66667 | DC19: 250 | DD19: 250 | DG19: 250 | DI19: 358.33333 | DJ19: 266.66667 | DL19: 258.33333 | DN19: 337.5 | DO19: 250 | DP19: 250 | DQ19: 250 | DS19: 350 | DU19: 250 | DW19: 250 | DZ19: 333.33333 | EA19: 250 | EB19: 250 | EC19: 250 | EE19: 350 | EF19: 250 | EH19: 250
A20: 40210 | B20: 282 | C20: 378 | D20: 204 | E20: 194 | F20: 195 | G20: 415 | H20: 353 | I20: 250 | J20: 250 | K20: 251 | N20: Fatick | P20: 366.66667 | Q20: 203.33333 | R20: 208.33333 | S20: 193.33333 | U20: 425 | V20: 366.66667 | Y20: 250 | Z20: 350 | AA20: 200 | AB20: 200 | AC20: 200 | AE20: 403.33333 | AF20: 227.33333 | AI20: 250 | AJ20: 350 | AK20: 200 | AL20: 212.5 | AM20: 200 | AO20: 402.5 | AP20: 317.5 | AR20: 300 | AS20: 200 | AT20: 300 | AU20: 225 | AV20: 225 | AW20: 192.5 | AY20: 400 | AZ20: 307.5 | BB20: 310 | BC20: 200 | BD20: 350 | BE20: 225 | BF20: 200 | BG20: 185.5 | BI20: 402.5 | BJ20: 311.66667 | BL20: 310 | BM20: 300 | BO20: 225 | BP20: 237.5 | BQ20: 180 | BS20: 400 | BT20: 310 | BW20: 350 | BY20: 225 | BZ20: 225 | CA20: 192.5 | CC20: 395 | CD20: 275 | CG20: 375 | CI20: 225 | CJ20: 225 | CK20: 185 | CM20: 375 | CN20: 275 | CR20: 450 | CS20: 212.5 | CT20: 207.5 | CU20: 200 | CW20: 337.5 | CX20: 272.5 | DB20: 333.33333 | DC20: 200 | DD20: 225 | DI20: 350 | DJ20: 250 | DL20: 251.66667 | DN20: 350 | DO20: 181.25 | DP20: 200 | DQ20: 200 | DS20: 350 | DU20: 250 | DZ20: 350 | EA20: 200 | EB20: 208.33333 | EC20: 200 | EE20: 358.33333 | EF20: 258.33333
A21: 40238 | B21: 307 | C21: 375 | D21: 201 | E21: 196 | F21: 194 | G21: 408 | H21: 349 | I21: 266 | J21: 250 | K21: 260 | N21: Kaolack | O21: 250 | P21: 333.33333 | Q21: 128.33333 | R21: 136.66667 | S21: 145 | U21: 363.33333 | V21: 343.33333 | X21: 331.66667 | Y21: 225 | Z21: 291.66667 | AA21: 156.66667 | AB21: 143.33333 | AC21: 176.66667 | AD21: 533.33333 | AE21: 393.33333 | AF21: 313.33333 | AG21: 280 | AH21: 350 | AI21: 231.25 | AJ21: 281.25 | AK21: 165 | AL21: 167.5 | AM21: 175 | AN21: 475 | AO21: 400 | AP21: 300 | AQ21: 280 | AS21: 187.5 | AT21: 275 | AU21: 177.5 | AV21: 177.5 | AW21: 170 | AX21: 500 | AY21: 395 | AZ21: 290 | BC21: 175 | BD21: 262.5 | BE21: 180 | BF21: 183.75 | BG21: 178.75 | BH21: 500 | BI21: 380 | BJ21: 270 | BM21: 187.5 | BN21: 250 | BO21: 177.5 | BP21: 185 | BQ21: 175 | BS21: 372.5 | BT21: 270 | BW21: 241.66667 | BY21: 180 | BZ21: 191.66667 | CA21: 181.66667 | CB21: 500 | CC21: 376.66667 | CD21: 275 | CE21: 255 | CG21: 350 | CI21: 180 | CJ21: 200 | CK21: 170 | CM21: 350 | CN21: 260 | CP21: 245 | CR21: 325 | CS21: 175 | CT21: 175 | CU21: 170 | CW21: 340 | CX21: 250 | DB21: 316.66667 | DC21: 158.33333 | DD21: 178.33333 | DG21: 156.66667 | DI21: 340 | DJ21: 250 | DL21: 245 | DN21: 300 | DO21: 132.5 | DP21: 186.25 | DQ21: 132.5 | DS21: 337.5 | DU21: 242.5 | DW21: 230 | DZ21: 333.33333 | EA21: 140 | EB21: 158.33333 | EC21: 141.66667 | EE21: 341.66667 | EF21: 250 | EH21: 220
A22: 40269 | B22: 311 | C22: 383 | D22: 199 | E22: 194 | F22: 187 | G22: 408 | H22: 350 | I22: 276 | J22: 250 | K22: 263 | N22: Tamba | O22: 250 | P22: 333.33333 | Q22: 150 | R22: 150 | S22: 150 | U22: 441.66667 | V22: 383.33333 | X22: 375 | Y22: 266.66667 | Z22: 316.66667 | AA22: 200 | AB22: 175 | AC22: 166.66667 | AE22: 425 | AF22: 341.66667 | AH22: 325 | AI22: 250 | AJ22: 312.5 | AK22: 190 | AL22: 187.5 | AM22: 165 | AO22: 425 | AP22: 325 | AR22: 325 | AS22: 250 | AT22: 300 | AU22: 225 | AV22: 225 | AW22: 200 | AY22: 425 | AZ22: 325 | BB22: 325 | BC22: 262.5 | BD22: 300 | BE22: 225 | BF22: 212.5 | BG22: 200 | BI22: 418.75 | BJ22: 281.25 | BL22: 306.25 | BM22: 337.5 | BO22: 225 | BP22: 200 | BQ22: 200 | BS22: 400 | BT22: 300 | BV22: 300 | BW22: 383.33333 | BY22: 225 | BZ22: 216.66667 | CA22: 216.66667 | CC22: 366.66667 | CD22: 286.66667 | CF22: 310 | CG22: 450 | CI22: 225 | CJ22: 225 | CK22: 225 | CM22: 400 | CN22: 300 | CP22: 300 | CQ22: 400 | CR22: 425 | CS22: 200 | CT22: 200 | CU22: 200 | CW22: 400 | CX22: 300 | CZ22: 275 | DB22: 333.33333 | DC22: 150 | DD22: 158.33333 | DG22: 158.33333 | DI22: 350 | DJ22: 258.33333 | DL22: 266.66667 | DN22: 350 | DO22: 131.25 | DP22: 137.5 | DQ22: 131.25 | DS22: 350 | DU22: 250 | DZ22: 350 | EA22: 121.66667 | EB22: 121.66667 | EC22: 116.66667 | EE22: 350 | EF22: 266.66667 | EG22: 250 | EH22: 275
A23: 40299 | B23: 331 | C23: 400 | D23: 202 | E23: 201 | F23: 191 | G23: 410 | H23: 349 | I23: 275 | J23: 250 | K23: 256 | N23: Kolda | P23: 450 | Q23: 191.66667 | R23: 183.33333 | S23: 175 | T23: 475 | U23: 426.66667 | V23: 350 | Z23: 450 | AA23: 183.33333 | AB23: 175 | AC23: 175 | AE23: 415 | AF23: 325 | AI23: 308.33333 | AJ23: 375 | AK23: 187.5 | AL23: 175 | AM23: 180 | AO23: 415 | AP23: 325 | AS23: 300 | AT23: 400 | AU23: 255 | AV23: 225 | AW23: 225 | AX23: 475 | AY23: 420 | AZ23: 325 | BB23: 325 | BC23: 300 | BD23: 400 | BE23: 225 | BF23: 225 | BG23: 225 | BH23: 450 | BI23: 405 | BJ23: 293.33333 | BL23: 300 | BM23: 325 | BO23: 225 | BP23: 212.5 | BQ23: 212.5 | BS23: 395 | BT23: 285 | BW23: 383.33333 | BY23: 225 | BZ23: 206.66667 | CA23: 216.66667 | CC23: 386.66667 | CD23: 275 | CG23: 400 | CI23: 225 | CJ23: 225 | CK23: 225 | CM23: 375 | CN23: 275 | CR23: 600 | CS23: 200 | CT23: 200 | CU23: 200 | CW23: 360 | CX23: 275 | DB23: 400 | DC23: 175 | DD23: 175 | DG23: 175 | DI23: 356.66667 | DJ23: 250 | DL23: 275 | DN23: 400 | DO23: 175 | DP23: 168.75 | DQ23: 156.25 | DS23: 350 | DU23: 250 | DZ23: 400 | EA23: 175 | EB23: 153.33333 | EC23: 150 | EE23: 350 | EF23: 266.66667
A24: 40330 | B24: 410 | C24: - | D24: 201 | E24: 208 | F24: 193 | G24: 410 | H24: 350 | I24: 278 | J24: 256 | K24: 265 | N24: Ziguinchor | P24: 350 | Q24: 208.33333 | R24: 216.66667 | S24: 225 | U24: 425 | V24: 350 | Y24: 283.33333 | Z24: 300 | AA24: 216.66667 | AB24: 225 | AC24: 225 | AE24: 416.66667 | AF24: 333.33333 | AI24: 250 | AJ24: 312.5 | AK24: 212.5 | AL24: 225 | AM24: 225 | AO24: 412.5 | AP24: 325 | AS24: 250 | AT24: 325 | AU24: 225 | AV24: 250 | AW24: 237.5 | AY24: 425 | AZ24: 325 | BC24: 250 | BD24: 375 | BE24: 225 | BF24: 250 | BG24: 225 | BI24: 406.25 | BJ24: 312.5 | BM24: 275 | BO24: 225 | BP24: 250 | BQ24: 225 | BR24: 450 | BS24: 400 | BT24: 287.5 | BW24: 333.33333 | BY24: 225 | BZ24: 250 | CA24: 233.33333 | CB24: 450 | CC24: 400 | CD24: 300 | CG24: 400 | CI24: 225 | CJ24: 250 | CK24: 237.5 | CL24: 450 | CM24: 400 | CN24: 300 | CP24: 250 | CR24: 375 | CS24: 237.5 | CT24: 237.5 | CU24: 250 | CV24: 450 | CW24: 362.5 | CX24: 275 | CZ24: 275 | DB24: 316.66667 | DC24: 233.33333 | DD24: 250 | DG24: 225 | DH24: 450 | DI24: 375 | DJ24: 275 | DL24: 275 | DN24: 312.5 | DO24: 200 | DP24: 250 | DQ24: 200 | DR24: 450 | DS24: 356.25 | DU24: 256.25 | DW24: 275 | DZ24: 350 | EA24: 200 | EB24: 250 | EC24: 200 | ED24: 425 | EE24: 366.66667 | EF24: 266.66667
A25: 40360 | B25: 519 | C25: 581 | D25: 206 | E25: 215 | F25: 195 | G25: 408 | H25: 352 | I25: 285 | J25: 263 | K25: 274 | N25: Prix Moyen | O25: 241.42857 | P25: 336.36364 | Q25: 207.42424 | R25: 203.48485 | S25: 194.54545 | T25: 455 | U25: 414.69697 | V25: 356.9697 | X25: 340.2381 | Y25: 246.25 | Z25: 319.69697 | AA25: 215.75758 | AB25: 206.21212 | AC25: 199.39394 | AD25: 477.77778 | AE25: 406.9697 | AF25: 315.81818 | AG25: 277.5 | AH25: 310.2381 | AI25: 229.73485 | AJ25: 310.79545 | AK25: 211.81818 | AL25: 207.27273 | AM25: 201.36364 | AN25: 458.33333 | AO25: 409.43182 | AP25: 321.93182 | AQ25: 280 | AR25: 305.53571 | AS25: 198.86364 | AT25: 293.18182 | AU25: 221.36364 | AV25: 216.59091 | AW25: 215.25 | AX25: 468.75 | AY25: 405.90909 | AZ25: 307.72727 | BB25: 307.5 | BC25: 194.88636 | BD25: 301.13636 | BE25: 223.06818 | BF25: 220.79545 | BG25: 208.3 | BH25: 462.5 | BI25: 398.06818 | BJ25: 291.47727 | BL25: 300.3125 | BM25: 265.90909 | BN25: 300 | BO25: 226.59091 | BP25: 222.27273 | BQ25: 206.13636 | BR25: 439.16667 | BS25: 389.09091 | BT25: 288.18182 | BV25: 293.33333 | BW25: 327.27273 | BX25: 325 | BY25: 225.90909 | BZ25: 226.66667 | CA25: 211.43939 | CB25: 450 | CC25: 384.09091 | CD25: 279.84848 | CE25: 277 | CF25: 279.44444 | CG25: 376.13636 | CI25: 226.36364 | CJ25: 230.45455 | CK25: 212.95455 | CL25: 433.33333 | CM25: 377.27273 | CN25: 278.18182 | CO25: 250 | CP25: 271.11111 | CQ25: 318.75 | CR25: 386.36364 | CS25: 225 | CT25: 217.27273 | CU25: 210.75 | CV25: 433.33333 | CW25: 360.22727 | CX25: 272.5 | CY25: 300 | CZ25: 267.1875 | DB25: 323.48485 | DC25: 204.39394 | DD25: 215.07576 | DG25: 203.54167 | DH25: 430.55556 | DI25: 357.27273 | DJ25: 261.36364 | DK25: 279.16667 | DL25: 258.78788 | DN25: 335.22727 | DO25: 194.43182 | DP25: 208.06818 | DQ25: 193.54167 | DR25: 416.66667 | DS25: 351.70455 | DU25: 256.70455 | DV25: 250 | DW25: 249.84375 | DZ25: 349.24242 | EA25: 194.69697 | EB25: 198.78788 | EC25: 189.39394 | ED25: 406.25 | EE25: 350 | EF25: 265.90909 | EG25: 250 | EH25: 244.16667
A26: 40391 | B26: 465 | C26: 534 | D26: 204 | E26: 213 | F26: 196 | G26: 408 | H26: 352 | I26: 289 | J26: 275 | K26: 277
A27: 40422 | B27: 493 | C27: 519 | D27: 196 | E27: 209 | F27: 193 | G27: 408 | H27: 351 | I27: 290 | J27: 250 | K27: 272
A28: 40452 | B28: 500 | C28: 401 | D28: 186 | E28: 205 | F28: 193 | G28: 396 | H28: 354 | I28: 297 | J28: 288 | K28: 281 | N28: 2010
A29: 40483 | B29: - | C29: 445 | D29: 185 | E29: 210 | F29: 189 | G29: 405 | H29: 356 | I29: 298 | J29: 288 | K29: 281 | Q29: TENDANCES DES MARCHES | AB29: TENDANCES DES MARCHES | AL29: TENDANCES DES MARCHES | AV29: TENDANCES DES MARCHES | BF29: TENDANCES DES MARCHES | BP29: TENDANCES DES MARCHES | CA29: TENDANCES DES MARCHES | CK29: TENDANCES DES MARCHES | CU29: TENDANCES DES MARCHES | DE29: TENDANCES DES MARCHES | DO29: TENDANCES DES MARCHES | DY29: TENDANCES DES MARCHES
A30: 40513 | B30: - | C30: 482 | D30: 185 | E30: 195 | F30: 190 | G30: 398 | H30: 349 | I30: 291 | J30: 295 | K30: 282 | Q30: Prix moyens du mois de janvier 2010 | AB30: Prix moyens du mois de février 2010 | AL30: Prix moyens du mois de mars 2010 | AV30: Prix moyens du mois d'avril 2010 | BF30: Prix moyens du mois de mai 2010 | BP30: Prix moyens du mois de juin 2010 | CA30: Prix moyens du mois de juillet 2010 | CK30: Prix moyens du mois d'août 2010 | CU30: Prix moyens du mois de septembre 2010 | DE30: Prix moyens du mois d'octobre 2010 | DO30: Prix moyens du mois de novembre 2010 | DY30: Prix moyens du mois de décembre 2010
A31: 40544 | B31: - | C31: 451 | D31: 191 | E31: 196 | F31: 192 | G31: 405 | H31: 353 | I31: 301 | J31: 306 | K31: 282 | N31: OIGNON | P31: CEREALES LOCALES | S31: RIZ BRISE 100 % | X31: OIGNON | Z31: CEREALES LOCALES | AC31: RIZ BRISE 100 % | AH31: OIGNON | AJ31: CEREALES LOCALES | AM31: RIZ BRISE 100 % | AR31: OIGNON | AT31: CEREALES LOCALES | AW31: RIZ BRISE 100 % | BB31: OIGNON | BD31: CEREALES LOCALES | BG31: RIZ BRISE 100 % | BL31: OIGNON | BN31: CEREALES LOCALES | BQ31: RIZ BRISE 100 % | BV31: OIGNON | BX31: CEREALES LOCALES | CA31: RIZ BRISE 100 % | CF31: OIGNON | CH31: CEREALES LOCALES | CK31: RIZ BRISE 100 % | CP31: OIGNON | CR31: CEREALES LOCALES | CU31: RIZ BRISE 100 % | CZ31: OIGNON | DB31: CEREALES LOCALES | DE31: RIZ BRISE 100 % | DJ31: OIGNON | DL31: CEREALES LOCALES | DO31: RIZ BRISE 100 % | DT31: OIGNON | DV31: CEREALES LOCALES | DY31: RIZ BRISE 100 %
A32: 40575 | B32: 360.71429 | C32: 438.06818 | D32: 192.04545 | E32: 202.04545 | F32: 192.84091 | G32: 406.25 | H32: 341.02273 | I32: 298.63636 | J32: 262.5 | K32: 284.10714 | N32: prix dominant (Fcfa/ Kg) | P32: prix dominant (Fcfa/ Kg) | S32: prix dominant (Fcfa/ Kg) | X32: prix dominant (Fcfa/ Kg) | Z32: prix dominant (Fcfa/ Kg) | AC32: prix dominant (Fcfa/ Kg) | AH32: prix dominant (Fcfa/ Kg) | AJ32: prix dominant (Fcfa/ Kg) | AM32: prix dominant (Fcfa/ Kg) | AR32: prix dominant (Fcfa/ Kg) | AT32: prix dominant (Fcfa/ Kg) | AW32: prix dominant (Fcfa/ Kg) | BB32: prix dominant (Fcfa/ Kg) | BD32: prix dominant (Fcfa/ Kg) | BG32: prix dominant (Fcfa/ Kg) | BL32: prix dominant (Fcfa/ Kg) | BN32: prix dominant (Fcfa/ Kg) | BQ32: prix dominant (Fcfa/ Kg) | BV32: prix dominant (Fcfa/ Kg) | BX32: prix dominant (Fcfa/ Kg) | CA32: prix dominant (Fcfa/ Kg) | CF32: prix dominant (Fcfa/ Kg) | CH32: prix dominant (Fcfa/ Kg) | CK32: prix dominant (Fcfa/ Kg) | CP32: prix dominant (Fcfa/ Kg) | CR32: prix dominant (Fcfa/ Kg) | CU32: prix dominant (Fcfa/ Kg) | CZ32: prix dominant (Fcfa/ Kg) | DB32: prix dominant (Fcfa/ Kg) | DE32: prix dominant (Fcfa/ Kg) | DJ32: prix dominant (Fcfa/ Kg) | DL32: prix dominant (Fcfa/ Kg) | DO32: prix dominant (Fcfa/ Kg) | DT32: prix dominant (Fcfa/ Kg) | DV32: prix dominant (Fcfa/ Kg) | DY32: prix dominant (Fcfa/ Kg)
A33: 40603 | B33: 349.58333 | C33: 434.65909 | D33: 190.22727 | E33: 198.97727 | F33: 198.63636 | G33: 406.25 | H33: 334.65909 | I33: 297.65152 | J33: 280 | K33: 282.91667 | N33: Local | O33: Importé | P33: Souna | Q33: Sorgho | R33: Maïs | S33: parfumé | U33: Non Parfumé | V33: Indien ordinaire | W33: Local | X33: Local | Y33: Importé | Z33: Souna | AA33: Sorgho | AB33: Maïs | AC33: parfumé | AE33: Non Parfumé | AF33: Indien ordinaire | AG33: Local | AH33: Local | AI33: Importé | AJ33: Souna | AK33: Sorgho | AL33: Maïs | AM33: parfumé | AO33: Non Parfumé | AP33: Indien ordinaire | AQ33: Local | AR33: Local | AS33: Importé | AT33: Souna | AU33: Sorgho | AV33: Maïs | AW33: parfumé | AY33: Non Parfumé | AZ33: Indien ordinaire | BA33: Local | BB33: Local | BC33: Importé | BD33: Souna | BE33: Sorgho | BF33: Maïs | BG33: parfumé | BI33: Non Parfumé | BJ33: Indien ordinaire | BK33: Local | BL33: Local | BM33: Importé | BN33: Souna | BO33: Sorgho | BP33: Maïs | BQ33: parfumé | BS33: Non Parfumé | BT33: Indien ordinaire | BU33: Local | BV33: Local | BW33: Importé | BX33: Souna | BY33: Sorgho | BZ33: Maïs | CA33: parfumé | CC33: Non Parfumé | CD33: Indien ordinaire | CE33: Local | CF33: Local | CG33: Importé | CH33: Souna | CI33: Sorgho | CJ33: Maïs | CK33: parfumé | CM33: Non Parfumé | CN33: Indien ordinaire | CO33: Local | CP33: Local | CQ33: Importé | CR33: Souna | CS33: Sorgho | CT33: Maïs | CU33: parfumé | CW33: Non Parfumé | CX33: Indien ordinaire | CY33: Local | CZ33: Local | DA33: Importé | DB33: Souna | DC33: Sorgho | DD33: Maïs | DE33: parfumé | DG33: Non Parfumé | DH33: Indien ordinaire | DI33: Local | DJ33: Local | DK33: Importé | DL33: Souna | DM33: Sorgho | DN33: Maïs | DO33: parfumé | DQ33: Non Parfumé | DR33: Indien ordinaire | DS33: Local | DT33: Local | DU33: Importé | DV33: Souna | DW33: Sorgho | DX33: Maïs | DY33: parfumé | EA33: Non Parfumé | EB33: Indien ordinaire | EC33: Local
A34: 40634 | B34: 259 | C34: 407 | D34: 197 | E34: 207 | F34: 203 | G34: 406 | H34: 351 | I34: 296 | J34: 281 | K34: 284 | S34: Luxe | T34: Ordinaire | AC34: Luxe | AD34: Ordinaire | AM34: Luxe | AN34: Ordinaire | AW34: Luxe | AX34: Ordinaire | BG34: Luxe | BH34: Ordinaire | BQ34: Luxe | BR34: Ordinaire | CA34: Luxe | CB34: Ordinaire | CK34: Luxe | CL34: Ordinaire | CU34: Luxe | CV34: Ordinaire | DE34: Luxe | DF34: Ordinaire | DO34: Luxe | DP34: Ordinaire | DY34: Luxe | DZ34: Ordinaire
A35: 40664 | B35: 231 | C35: 352 | D35: 211 | E35: 222 | F35: 211 | G35: 406 | H35: 336 | I35: 298 | J35: 286 | K35: 287 | O35: 350 | P35: 225 | Q35: 231.25 | R35: 212.5 | S35: 400 | T35: 350 | U35: 250 | V35: 250 | W35: 256.25 | X35: 300 | Y35: 350 | Z35: 200 | AA35: 225 | AB35: 212.5 | AC35: 400 | AD35: 350 | AE35: 250 | AF35: 250 | AG35: 250 | AH35: 300 | AI35: 350 | AJ35: 216.66667 | AK35: 233.33333 | AL35: 225 | AM35: 400 | AN35: 350 | AO35: 266.66667 | AP35: 250 | AQ35: 266.66667 | AR35: 300 | AS35: 400 | AT35: 218.75 | AU35: 225 | AV35: 218.75 | AW35: 400 | AX35: 350 | AY35: 275 | AZ35: 250 | BA35: 262.5 | BB35: 312.5 | BC35: 400 | BD35: 200 | BE35: 237.5 | BF35: 206.25 | BG35: 400 | BH35: 350 | BI35: 262.5 | BJ35: 250 | BK35: 268.75 | BL35: 381.25 | BN35: 218.75 | BO35: 237.5 | BP35: 206.25 | BQ35: 400 | BR35: 350 | BS35: 268.75 | BT35: 256.25 | BU35: 262.5 | BV35: 475 | BW35: 566.66667 | BX35: 212.5 | BY35: 231.25 | BZ35: 212.5 | CA35: 400 | CB35: 350 | CC35: 268.75 | CD35: 262.5 | CE35: 275 | CF35: 368.75 | CG35: 475 | CH35: 218.75 | CI35: 237.5 | CJ35: 218.75 | CK35: 400 | CL35: 350 | CM35: 275 | CN35: 275 | CO35: 275 | CQ35: 483.33333 | CR35: 225 | CS35: 233.33333 | CT35: 208.33333 | CU35: 400 | CV35: 350 | CW35: 291.66667 | CY35: 258.33333 | DA35: 360 | DB35: 210 | DC35: 225 | DD35: 215 | DE35: 400 | DF35: 350 | DG35: 300 | DH35: 312.5 | DI35: 285 | DK35: 400 | DL35: 216.66667 | DM35: 225 | DN35: 216.66667 | DO35: 400 | DP35: 350 | DQ35: 300 | DR35: 300 | DS35: 291.66667 | DU35: 425 | DV35: 212.5 | DW35: 225 | DX35: 218.75 | DY35: 400 | DZ35: 350 | EA35: 300 | EB35: 300 | EC35: 300
A36: 40695 | B36: 240 | C36: 388 | D36: 213 | E36: 222 | F36: 217 | G36: 403 | H36: 336 | I36: 298 | J36: 300 | K36: 286 | O36: 337.5 | P36: 187.5 | Q36: 200 | R36: 200 | S36: 400 | T36: 331.25 | U36: 253.75 | W36: 250 | X36: 250 | Y36: 312.5 | Z36: 200 | AA36: 187.5 | AB36: 200 | AC36: 400 | AD36: 350 | AE36: 257.5 | AG36: 250 | AH36: 275 | AI36: 350 | AJ36: 191.66667 | AK36: 191.66667 | AL36: 200 | AM36: 400 | AN36: 341.66667 | AO36: 253.33333 | AQ36: 250 | AR36: 293.75 | AS36: 325 | AT36: 200 | AU36: 200 | AV36: 200 | AW36: 400 | AX36: 325 | AY36: 250 | BA36: 250 | BB36: 293.75 | BD36: 193.75 | BE36: 200 | BF36: 200 | BG36: 400 | BH36: 331.25 | BI36: 256.25 | BK36: 250 | BL36: 400 | BN36: 200 | BO36: 193.75 | BP36: 200 | BQ36: 400 | BR36: 325 | BS36: 250 | BU36: 250 | BV36: 443.75 | BW36: 566.66667 | BX36: 200 | BY36: 200 | BZ36: 200 | CA36: 400 | CB36: 331.25 | CC36: 262.5 | CD36: - | CE36: 250 | CF36: 425 | CG36: 487.5 | CH36: 200 | CI36: 200 | CJ36: 200 | CK36: 400 | CL36: 331.25 | CM36: 275 | CN36: - | CO36: - | CP36: 475 | CQ36: 466.66667 | CR36: 173.33333 | CS36: 200 | CT36: 200 | CU36: 400 | CV36: 341.66667 | CW36: 275 | DA36: 320 | DB36: 160 | DC36: 200 | DD36: 200 | DE36: 400 | DF36: 325 | DG36: 275 | DK36: 383.33333 | DL36: 178.33333 | DM36: 175 | DN36: 200 | DO36: 400 | DP36: 333.33333 | DQ36: 275 | DU36: 412.5 | DV36: 160 | DW36: 185 | DX36: 200 | DY36: 400 | DZ36: 325 | EA36: 278.75
